Workbook
Name Aggr_2021: Intentionally_produced_MPs!$J$63
Name In_EU_2018: Agriculture!$E$4
Name In_EU_2019: Agriculture!$E$5
Name IN_NL_2018_high: Agriculture!$E$23
Name In_NL_2018_low: Agriculture!$E$22
Name IN_NL_2019_high: Agriculture!$E$25
Name IN_NL_2019_low: Agriculture!$E$24
Name Intentional_Agr_EU_2020: Agriculture!$B$232
Name Intentional_Agr_NL_2020: Agriculture!$C$232
Name OECD_ref_2018: 'Input projections'!$B$40
Name OECD_ref_2019: 'Input projections'!$B$41
Name OIL_GAS_2020: Intentionally_produced_MPs!$J$65
Name POP_coef_2020: Intentionally_produced_MPs!$J$61
Name Synthetic_fraction: Clothing_update!#REF!

Sheet README
A1: Explanation of the sheets in this document
A2: Sheet name | B2: Description | D2: More detailed info
A3: Data Quality Indicators | B3: Descriptions of the scores of the data quality indicators | D3: Input values and transfer coefficient values are assigned a 'data quality indicator' for five categories. The indicator scores range from 1 (very good) to 4 (very poor). The table is adopted from Kawecki et al. (2019) can be used to assign the correct data quality indicator score to each input and transfer coefficient value.
A4: Materials | B4: All polymers that are considered in this study
A5: Input_EU | B5: Input data in kton per year at EU scale for the input compartments | D5: The 13 input compartments are: Packaging, Building and Construction, Automotive (product sector), EEE (product sector), Agriculture, Clothing (product sector), Household textiles (product sector), Technical textiles, Other plastic products (product sector), Paint, Intentionally produced microparticles, Domestic primary plastic production, Import of primary plastics
A6: Input_NL | B6: Input data in kton per year at NL scale for the input compartments | D6: The 13 input compartments are: Packaging, Building and Construction, Automotive (product sector), EEE (product sector), Agriculture, Clothing (product sector), Household textiles (product sector), Technical textiles, Other plastic products (product sector), Paint, Intentionally produced microparticles, Domestic primary plastic production, Import of primary plastics
A7: Transfer coefficients | B7: Transfer coefficients (0 - 1) that describe the distribution of microplastics from one to another compartment between compartments | D7: Plastics are transferred from one compartment to the other. How the plastics are distributed amongst the next compartments is defined by the transfer coefficients. The sum of the transfer coefficients for each compartment must equal 1 (mass balance: no plastics are lost)
A8: Lifetimes_pairs | B8: The lifetime categories that are assgined to each stock compartment | D8: Plastic producs have a lifetime, which refers to the length of time for which it is estimated that the product will be used by the consumer. This table links each stock compartment to a lifetime category.
A9: Lifetimes | B9: The lifetime (or discarding) funtion for each lifetime category (for the first 200 years) | D9: The fraction of the plastic product that flows to the next compartment(s) in the first 200 years after the product is consumed.
A10: Compartments | B10: List of all compartments included in this study | D10: x
A11: Compartments_Kawecki&Nowack19 | B11: List of all compartments included in the study from Kawecki and Nowack (2019) | D11: x
A12: Compartments_Added_by_RIVM_TNO | B12: List of all compartments that were not inlcuded in the study from Kawecki and Nowack (2019) and that have been added by the RIVM/TNO team in 2023 | D12: x
A13: Check_Compartments | B13: Check sheet | D13: Checks all input compartments. Checks if input compartments only have an outgoing flow (from). Checks if flow compartments have and in- and outgoing flow (from & to). Checks if sink compartments only have an ingoing flow (to).
A14: Textiles | B14: Calculation of the input and transfer coefficients of textile related compartments | D14: The cells that are highlighted in green contain the values that are used in the 'Input_EU', 'Input_NL', or 'Transfer coefficient' sheet.
A15: Intentionally produced microparticles | B15: Calculation of the input and transfer coefficients of intentionally produced microparticle related compartments | D15: The cells that are highlighted in green contain the values that are used in the 'Input_EU', 'Input_NL', or 'Transfer coefficient' sheet.
A16: Packaging | B16: Calculation of the input and transfer coefficients of packaging related compartments | D16: The cells that are highlighted in green contain the values that are used in the 'Input_EU', 'Input_NL', or 'Transfer coefficient' sheet.
A19: Sources used in this document | B19: Full citation
A20: Kawecki & Nowack (2019) | B20: Kawecki, D., & Nowack, B. (2019). Polymer-specific modeling of the environmental emissions of seven commodity plastics as macro-and microplastics. Environmental science & technology, 53(16), 9664-9676.
A21: Kawecki et al. (2021) | B21: Kawecki, D., Wu, Q., Gonçalves, J. S., & Nowack, B. (2021). Polymer-specific dynamic probabilistic material flow analysis of seven polymers in Europe from 1950 to 2016. Resources, Conservation and Recycling, 173, 105733.

Sheet Version
A1: Date | B1: Adjustment
A2: 28-1-2025 | B2: Added Clothing_update tab

Sheet Data Quality Indicators
A1: Category | B1: Abbreviation | C1: Very Good | D1: Good | E1: Poor | F1: Very Poor
A2: Score | C2: DQIS = 1 | D2: DQIS = 2 | E2: DQIS = 3 | F2: DQIS = 4
A3: Geographical representativeness | B3: Geo (NL or EU) | C3: Same region (for EU: EU28 and EU28+2 qualify, for NL: CBS data qualifies) | D3: Socioeconomically similar region (i.e. Europe vs. Switzerland) | E3: Socioeconomically different region (i.e. USA vs. Europe) | F3: Socioeconomically very different region (i.e. World vs. Europe)
A4: Temporal representativeness | B4: Temp | C4: Same year (2019 reference year) | D4: 1-3 year difference (2016-2018, 2020-2022) | E4: 4-10 year difference (2009-2015) | F4: More than 10 year difference (prior to 2009)
A5: Material representativeness | B5: Mat | C5: Same polymer | D5: Same polymer datum corrected with data for all polymers | E5: Data for a different polymer, or for plastic as a whole, or including similar materials | F5: Including non-similar materials
A6: (Technical) Completeness | B6: Tech | C6: Includes all relevant processes/flows | D6: Includes main processes/flows | E6: Partially including main processes/flows | F6: Important processes/flows are missing
A7: Source reliability | B7: Rel | C7: Official report /peer reviewed documentation | D7: Martket reports and other reports / Public databases | E7: Qualified estimate | F7: Non-qualified estimate

Sheet Materials
A1: Name
A2: LDPE
A3: HDPE
A4: PP
A5: PS
A6: EPS
A7: PVC
A8: PET
A9: RUBBER
A10: PUR
A11: ABS
A12: PA
... A16: Acryl

Sheet Input_NL
A1: Compartment | B1: Year | C1: Material | D1: Data (kt) | E1: Source | F1: Geo | G1: Temp | H1: Mat | I1: Tech | J1: Rel | K1: Spread | L1: Codes and comments
A2: =Agriculture!A47 -> Agriculture | B2: =Agriculture!C47 -> 2019 | C2: =Agriculture!D47 -> LDPE | D2: =Agriculture!E47 -> 40.881766 | E2: =Agriculture!F47 -> Combined from TNO Sieger Henke and Statistics - APE Europe [WWW Document], n.d. URL https://web.archive.org/web/20230930160250/https://apeeurope.eu/statistics/ (accessed 3.27.24). Using 6.7% conversion to NL | F2: 2 | G2: 1 | H2: 2 | I2: 1 | J2: 2 | K2: =IF( OR( ISBLANK(F2),ISBLANK(G2), ISBLANK(H2), ISBLANK(I2), ISBLANK(J2) ), "", 1.5*SQRT( EXP(2.21*(F2-1)) + EXP(2.21*(G2-1)) + EXP(2.21*(H2-1)) + EXP(2.21*(I2-1)) + EXP(2.21*J2) )/100*2.45 ) -> 0.37356464 | L2: =Agriculture!M47 -> Estimation using 6.7% conversion to NL (https://ec.europa.eu/eurostat/databrowser/bookmark/ad869a47-4196-4282-b054-0a75caf9373f?lang=en)
A3: =Agriculture!A37 -> Agriculture | B3: =Agriculture!C37 -> 2018 | C3: =Agriculture!D37 -> LDPE | D3: =Agriculture!E37 -> 40.723724 | E3: =Agriculture!F37 -> Combined from TNO Sieger Henke and Statistics - APE Europe [WWW Document], n.d. URL https://web.archive.org/web/20230930160250/https://apeeurope.eu/statistics/ (accessed 3.27.24). Using 6.7% conversion to NL | F3: 2 | G3: 1 | H3: 2 | I3: 1 | J3: 2 | K3: =IF( OR( ISBLANK(F3),ISBLANK(G3), ISBLANK(H3), ISBLANK(I3), ISBLANK(J3) ), "", 1.5*SQRT( EXP(2.21*(F3-1)) + EXP(2.21*(G3-1)) + EXP(2.21*(H3-1)) + EXP(2.21*(I3-1)) + EXP(2.21*J3) )/100*2.45 ) -> 0.37356464 | L3: =Agriculture!M37 -> Estimation using 6.7% conversion to NL (https://ec.europa.eu/eurostat/databrowser/bookmark/ad869a47-4196-4282-b054-0a75caf9373f?lang=en)
A4: =Agriculture!A42 -> Agriculture | B4: =Agriculture!C42 -> 2019 | C4: =Agriculture!D42 -> LDPE | D4: =Agriculture!E42 -> 20.034144 | E4: =Agriculture!F42 -> Combined from TNO Sieger Henke and Statistics - APE Europe [WWW Document], n.d. URL https://web.archive.org/web/20230930160250/https://apeeurope.eu/statistics/ (accessed 3.27.24). Using 3.36% conversion to NL | F4: 2 | G4: 1 | H4: 2 | I4: 1 | J4: 2 | K4: =IF( OR( ISBLANK(F4),ISBLANK(G4), ISBLANK(H4), ISBLANK(I4), ISBLANK(J4) ), "", 1.5*SQRT( EXP(2.21*(F4-1)) + EXP(2.21*(G4-1)) + EXP(2.21*(H4-1)) + EXP(2.21*(I4-1)) + EXP(2.21*J4) )/100*2.45 ) -> 0.37356464 | L4: =Agriculture!M42 -> Estimation using 3.36% conversion to NL (Plastics Europe, 2014)
A5: =Agriculture!A32 -> Agriculture | B5: =Agriculture!C32 -> 2018 | C5: =Agriculture!D32 -> LDPE | D5: =Agriculture!E32 -> 19.955032 | E5: =Agriculture!F32 -> Combined from TNO Sieger Henke and Statistics - APE Europe [WWW Document], n.d. URL https://web.archive.org/web/20230930160250/https://apeeurope.eu/statistics/ (accessed 3.27.24). Using 3.36% conversion to NL | F5: 2 | G5: 1 | H5: 2 | I5: 1 | J5: 2 | K5: =IF( OR( ISBLANK(F5),ISBLANK(G5), ISBLANK(H5), ISBLANK(I5), ISBLANK(J5) ), "", 1.5*SQRT( EXP(2.21*(F5-1)) + EXP(2.21*(G5-1)) + EXP(2.21*(H5-1)) + EXP(2.21*(I5-1)) + EXP(2.21*J5) )/100*2.45 ) -> 0.37356464 | L5: =Agriculture!M32 -> Estimation using 3.36% conversion to NL (Plastics Europe, 2014)
A6: =Agriculture!A44 -> Agriculture | B6: =Agriculture!C44 -> 2019 | C6: =Agriculture!D44 -> PVC | D6: =Agriculture!E44 -> 4.7909395 | E6: =Agriculture!F44 -> Combined from TNO Sieger Henke and Statistics - APE Europe [WWW Document], n.d. URL https://web.archive.org/web/20230930160250/https://apeeurope.eu/statistics/ (accessed 3.27.24). Using 6.7% conversion to NL | F6: 2 | G6: 1 | H6: 2 | I6: 1 | J6: 2 | K6: =IF( OR( ISBLANK(F6),ISBLANK(G6), ISBLANK(H6), ISBLANK(I6), ISBLANK(J6) ), "", 1.5*SQRT( EXP(2.21*(F6-1)) + EXP(2.21*(G6-1)) + EXP(2.21*(H6-1)) + EXP(2.21*(I6-1)) + EXP(2.21*J6) )/100*2.45 ) -> 0.37356464 | L6: =Agriculture!M44 -> Estimation using 6.7% conversion to NL (https://ec.europa.eu/eurostat/databrowser/bookmark/ad869a47-4196-4282-b054-0a75caf9373f?lang=en)
A7: =Agriculture!A34 -> Agriculture | B7: =Agriculture!C34 -> 2018 | C7: =Agriculture!D34 -> PVC | D7: =Agriculture!E34 -> 4.7724185 | E7: =Agriculture!F34 -> Combined from TNO Sieger Henke and Statistics - APE Europe [WWW Document], n.d. URL https://web.archive.org/web/20230930160250/https://apeeurope.eu/statistics/ (accessed 3.27.24). Using 6.7% conversion to NL | F7: 2 | G7: 1 | H7: 2 | I7: 1 | J7: 2 | K7: =IF( OR( ISBLANK(F7),ISBLANK(G7), ISBLANK(H7), ISBLANK(I7), ISBLANK(J7) ), "", 1.5*SQRT( EXP(2.21*(F7-1)) + EXP(2.21*(G7-1)) + EXP(2.21*(H7-1)) + EXP(2.21*(I7-1)) + EXP(2.21*J7) )/100*2.45 ) -> 0.37356464 | L7: =Agriculture!M34 -> Estimation using 6.7% conversion to NL (https://ec.europa.eu/eurostat/databrowser/bookmark/ad869a47-4196-4282-b054-0a75caf9373f?lang=en)
A8: =Agriculture!A39 -> Agriculture | B8: =Agriculture!C39 -> 2019 | C8: =Agriculture!D39 -> PVC | D8: =Agriculture!E39 -> 2.3478039 | E8: =Agriculture!F39 -> Combined from TNO Sieger Henke and Statistics - APE Europe [WWW Document], n.d. URL https://web.archive.org/web/20230930160250/https://apeeurope.eu/statistics/ (accessed 3.27.24). Using 3.36% conversion to NL | F8: 2 | G8: 1 | H8: 2 | I8: 1 | J8: 2 | K8: =IF( OR( ISBLANK(F8),ISBLANK(G8), ISBLANK(H8), ISBLANK(I8), ISBLANK(J8) ), "", 1.5*SQRT( EXP(2.21*(F8-1)) + EXP(2.21*(G8-1)) + EXP(2.21*(H8-1)) + EXP(2.21*(I8-1)) + EXP(2.21*J8) )/100*2.45 ) -> 0.37356464 | L8: =Agriculture!M39 -> Estimation using 3.36% conversion to NL (Plastics Europe, 2014)
A9: =Agriculture!A29 -> Agriculture | B9: =Agriculture!C29 -> 2018 | C9: =Agriculture!D29 -> PVC | D9: =Agriculture!E29 -> 2.3385328 | E9: =Agriculture!F29 -> Combined from TNO Sieger Henke and Statistics - APE Europe [WWW Document], n.d. URL https://web.archive.org/web/20230930160250/https://apeeurope.eu/statistics/ (accessed 3.27.24). Using 3.36% conversion to NL | F9: 2 | G9: 1 | H9: 2 | I9: 1 | J9: 2 | K9: =IF( OR( ISBLANK(F9),ISBLANK(G9), ISBLANK(H9), ISBLANK(I9), ISBLANK(J9) ), "", 1.5*SQRT( EXP(2.21*(F9-1)) + EXP(2.21*(G9-1)) + EXP(2.21*(H9-1)) + EXP(2.21*(I9-1)) + EXP(2.21*J9) )/100*2.45 ) -> 0.37356464 | L9: =Agriculture!M29 -> Estimation using 3.36% conversion to NL (Plastics Europe, 2014)
A10: =Agriculture!A48 -> Agriculture | B10: =Agriculture!C48 -> 2019 | C10: =Agriculture!D48 -> HDPE | D10: =Agriculture!E48 -> 0.57869314 | E10: =Agriculture!F48 -> Combined from TNO Sieger Henke and Statistics - APE Europe [WWW Document], n.d. URL https://web.archive.org/web/20230930160250/https://apeeurope.eu/statistics/ (accessed 3.27.24). Using 6.7% conversion to NL | F10: 2 | G10: 1 | H10: 2 | I10: 1 | J10: 2 | K10: =IF( OR( ISBLANK(F10),ISBLANK(G10), ISBLANK(H10), ISBLANK(I10), ISBLANK(J10) ), "", 1.5*SQRT( EXP(2.21*(F10-1)) + EXP(2.21*(G10-1)) + EXP(2.21*(H10-1)) + EXP(2.21*(I10-1)) + EXP(2.21*J10) )/100*2.45 ) -> 0.37356464 | L10: =Agriculture!M48 -> Estimation using 6.7% conversion to NL (https://ec.europa.eu/eurostat/databrowser/bookmark/ad869a47-4196-4282-b054-0a75caf9373f?lang=en)
A11: =Agriculture!A38 -> Agriculture | B11: =Agriculture!C38 -> 2018 | C11: =Agriculture!D38 -> HDPE | D11: =Agriculture!E38 -> 0.576456 | E11: =Agriculture!F38 -> Combined from TNO Sieger Henke and Statistics - APE Europe [WWW Document], n.d. URL https://web.archive.org/web/20230930160250/https://apeeurope.eu/statistics/ (accessed 3.27.24). Using 6.7% conversion to NL | F11: 2 | G11: 1 | H11: 2 | I11: 1 | J11: 2 | K11: =IF( OR( ISBLANK(F11),ISBLANK(G11), ISBLANK(H11), ISBLANK(I11), ISBLANK(J11) ), "", 1.5*SQRT( EXP(2.21*(F11-1)) + EXP(2.21*(G11-1)) + EXP(2.21*(H11-1)) + EXP(2.21*(I11-1)) + EXP(2.21*J11) )/100*2.45 ) -> 0.37356464 | L11: =Agriculture!M38 -> Estimation using 6.7% conversion to NL (https://ec.europa.eu/eurostat/databrowser/bookmark/ad869a47-4196-4282-b054-0a75caf9373f?lang=en)
A12: =Agriculture!A43 -> Agriculture | B12: =Agriculture!C43 -> 2019 | C12: =Agriculture!D43 -> HDPE | D12: =Agriculture!E43 -> 0.28358906 | E12: =Agriculture!F43 -> Combined from TNO Sieger Henke and Statistics - APE Europe [WWW Document], n.d. URL https://web.archive.org/web/20230930160250/https://apeeurope.eu/statistics/ (accessed 3.27.24). Using 3.36% conversion to NL | F12: 2 | G12: 1 | H12: 2 | I12: 1 | J12: 2 | K12: =IF( OR( ISBLANK(F12),ISBLANK(G12), ISBLANK(H12), ISBLANK(I12), ISBLANK(J12) ), "", 1.5*SQRT( EXP(2.21*(F12-1)) + EXP(2.21*(G12-1)) + EXP(2.21*(H12-1)) + EXP(2.21*(I12-1)) + EXP(2.21*J12) )/100*2.45 ) -> 0.37356464 | L12: =Agriculture!M43 -> Estimation using 3.36% conversion to NL (Plastics Europe, 2014)
A13: =Agriculture!A33 -> Agriculture | B13: =Agriculture!C33 -> 2018 | C13: =Agriculture!D33 -> HDPE | D13: =Agriculture!E33 -> 0.2824692 | E13: =Agriculture!F33 -> Combined from TNO Sieger Henke and Statistics - APE Europe [WWW Document], n.d. URL https://web.archive.org/web/20230930160250/https://apeeurope.eu/statistics/ (accessed 3.27.24). Using 3.36% conversion to NL | F13: 2 | G13: 1 | H13: 2 | I13: 1 | J13: 2 | K13: =IF( OR( ISBLANK(F13),ISBLANK(G13), ISBLANK(H13), ISBLANK(I13), ISBLANK(J13) ), "", 1.5*SQRT( EXP(2.21*(F13-1)) + EXP(2.21*(G13-1)) + EXP(2.21*(H13-1)) + EXP(2.21*(I13-1)) + EXP(2.21*J13) )/100*2.45 ) -> 0.37356464 | L13: =Agriculture!M33 -> Estimation using 3.36% conversion to NL (Plastics Europe, 2014)
A14: =Agriculture!A45 -> Agriculture | B14: =Agriculture!C45 -> 2019 | C14: =Agriculture!D45 -> PS | D14: =Agriculture!E45 -> 0.22754023 | E14: =Agriculture!F45 -> Combined from TNO Sieger Henke and Statistics - APE Europe [WWW Document], n.d. URL https://web.archive.org/web/20230930160250/https://apeeurope.eu/statistics/ (accessed 3.27.24). Using 6.7% conversion to NL | F14: 2 | G14: 1 | H14: 2 | I14: 1 | J14: 2 | K14: =IF( OR( ISBLANK(F14),ISBLANK(G14), ISBLANK(H14), ISBLANK(I14), ISBLANK(J14) ), "", 1.5*SQRT( EXP(2.21*(F14-1)) + EXP(2.21*(G14-1)) + EXP(2.21*(H14-1)) + EXP(2.21*(I14-1)) + EXP(2.21*J14) )/100*2.45 ) -> 0.37356464 | L14: =Agriculture!M45 -> Estimation using 6.7% conversion to NL (https://ec.europa.eu/eurostat/databrowser/bookmark/ad869a47-4196-4282-b054-0a75caf9373f?lang=en)
A15: =Agriculture!A46 -> Agriculture | B15: =Agriculture!C46 -> 2019 | C15: =Agriculture!D46 -> PP | D15: =Agriculture!E46 -> 0.22754023 | E15: =Agriculture!F46 -> Combined from TNO Sieger Henke and Statistics - APE Europe [WWW Document], n.d. URL https://web.archive.org/web/20230930160250/https://apeeurope.eu/statistics/ (accessed 3.27.24). Using 6.7% conversion to NL | F15: 2 | G15: 1 | H15: 2 | I15: 1 | J15: 2 | K15: =IF( OR( ISBLANK(F15),ISBLANK(G15), ISBLANK(H15), ISBLANK(I15), ISBLANK(J15) ), "", 1.5*SQRT( EXP(2.21*(F15-1)) + EXP(2.21*(G15-1)) + EXP(2.21*(H15-1)) + EXP(2.21*(I15-1)) + EXP(2.21*J15) )/100*2.45 ) -> 0.37356464 | L15: =Agriculture!M46 -> Estimation using 6.7% conversion to NL (https://ec.europa.eu/eurostat/databrowser/bookmark/ad869a47-4196-4282-b054-0a75caf9373f?lang=en)
A16: =Agriculture!A35 -> Agriculture | B16: =Agriculture!C35 -> 2018 | C16: =Agriculture!D35 -> PS | D16: =Agriculture!E35 -> 0.2266606 | E16: =Agriculture!F35 -> Combined from TNO Sieger Henke and Statistics - APE Europe [WWW Document], n.d. URL https://web.archive.org/web/20230930160250/https://apeeurope.eu/statistics/ (accessed 3.27.24). Using 6.7% conversion to NL | F16: 2 | G16: 1 | H16: 2 | I16: 1 | J16: 2 | K16: =IF( OR( ISBLANK(F16),ISBLANK(G16), ISBLANK(H16), ISBLANK(I16), ISBLANK(J16) ), "", 1.5*SQRT( EXP(2.21*(F16-1)) + EXP(2.21*(G16-1)) + EXP(2.21*(H16-1)) + EXP(2.21*(I16-1)) + EXP(2.21*J16) )/100*2.45 ) -> 0.37356464 | L16: =Agriculture!M35 -> Estimation using 6.7% conversion to NL (https://ec.europa.eu/eurostat/databrowser/bookmark/ad869a47-4196-4282-b054-0a75caf9373f?lang=en)
A17: =Agriculture!A36 -> Agriculture | B17: =Agriculture!C36 -> 2018 | C17: =Agriculture!D36 -> PP | D17: =Agriculture!E36 -> 0.2266606 | E17: =Agriculture!F36 -> Combined from TNO Sieger Henke and Statistics - APE Europe [WWW Document], n.d. URL https://web.archive.org/web/20230930160250/https://apeeurope.eu/statistics/ (accessed 3.27.24). Using 6.7% conversion to NL | F17: 2 | G17: 1 | H17: 2 | I17: 1 | J17: 2 | K17: =IF( OR( ISBLANK(F17),ISBLANK(G17), ISBLANK(H17), ISBLANK(I17), ISBLANK(J17) ), "", 1.5*SQRT( EXP(2.21*(F17-1)) + EXP(2.21*(G17-1)) + EXP(2.21*(H17-1)) + EXP(2.21*(I17-1)) + EXP(2.21*J17) )/100*2.45 ) -> 0.37356464 | L17: =Agriculture!M36 -> Estimation using 6.7% conversion to NL (https://ec.europa.eu/eurostat/databrowser/bookmark/ad869a47-4196-4282-b054-0a75caf9373f?lang=en)
A18: =Agriculture!A40 -> Agriculture | B18: =Agriculture!C40 -> 2019 | C18: =Agriculture!D40 -> PS | D18: =Agriculture!E40 -> 0.11150628 | E18: =Agriculture!F40 -> Combined from TNO Sieger Henke and Statistics - APE Europe [WWW Document], n.d. URL https://web.archive.org/web/20230930160250/https://apeeurope.eu/statistics/ (accessed 3.27.24). Using 3.36% conversion to NL | F18: 2 | G18: 1 | H18: 2 | I18: 1 | J18: 2 | K18: =IF( OR( ISBLANK(F18),ISBLANK(G18), ISBLANK(H18), ISBLANK(I18), ISBLANK(J18) ), "", 1.5*SQRT( EXP(2.21*(F18-1)) + EXP(2.21*(G18-1)) + EXP(2.21*(H18-1)) + EXP(2.21*(I18-1)) + EXP(2.21*J18) )/100*2.45 ) -> 0.37356464 | L18: =Agriculture!M40 -> Estimation using 3.36% conversion to NL (Plastics Europe, 2014)
A19: =Agriculture!A41 -> Agriculture | B19: =Agriculture!C41 -> 2019 | C19: =Agriculture!D41 -> PP | D19: =Agriculture!E41 -> 0.11150628 | E19: =Agriculture!F41 -> Combined from TNO Sieger Henke and Statistics - APE Europe [WWW Document], n.d. URL https://web.archive.org/web/20230930160250/https://apeeurope.eu/statistics/ (accessed 3.27.24). Using 3.36% conversion to NL | F19: 2 | G19: 1 | H19: 2 | I19: 1 | J19: 2 | K19: =IF( OR( ISBLANK(F19),ISBLANK(G19), ISBLANK(H19), ISBLANK(I19), ISBLANK(J19) ), "", 1.5*SQRT( EXP(2.21*(F19-1)) + EXP(2.21*(G19-1)) + EXP(2.21*(H19-1)) + EXP(2.21*(I19-1)) + EXP(2.21*J19) )/100*2.45 ) -> 0.37356464 | L19: =Agriculture!M41 -> Estimation using 3.36% conversion to NL (Plastics Europe, 2014)
A20: =Agriculture!A30 -> Agriculture | B20: =Agriculture!C30 -> 2018 | C20: =Agriculture!D30 -> PS | D20: =Agriculture!E30 -> 0.11106596 | E20: =Agriculture!F30 -> Combined from TNO Sieger Henke and Statistics - APE Europe [WWW Document], n.d. URL https://web.archive.org/web/20230930160250/https://apeeurope.eu/statistics/ (accessed 3.27.24). Using 3.36% conversion to NL | F20: 2 | G20: 1 | H20: 2 | I20: 1 | J20: 2 | K20: =IF( OR( ISBLANK(F20),ISBLANK(G20), ISBLANK(H20), ISBLANK(I20), ISBLANK(J20) ), "", 1.5*SQRT( EXP(2.21*(F20-1)) + EXP(2.21*(G20-1)) + EXP(2.21*(H20-1)) + EXP(2.21*(I20-1)) + EXP(2.21*J20) )/100*2.45 ) -> 0.37356464 | L20: =Agriculture!M30 -> Estimation using 3.36% conversion to NL (Plastics Europe, 2014)
A21: =Agriculture!A31 -> Agriculture | B21: =Agriculture!C31 -> 2018 | C21: =Agriculture!D31 -> PP | D21: =Agriculture!E31 -> 0.11106596 | E21: =Agriculture!F31 -> Combined from TNO Sieger Henke and Statistics - APE Europe [WWW Document], n.d. URL https://web.archive.org/web/20230930160250/https://apeeurope.eu/statistics/ (accessed 3.27.24). Using 3.36% conversion to NL | F21: 2 | G21: 1 | H21: 2 | I21: 1 | J21: 2 | K21: =IF( OR( ISBLANK(F21),ISBLANK(G21), ISBLANK(H21), ISBLANK(I21), ISBLANK(J21) ), "", 1.5*SQRT( EXP(2.21*(F21-1)) + EXP(2.21*(G21-1)) + EXP(2.21*(H21-1)) + EXP(2.21*(I21-1)) + EXP(2.21*J21) )/100*2.45 ) -> 0.37356464 | L21: =Agriculture!M31 -> Estimation using 3.36% conversion to NL (Plastics Europe, 2014)
A22: Clothing (product sector) | B22: 2019 | C22: PET | D22: 22.7689 | E22: Information combined from: CBS (2019) and Synthetic Fibers (polymerdatabase.com) | F22: 1 | G22: 1 | H22: 2 | I22: 3 | J22: 2 | K22: =IF( OR( ISBLANK(F22),ISBLANK(G22), ISBLANK(H22), ISBLANK(I22), ISBLANK(J22) ), "", 1.5*SQRT( EXP(2.21*(F22-1)) + EXP(2.21*(G22-1)) + EXP(2.21*(H22-1)) + EXP(2.21*(I22-1)) + EXP(2.21*J22) )/100*2.45 ) -> 0.48935256
A23: Clothing (product sector) | B23: 2019 | C23: PA | D23: 3.5484 | E23: Information combined from: CBS (2019) and Synthetic Fibers (polymerdatabase.com) | F23: 1 | G23: 1 | H23: 2 | I23: 3 | J23: 2 | K23: =IF( OR( ISBLANK(F23),ISBLANK(G23), ISBLANK(H23), ISBLANK(I23), ISBLANK(J23) ), "", 1.5*SQRT( EXP(2.21*(F23-1)) + EXP(2.21*(G23-1)) + EXP(2.21*(H23-1)) + EXP(2.21*(I23-1)) + EXP(2.21*J23) )/100*2.45 ) -> 0.48935256
A24: Clothing (product sector) | B24: 2019 | C24: Acryl | D24: 2.6613 | E24: Information combined from: CBS (2019) and Synthetic Fibers (polymerdatabase.com) | F24: 1 | G24: 1 | H24: 2 | I24: 3 | J24: 2 | K24: =IF( OR( ISBLANK(F24),ISBLANK(G24), ISBLANK(H24), ISBLANK(I24), ISBLANK(J24) ), "", 1.5*SQRT( EXP(2.21*(F24-1)) + EXP(2.21*(G24-1)) + EXP(2.21*(H24-1)) + EXP(2.21*(I24-1)) + EXP(2.21*J24) )/100*2.45 ) -> 0.48935256
A25: Clothing (product sector) | B25: 2019 | C25: HDPE | D25: 0.2957 | E25: Information combined from: CBS (2019) and Synthetic Fibers (polymerdatabase.com) | F25: 1 | G25: 1 | H25: 2 | I25: 3 | J25: 2 | K25: =IF( OR( ISBLANK(F25),ISBLANK(G25), ISBLANK(H25), ISBLANK(I25), ISBLANK(J25) ), "", 1.5*SQRT( EXP(2.21*(F25-1)) + EXP(2.21*(G25-1)) + EXP(2.21*(H25-1)) + EXP(2.21*(I25-1)) + EXP(2.21*J25) )/100*2.45 ) -> 0.48935256
A26: Clothing (product sector) | B26: 2019 | C26: PP | D26: 0.2957 | E26: Information combined from: CBS (2019) and Synthetic Fibers (polymerdatabase.com) | F26: 1 | G26: 1 | H26: 2 | I26: 3 | J26: 2 | K26: =IF( OR( ISBLANK(F26),ISBLANK(G26), ISBLANK(H26), ISBLANK(I26), ISBLANK(J26) ), "", 1.5*SQRT( EXP(2.21*(F26-1)) + EXP(2.21*(G26-1)) + EXP(2.21*(H26-1)) + EXP(2.21*(I26-1)) + EXP(2.21*J26) )/100*2.45 ) -> 0.48935256
A27: Domestic primary plastic production | B27: 1995 | C27: LDPE | D27: 1435 | E27: Statistics | Eurostat [WWW Document], n.d. URL https://ec.europa.eu/eurostat/databrowser/view/DS-056120__custom_5851448/default/table (accessed 2.15.24). | F27: 1 | G27: 1 | H27: 1 | I27: 2 | J27: 2 | K27: =IF( OR( ISBLANK(F27),ISBLANK(G27), ISBLANK(H27), ISBLANK(I27), ISBLANK(J27) ), "", 1.5*SQRT( EXP(2.21*(F27-1)) + EXP(2.21*(G27-1)) + EXP(2.21*(H27-1)) + EXP(2.21*(I27-1)) + EXP(2.21*J27) )/100*2.45 ) -> 0.35859414 | L27: See 'Pellets_trade' document and pellet_input.py in the Microsoft Teams folder 'Pellet'
A28: Domestic primary plastic production | B28: 1995 | C28: HDPE | D28: 290 | E28: Statistics | Eurostat [WWW Document], n.d. URL https://ec.europa.eu/eurostat/databrowser/view/DS-056120__custom_5851448/default/table (accessed 2.15.24). | F28: 1 | G28: 1 | H28: 1 | I28: 2 | J28: 2 | K28: =IF( OR( ISBLANK(F28),ISBLANK(G28), ISBLANK(H28), ISBLANK(I28), ISBLANK(J28) ), "", 1.5*SQRT( EXP(2.21*(F28-1)) + EXP(2.21*(G28-1)) + EXP(2.21*(H28-1)) + EXP(2.21*(I28-1)) + EXP(2.21*J28) )/100*2.45 ) -> 0.35859414 | L28: See 'Pellets_trade' document and pellet_input.py in the Microsoft Teams folder 'Pellet'
A29: Domestic primary plastic production | B29: 1995 | C29: PP | D29: 852 | E29: Statistics | Eurostat [WWW Document], n.d. URL https://ec.europa.eu/eurostat/databrowser/view/DS-056120__custom_5851448/default/table (accessed 2.15.24). | F29: 1 | G29: 1 | H29: 1 | I29: 2 | J29: 2 | K29: =IF( OR( ISBLANK(F29),ISBLANK(G29), ISBLANK(H29), ISBLANK(I29), ISBLANK(J29) ), "", 1.5*SQRT( EXP(2.21*(F29-1)) + EXP(2.21*(G29-1)) + EXP(2.21*(H29-1)) + EXP(2.21*(I29-1)) + EXP(2.21*J29) )/100*2.45 ) -> 0.35859414 | L29: See 'Pellets_trade' document and pellet_input.py in the Microsoft Teams folder 'Pellet'
A30: Domestic primary plastic production | B30: 1995 | C30: PS | D30: 4 | E30: Statistics | Eurostat [WWW Document], n.d. URL https://ec.europa.eu/eurostat/databrowser/view/DS-056120__custom_5851448/default/table (accessed 2.15.24). | F30: 1 | G30: 1 | H30: 1 | I30: 2 | J30: 2 | K30: =IF( OR( ISBLANK(F30),ISBLANK(G30), ISBLANK(H30), ISBLANK(I30), ISBLANK(J30) ), "", 1.5*SQRT( EXP(2.21*(F30-1)) + EXP(2.21*(G30-1)) + EXP(2.21*(H30-1)) + EXP(2.21*(I30-1)) + EXP(2.21*J30) )/100*2.45 ) -> 0.35859414 | L30: See 'Pellets_trade' document and pellet_input.py in the Microsoft Teams folder 'Pellet'
A31: Domestic primary plastic production | B31: 1995 | C31: EPS | D31: 191 | E31: Statistics | Eurostat [WWW Document], n.d. URL https://ec.europa.eu/eurostat/databrowser/view/DS-056120__custom_5851448/default/table (accessed 2.15.24). | F31: 1 | G31: 1 | H31: 1 | I31: 2 | J31: 2 | K31: =IF( OR( ISBLANK(F31),ISBLANK(G31), ISBLANK(H31), ISBLANK(I31), ISBLANK(J31) ), "", 1.5*SQRT( EXP(2.21*(F31-1)) + EXP(2.21*(G31-1)) + EXP(2.21*(H31-1)) + EXP(2.21*(I31-1)) + EXP(2.21*J31) )/100*2.45 ) -> 0.35859414 | L31: See 'Pellets_trade' document and pellet_input.py in the Microsoft Teams folder 'Pellet'
A32: Domestic primary plastic production | B32: 1995 | C32: PVC | D32: 610 | E32: Statistics | Eurostat [WWW Document], n.d. URL https://ec.europa.eu/eurostat/databrowser/view/DS-056120__custom_5851448/default/table (accessed 2.15.24). | F32: 1 | G32: 1 | H32: 1 | I32: 2 | J32: 2 | K32: =IF( OR( ISBLANK(F32),ISBLANK(G32), ISBLANK(H32), ISBLANK(I32), ISBLANK(J32) ), "", 1.5*SQRT( EXP(2.21*(F32-1)) + EXP(2.21*(G32-1)) + EXP(2.21*(H32-1)) + EXP(2.21*(I32-1)) + EXP(2.21*J32) )/100*2.45 ) -> 0.35859414 | L32: See 'Pellets_trade' document and pellet_input.py in the Microsoft Teams folder 'Pellet'
A33: Domestic primary plastic production | B33: 1995 | C33: PET | D33: 0 | E33: Statistics | Eurostat [WWW Document], n.d. URL https://ec.europa.eu/eurostat/databrowser/view/DS-056120__custom_5851448/default/table (accessed 2.15.24). | F33: 1 | G33: 1 | H33: 1 | I33: 2 | J33: 2 | K33: =IF( OR( ISBLANK(F33),ISBLANK(G33), ISBLANK(H33), ISBLANK(I33), ISBLANK(J33) ), "", 1.5*SQRT( EXP(2.21*(F33-1)) + EXP(2.21*(G33-1)) + EXP(2.21*(H33-1)) + EXP(2.21*(I33-1)) + EXP(2.21*J33) )/100*2.45 ) -> 0.35859414 | L33: See 'Pellets_trade' document and pellet_input.py in the Microsoft Teams folder 'Pellet'
A34: Domestic primary plastic production | B34: 1995 | C34: ABS | D34: 144 | E34: Statistics | Eurostat [WWW Document], n.d. URL https://ec.europa.eu/eurostat/databrowser/view/DS-056120__custom_5851448/default/table (accessed 2.15.24). | F34: 1 | G34: 1 | H34: 1 | I34: 2 | J34: 2 | K34: =IF( OR( ISBLANK(F34),ISBLANK(G34), ISBLANK(H34), ISBLANK(I34), ISBLANK(J34) ), "", 1.5*SQRT( EXP(2.21*(F34-1)) + EXP(2.21*(G34-1)) + EXP(2.21*(H34-1)) + EXP(2.21*(I34-1)) + EXP(2.21*J34) )/100*2.45 ) -> 0.35859414 | L34: See 'Pellets_trade' document and pellet_input.py in the Microsoft Teams folder 'Pellet'
A35: Domestic primary plastic production | B35: 1995 | C35: PC | D35: 337 | E35: Statistics | Eurostat [WWW Document], n.d. URL https://ec.europa.eu/eurostat/databrowser/view/DS-056120__custom_5851448/default/table (accessed 2.15.24). | F35: 1 | G35: 1 | H35: 1 | I35: 2 | J35: 2 | K35: =IF( OR( ISBLANK(F35),ISBLANK(G35), ISBLANK(H35), ISBLANK(I35), ISBLANK(J35) ), "", 1.5*SQRT( EXP(2.21*(F35-1)) + EXP(2.21*(G35-1)) + EXP(2.21*(H35-1)) + EXP(2.21*(I35-1)) + EXP(2.21*J35) )/100*2.45 ) -> 0.35859414 | L35: See 'Pellets_trade' document and pellet_input.py in the Microsoft Teams folder 'Pellet'
A36: Domestic primary plastic production | B36: 1995 | C36: PMMA | D36: 233 | E36: Statistics | Eurostat [WWW Document], n.d. URL https://ec.europa.eu/eurostat/databrowser/view/DS-056120__custom_5851448/default/table (accessed 2.15.24). | F36: 1 | G36: 1 | H36: 1 | I36: 2 | J36: 2 | K36: =IF( OR( ISBLANK(F36),ISBLANK(G36), ISBLANK(H36), ISBLANK(I36), ISBLANK(J36) ), "", 1.5*SQRT( EXP(2.21*(F36-1)) + EXP(2.21*(G36-1)) + EXP(2.21*(H36-1)) + EXP(2.21*(I36-1)) + EXP(2.21*J36) )/100*2.45 ) -> 0.35859414 | L36: See 'Pellets_trade' document and pellet_input.py in the Microsoft Teams folder 'Pellet'
A37: Domestic primary plastic production | B37: 1995 | C37: PA | D37: 200 | E37: Statistics | Eurostat [WWW Document], n.d. URL https://ec.europa.eu/eurostat/databrowser/view/DS-056120__custom_5851448/default/table (accessed 2.15.24). | F37: 1 | G37: 1 | H37: 1 | I37: 2 | J37: 2 | K37: =IF( OR( ISBLANK(F37),ISBLANK(G37), ISBLANK(H37), ISBLANK(I37), ISBLANK(J37) ), "", 1.5*SQRT( EXP(2.21*(F37-1)) + EXP(2.21*(G37-1)) + EXP(2.21*(H37-1)) + EXP(2.21*(I37-1)) + EXP(2.21*J37) )/100*2.45 ) -> 0.35859414 | L37: See 'Pellets_trade' document and pellet_input.py in the Microsoft Teams folder 'Pellet'
A38: Domestic primary plastic production | B38: 1995 | C38: PUR | D38: 98 | E38: Statistics | Eurostat [WWW Document], n.d. URL https://ec.europa.eu/eurostat/databrowser/view/DS-056120__custom_5851448/default/table (accessed 2.15.24). | F38: 1 | G38: 1 | H38: 1 | I38: 2 | J38: 2 | K38: =IF( OR( ISBLANK(F38),ISBLANK(G38), ISBLANK(H38), ISBLANK(I38), ISBLANK(J38) ), "", 1.5*SQRT( EXP(2.21*(F38-1)) + EXP(2.21*(G38-1)) + EXP(2.21*(H38-1)) + EXP(2.21*(I38-1)) + EXP(2.21*J38) )/100*2.45 ) -> 0.35859414 | L38: See 'Pellets_trade' document and pellet_input.py in the Microsoft Teams folder 'Pellet'
... A377: Domestic primary plastic production | B377: 2021 | C377: OTHER | D377: 2480 | E377: Statistics | Eurostat [WWW Document], n.d. URL https://ec.europa.eu/eurostat/databrowser/view/DS-056120__custom_5851448/default/table (accessed 2.15.24). | F377: 1 | G377: 1 | H377: 1 | I377: 2 | J377: 2 | K377: =IF( OR( ISBLANK(F377),ISBLANK(G377), ISBLANK(H377), ISBLANK(I377), ISBLANK(J377) ), "", 1.5*SQRT( EXP(2.21*(F377-1)) + EXP(2.21*(G377-1)) + EXP(2.21*(H377-1)) + EXP(2.21*(I377-1)) + EXP(2.21*J377) )/100*2.45 ) -> 0.35859414 | L377: See 'Pellets_trade' document and pellet_input.py in the Microsoft Teams folder 'Pellet'
A378: Household textiles (product sector) | B378: 2017 | C378: PET | D378: 30.108567 | E378: Information combined from: CBS (2019), Synthetic Fibers (polymerdatabase.com), and Kawecki & Nowack (2019) | F378: 1 | G378: 1 | H378: 2 | I378: 3 | J378: 2 | K378: =IF( OR( ISBLANK(F378),ISBLANK(G378), ISBLANK(H378), ISBLANK(I378), ISBLANK(J378) ), "", 1.5*SQRT( EXP(2.21*(F378-1)) + EXP(2.21*(G378-1)) + EXP(2.21*(H378-1)) + EXP(2.21*(I378-1)) + EXP(2.21*J378) )/100*2.45 ) -> 0.48935256
A379: Household textiles (product sector) | B379: 2017 | C379: HDPE | D379: 7.2763667 | E379: Information combined from: CBS (2019), Synthetic Fibers (polymerdatabase.com), and Kawecki & Nowack (2019) | F379: 1 | G379: 1 | H379: 2 | I379: 3 | J379: 2 | K379: =IF( OR( ISBLANK(F379),ISBLANK(G379), ISBLANK(H379), ISBLANK(I379), ISBLANK(J379) ), "", 1.5*SQRT( EXP(2.21*(F379-1)) + EXP(2.21*(G379-1)) + EXP(2.21*(H379-1)) + EXP(2.21*(I379-1)) + EXP(2.21*J379) )/100*2.45 ) -> 0.48935256
A380: Household textiles (product sector) | B380: 2017 | C380: PA | D380: 4.2914 | E380: Information combined from: CBS (2019), Synthetic Fibers (polymerdatabase.com), and Kawecki & Nowack (2019) | F380: 1 | G380: 1 | H380: 2 | I380: 3 | J380: 2 | K380: =IF( OR( ISBLANK(F380),ISBLANK(G380), ISBLANK(H380), ISBLANK(I380), ISBLANK(J380) ), "", 1.5*SQRT( EXP(2.21*(F380-1)) + EXP(2.21*(G380-1)) + EXP(2.21*(H380-1)) + EXP(2.21*(I380-1)) + EXP(2.21*J380) )/100*2.45 ) -> 0.48935256
A381: Household textiles (product sector) | B381: 2017 | C381: PP | D381: 4.2263667 | E381: Information combined from: CBS (2019), Synthetic Fibers (polymerdatabase.com), and Kawecki & Nowack (2019) | F381: 1 | G381: 1 | H381: 2 | I381: 3 | J381: 2 | K381: =IF( OR( ISBLANK(F381),ISBLANK(G381), ISBLANK(H381), ISBLANK(I381), ISBLANK(J381) ), "", 1.5*SQRT( EXP(2.21*(F381-1)) + EXP(2.21*(G381-1)) + EXP(2.21*(H381-1)) + EXP(2.21*(I381-1)) + EXP(2.21*J381) )/100*2.45 ) -> 0.48935256
A382: Household textiles (product sector) | B382: 2017 | C382: Acryl | D382: 2.6073 | E382: Information combined from: CBS (2019), Synthetic Fibers (polymerdatabase.com), and Kawecki & Nowack (2019) | F382: 1 | G382: 1 | H382: 2 | I382: 3 | J382: 2 | K382: =IF( OR( ISBLANK(F382),ISBLANK(G382), ISBLANK(H382), ISBLANK(I382), ISBLANK(J382) ), "", 1.5*SQRT( EXP(2.21*(F382-1)) + EXP(2.21*(G382-1)) + EXP(2.21*(H382-1)) + EXP(2.21*(I382-1)) + EXP(2.21*J382) )/100*2.45 ) -> 0.48935256
A383: Import of primary plastics | B383: 1995 | C383: LDPE | D383: 415 | E383: Statistics | Eurostat [WWW Document], n.d. URL https://ec.europa.eu/eurostat/databrowser/view/DS-056120__custom_5851448/default/table (accessed 2.15.24). | F383: 1 | G383: 1 | H383: 1 | I383: 2 | J383: 2 | K383: =IF( OR( ISBLANK(F383),ISBLANK(G383), ISBLANK(H383), ISBLANK(I383), ISBLANK(J383) ), "", 1.5*SQRT( EXP(2.21*(F383-1)) + EXP(2.21*(G383-1)) + EXP(2.21*(H383-1)) + EXP(2.21*(I383-1)) + EXP(2.21*J383) )/100*2.45 ) -> 0.35859414 | L383: See 'Pellets_trade' document and pellet_input.py in the Microsoft Teams folder 'Pellet'
A384: Import of primary plastics | B384: 1995 | C384: HDPE | D384: 130 | E384: Statistics | Eurostat [WWW Document], n.d. URL https://ec.europa.eu/eurostat/databrowser/view/DS-056120__custom_5851448/default/table (accessed 2.15.24). | F384: 1 | G384: 1 | H384: 1 | I384: 2 | J384: 2 | K384: =IF( OR( ISBLANK(F384),ISBLANK(G384), ISBLANK(H384), ISBLANK(I384), ISBLANK(J384) ), "", 1.5*SQRT( EXP(2.21*(F384-1)) + EXP(2.21*(G384-1)) + EXP(2.21*(H384-1)) + EXP(2.21*(I384-1)) + EXP(2.21*J384) )/100*2.45 ) -> 0.35859414 | L384: See 'Pellets_trade' document and pellet_input.py in the Microsoft Teams folder 'Pellet'
A385: Import of primary plastics | B385: 1995 | C385: PP | D385: 145 | E385: Statistics | Eurostat [WWW Document], n.d. URL https://ec.europa.eu/eurostat/databrowser/view/DS-056120__custom_5851448/default/table (accessed 2.15.24). | F385: 1 | G385: 1 | H385: 1 | I385: 2 | J385: 2 | K385: =IF( OR( ISBLANK(F385),ISBLANK(G385), ISBLANK(H385), ISBLANK(I385), ISBLANK(J385) ), "", 1.5*SQRT( EXP(2.21*(F385-1)) + EXP(2.21*(G385-1)) + EXP(2.21*(H385-1)) + EXP(2.21*(I385-1)) + EXP(2.21*J385) )/100*2.45 ) -> 0.35859414 | L385: See 'Pellets_trade' document and pellet_input.py in the Microsoft Teams folder 'Pellet'
A386: Import of primary plastics | B386: 1995 | C386: PS | D386: 103 | E386: Statistics | Eurostat [WWW Document], n.d. URL https://ec.europa.eu/eurostat/databrowser/view/DS-056120__custom_5851448/default/table (accessed 2.15.24). | F386: 1 | G386: 1 | H386: 1 | I386: 2 | J386: 2 | K386: =IF( OR( ISBLANK(F386),ISBLANK(G386), ISBLANK(H386), ISBLANK(I386), ISBLANK(J386) ), "", 1.5*SQRT( EXP(2.21*(F386-1)) + EXP(2.21*(G386-1)) + EXP(2.21*(H386-1)) + EXP(2.21*(I386-1)) + EXP(2.21*J386) )/100*2.45 ) -> 0.35859414 | L386: See 'Pellets_trade' document and pellet_input.py in the Microsoft Teams folder 'Pellet'
A387: Import of primary plastics | B387: 1995 | C387: EPS | D387: 29 | E387: Statistics | Eurostat [WWW Document], n.d. URL https://ec.europa.eu/eurostat/databrowser/view/DS-056120__custom_5851448/default/table (accessed 2.15.24). | F387: 1 | G387: 1 | H387: 1 | I387: 2 | J387: 2 | K387: =IF( OR( ISBLANK(F387),ISBLANK(G387), ISBLANK(H387), ISBLANK(I387), ISBLANK(J387) ), "", 1.5*SQRT( EXP(2.21*(F387-1)) + EXP(2.21*(G387-1)) + EXP(2.21*(H387-1)) + EXP(2.21*(I387-1)) + EXP(2.21*J387) )/100*2.45 ) -> 0.35859414 | L387: See 'Pellets_trade' document and pellet_input.py in the Microsoft Teams folder 'Pellet'
A388: Import of primary plastics | B388: 1995 | C388: PVC | D388: 213 | E388: Statistics | Eurostat [WWW Document], n.d. URL https://ec.europa.eu/eurostat/databrowser/view/DS-056120__custom_5851448/default/table (accessed 2.15.24). | F388: 1 | G388: 1 | H388: 1 | I388: 2 | J388: 2 | K388: =IF( OR( ISBLANK(F388),ISBLANK(G388), ISBLANK(H388), ISBLANK(I388), ISBLANK(J388) ), "", 1.5*SQRT( EXP(2.21*(F388-1)) + EXP(2.21*(G388-1)) + EXP(2.21*(H388-1)) + EXP(2.21*(I388-1)) + EXP(2.21*J388) )/100*2.45 ) -> 0.35859414 | L388: See 'Pellets_trade' document and pellet_input.py in the Microsoft Teams folder 'Pellet'
A389: Import of primary plastics | B389: 1995 | C389: PET | D389: 0 | E389: Statistics | Eurostat [WWW Document], n.d. URL https://ec.europa.eu/eurostat/databrowser/view/DS-056120__custom_5851448/default/table (accessed 2.15.24). | F389: 1 | G389: 1 | H389: 1 | I389: 2 | J389: 2 | K389: =IF( OR( ISBLANK(F389),ISBLANK(G389), ISBLANK(H389), ISBLANK(I389), ISBLANK(J389) ), "", 1.5*SQRT( EXP(2.21*(F389-1)) + EXP(2.21*(G389-1)) + EXP(2.21*(H389-1)) + EXP(2.21*(I389-1)) + EXP(2.21*J389) )/100*2.45 ) -> 0.35859414 | L389: See 'Pellets_trade' document and pellet_input.py in the Microsoft Teams folder 'Pellet'
A390: Import of primary plastics | B390: 1995 | C390: ABS | D390: 17 | E390: Statistics | Eurostat [WWW Document], n.d. URL https://ec.europa.eu/eurostat/databrowser/view/DS-056120__custom_5851448/default/table (accessed 2.15.24). | F390: 1 | G390: 1 | H390: 1 | I390: 2 | J390: 2 | K390: =IF( OR( ISBLANK(F390),ISBLANK(G390), ISBLANK(H390), ISBLANK(I390), ISBLANK(J390) ), "", 1.5*SQRT( EXP(2.21*(F390-1)) + EXP(2.21*(G390-1)) + EXP(2.21*(H390-1)) + EXP(2.21*(I390-1)) + EXP(2.21*J390) )/100*2.45 ) -> 0.35859414 | L390: See 'Pellets_trade' document and pellet_input.py in the Microsoft Teams folder 'Pellet'
A391: Import of primary plastics | B391: 1995 | C391: PC | D391: 38 | E391: Statistics | Eurostat [WWW Document], n.d. URL https://ec.europa.eu/eurostat/databrowser/view/DS-056120__custom_5851448/default/table (accessed 2.15.24). | F391: 1 | G391: 1 | H391: 1 | I391: 2 | J391: 2 | K391: =IF( OR( ISBLANK(F391),ISBLANK(G391), ISBLANK(H391), ISBLANK(I391), ISBLANK(J391) ), "", 1.5*SQRT( EXP(2.21*(F391-1)) + EXP(2.21*(G391-1)) + EXP(2.21*(H391-1)) + EXP(2.21*(I391-1)) + EXP(2.21*J391) )/100*2.45 ) -> 0.35859414 | L391: See 'Pellets_trade' document and pellet_input.py in the Microsoft Teams folder 'Pellet'
A392: Import of primary plastics | B392: 1995 | C392: PMMA | D392: 84 | E392: Statistics | Eurostat [WWW Document], n.d. URL https://ec.europa.eu/eurostat/databrowser/view/DS-056120__custom_5851448/default/table (accessed 2.15.24). | F392: 1 | G392: 1 | H392: 1 | I392: 2 | J392: 2 | K392: =IF( OR( ISBLANK(F392),ISBLANK(G392), ISBLANK(H392), ISBLANK(I392), ISBLANK(J392) ), "", 1.5*SQRT( EXP(2.21*(F392-1)) + EXP(2.21*(G392-1)) + EXP(2.21*(H392-1)) + EXP(2.21*(I392-1)) + EXP(2.21*J392) )/100*2.45 ) -> 0.35859414 | L392: See 'Pellets_trade' document and pellet_input.py in the Microsoft Teams folder 'Pellet'
A393: Import of primary plastics | B393: 1995 | C393: PA | D393: 142 | E393: Statistics | Eurostat [WWW Document], n.d. URL https://ec.europa.eu/eurostat/databrowser/view/DS-056120__custom_5851448/default/table (accessed 2.15.24). | F393: 1 | G393: 1 | H393: 1 | I393: 2 | J393: 2 | K393: =IF( OR( ISBLANK(F393),ISBLANK(G393), ISBLANK(H393), ISBLANK(I393), ISBLANK(J393) ), "", 1.5*SQRT( EXP(2.21*(F393-1)) + EXP(2.21*(G393-1)) + EXP(2.21*(H393-1)) + EXP(2.21*(I393-1)) + EXP(2.21*J393) )/100*2.45 ) -> 0.35859414 | L393: See 'Pellets_trade' document and pellet_input.py in the Microsoft Teams folder 'Pellet'
A394: Import of primary plastics | B394: 1995 | C394: PUR | D394: 19 | E394: Statistics | Eurostat [WWW Document], n.d. URL https://ec.europa.eu/eurostat/databrowser/view/DS-056120__custom_5851448/default/table (accessed 2.15.24). | F394: 1 | G394: 1 | H394: 1 | I394: 2 | J394: 2 | K394: =IF( OR( ISBLANK(F394),ISBLANK(G394), ISBLANK(H394), ISBLANK(I394), ISBLANK(J394) ), "", 1.5*SQRT( EXP(2.21*(F394-1)) + EXP(2.21*(G394-1)) + EXP(2.21*(H394-1)) + EXP(2.21*(I394-1)) + EXP(2.21*J394) )/100*2.45 ) -> 0.35859414 | L394: See 'Pellets_trade' document and pellet_input.py in the Microsoft Teams folder 'Pellet'
... A733: Import of primary plastics | B733: 2021 | C733: OTHER | D733: 1446 | E733: Statistics | Eurostat [WWW Document], n.d. URL https://ec.europa.eu/eurostat/databrowser/view/DS-056120__custom_5851448/default/table (accessed 2.15.24). | F733: 1 | G733: 1 | H733: 1 | I733: 2 | J733: 2 | K733: =IF( OR( ISBLANK(F733),ISBLANK(G733), ISBLANK(H733), ISBLANK(I733), ISBLANK(J733) ), "", 1.5*SQRT( EXP(2.21*(F733-1)) + EXP(2.21*(G733-1)) + EXP(2.21*(H733-1)) + EXP(2.21*(I733-1)) + EXP(2.21*J733) )/100*2.45 ) -> 0.35859414 | L733: See 'Pellets_trade' document and pellet_input.py in the Microsoft Teams folder 'Pellet'
A734: Intentionally produced microparticles | B734: 2016 | C734: RUBBER | D734: 18 | E734: Recybem | F734: 1 | G734: 1 | H734: 1 | I734: 1 | J734: 1 | K734: =IF( OR( ISBLANK(F734),ISBLANK(G734), ISBLANK(H734), ISBLANK(I734), ISBLANK(J734) ), "", 1.5*SQRT( EXP(2.21*(F734-1)) + EXP(2.21*(G734-1)) + EXP(2.21*(H734-1)) + EXP(2.21*(I734-1)) + EXP(2.21*J734) )/100*2.45 ) -> 0.13309243
A735: Intentionally produced microparticles | B735: 2020 | C735: RUBBER | D735: =Intentionally_produced_MPs!K106 -> 12.105 | E735: Recybem | F735: 1 | G735: 1 | H735: 1 | I735: 1 | J735: 1 | K735: =IF( OR( ISBLANK(F735),ISBLANK(G735), ISBLANK(H735), ISBLANK(I735), ISBLANK(J735) ), "", 1.5*SQRT( EXP(2.21*(F735-1)) + EXP(2.21*(G735-1)) + EXP(2.21*(H735-1)) + EXP(2.21*(I735-1)) + EXP(2.21*J735) )/100*2.45 ) -> 0.13309243
A736: Intentionally produced microparticles | B736: 2019 | C736: RUBBER | D736: 11.4 | E736: Recybem | F736: 1 | G736: 1 | H736: 1 | I736: 1 | J736: 1 | K736: =IF( OR( ISBLANK(F736),ISBLANK(G736), ISBLANK(H736), ISBLANK(I736), ISBLANK(J736) ), "", 1.5*SQRT( EXP(2.21*(F736-1)) + EXP(2.21*(G736-1)) + EXP(2.21*(H736-1)) + EXP(2.21*(I736-1)) + EXP(2.21*J736) )/100*2.45 ) -> 0.13309243
A737: Intentionally produced microparticles | B737: 2021 | C737: RUBBER | D737: 10.331 | E737: Recybem | F737: 1 | G737: 1 | H737: 1 | I737: 1 | J737: 1 | K737: =IF( OR( ISBLANK(F737),ISBLANK(G737), ISBLANK(H737), ISBLANK(I737), ISBLANK(J737) ), "", 1.5*SQRT( EXP(2.21*(F737-1)) + EXP(2.21*(G737-1)) + EXP(2.21*(H737-1)) + EXP(2.21*(I737-1)) + EXP(2.21*J737) )/100*2.45 ) -> 0.13309243
A738: Intentionally produced microparticles | B738: 2020 | C738: PUR | D738: =Intentionally_produced_MPs!L106 -> 0.8855726 | E738: Information combined from: Scudo et al. (2017), Microplastics Annex XV Report (2020), and Statistics | Eurostat | F738: 2 | G738: 1 | H738: 3 | I738: 1 | J738: 2 | K738: =IF( OR( ISBLANK(F738),ISBLANK(G738), ISBLANK(H738), ISBLANK(I738), ISBLANK(J738) ), "", 1.5*SQRT( EXP(2.21*(F738-1)) + EXP(2.21*(G738-1)) + EXP(2.21*(H738-1)) + EXP(2.21*(I738-1)) + EXP(2.21*J738) )/100*2.45 ) -> 0.48935256
A739: Intentionally produced microparticles | B739: 2020 | C739: OTHER | D739: =Intentionally_produced_MPs!Q106 -> 0.61395726 | E739: Information combined from: Scudo et al. (2017), Microplastics Annex XV Report (2020), and Statistics | Eurostat | F739: 2 | G739: 1 | H739: 3 | I739: 1 | J739: 2 | K739: =IF( OR( ISBLANK(F739),ISBLANK(G739), ISBLANK(H739), ISBLANK(I739), ISBLANK(J739) ), "", 1.5*SQRT( EXP(2.21*(F739-1)) + EXP(2.21*(G739-1)) + EXP(2.21*(H739-1)) + EXP(2.21*(I739-1)) + EXP(2.21*J739) )/100*2.45 ) -> 0.48935256
A740: Intentionally produced microparticles | B740: 2020 | C740: HDPE | D740: =Intentionally_produced_MPs!E106 -> 0.47206704 | E740: Information combined from: Scudo et al. (2017), Microplastics Annex XV Report (2020), and Statistics | Eurostat | F740: 2 | G740: 1 | H740: 3 | I740: 1 | J740: 2 | K740: =IF( OR( ISBLANK(F740),ISBLANK(G740), ISBLANK(H740), ISBLANK(I740), ISBLANK(J740) ), "", 1.5*SQRT( EXP(2.21*(F740-1)) + EXP(2.21*(G740-1)) + EXP(2.21*(H740-1)) + EXP(2.21*(I740-1)) + EXP(2.21*J740) )/100*2.45 ) -> 0.48935256
A741: Intentionally produced microparticles | B741: 2020 | C741: PA | D741: =Intentionally_produced_MPs!N106 -> 0.094626658 | E741: Information combined from: Scudo et al. (2017), Microplastics Annex XV Report (2020), and Statistics | Eurostat | F741: 2 | G741: 1 | H741: 3 | I741: 1 | J741: 2 | K741: =IF( OR( ISBLANK(F741),ISBLANK(G741), ISBLANK(H741), ISBLANK(I741), ISBLANK(J741) ), "", 1.5*SQRT( EXP(2.21*(F741-1)) + EXP(2.21*(G741-1)) + EXP(2.21*(H741-1)) + EXP(2.21*(I741-1)) + EXP(2.21*J741) )/100*2.45 ) -> 0.48935256
A742: Intentionally produced microparticles | B742: 2020 | C742: PMMA | D742: =Intentionally_produced_MPs!P106 -> 0.09409102 | E742: Information combined from: Scudo et al. (2017), Microplastics Annex XV Report (2020), and Statistics | Eurostat | F742: 2 | G742: 1 | H742: 3 | I742: 1 | J742: 2 | K742: =IF( OR( ISBLANK(F742),ISBLANK(G742), ISBLANK(H742), ISBLANK(I742), ISBLANK(J742) ), "", 1.5*SQRT( EXP(2.21*(F742-1)) + EXP(2.21*(G742-1)) + EXP(2.21*(H742-1)) + EXP(2.21*(I742-1)) + EXP(2.21*J742) )/100*2.45 ) -> 0.48935256
A743: Intentionally produced microparticles | B743: 2020 | C743: LDPE | D743: =Intentionally_produced_MPs!D106 -> 0.075513119 | E743: Information combined from: Scudo et al. (2017), Microplastics Annex XV Report (2020), and Statistics | Eurostat | F743: 2 | G743: 1 | H743: 3 | I743: 1 | J743: 2 | K743: =IF( OR( ISBLANK(F743),ISBLANK(G743), ISBLANK(H743), ISBLANK(I743), ISBLANK(J743) ), "", 1.5*SQRT( EXP(2.21*(F743-1)) + EXP(2.21*(G743-1)) + EXP(2.21*(H743-1)) + EXP(2.21*(I743-1)) + EXP(2.21*J743) )/100*2.45 ) -> 0.48935256
A744: Intentionally produced microparticles | B744: 2020 | C744: PVC | D744: =Intentionally_produced_MPs!I106 -> 0.075513119 | E744: Information combined from: Scudo et al. (2017), Microplastics Annex XV Report (2020), and Statistics | Eurostat | F744: 2 | G744: 1 | H744: 3 | I744: 1 | J744: 2 | K744: =IF( OR( ISBLANK(F744),ISBLANK(G744), ISBLANK(H744), ISBLANK(I744), ISBLANK(J744) ), "", 1.5*SQRT( EXP(2.21*(F744-1)) + EXP(2.21*(G744-1)) + EXP(2.21*(H744-1)) + EXP(2.21*(I744-1)) + EXP(2.21*J744) )/100*2.45 ) -> 0.48935256
A745: Intentionally produced microparticles | B745: 2020 | C745: PP | D745: =Intentionally_produced_MPs!F106 -> 0.067122773 | E745: Information combined from: Scudo et al. (2017), Microplastics Annex XV Report (2020), and Statistics | Eurostat | F745: 2 | G745: 1 | H745: 3 | I745: 1 | J745: 2 | K745: =IF( OR( ISBLANK(F745),ISBLANK(G745), ISBLANK(H745), ISBLANK(I745), ISBLANK(J745) ), "", 1.5*SQRT( EXP(2.21*(F745-1)) + EXP(2.21*(G745-1)) + EXP(2.21*(H745-1)) + EXP(2.21*(I745-1)) + EXP(2.21*J745) )/100*2.45 ) -> 0.48935256
A746: Intentionally produced microparticles | B746: 2020 | C746: PET | D746: =Intentionally_produced_MPs!J106 -> 0.026968247 | E746: Information combined from: Scudo et al. (2017), Microplastics Annex XV Report (2020), and Statistics | Eurostat | F746: 2 | G746: 1 | H746: 3 | I746: 1 | J746: 2 | K746: =IF( OR( ISBLANK(F746),ISBLANK(G746), ISBLANK(H746), ISBLANK(I746), ISBLANK(J746) ), "", 1.5*SQRT( EXP(2.21*(F746-1)) + EXP(2.21*(G746-1)) + EXP(2.21*(H746-1)) + EXP(2.21*(I746-1)) + EXP(2.21*J746) )/100*2.45 ) -> 0.48935256
A747: Packaging | B747: 2020 | C747: LDPE | D747: =Packaging!E19 -> 179.20539 | E747: Data based on EUROSTAT, polymer distribution based on Cimpan et al. (2021) | F747: 1 | G747: 1 | H747: 2 | I747: 1 | J747: 2 | K747: =IF( OR( ISBLANK(F747),ISBLANK(G747), ISBLANK(H747), ISBLANK(I747), ISBLANK(J747) ), "", 1.5*SQRT( EXP(2.21*(F747-1)) + EXP(2.21*(G747-1)) + EXP(2.21*(H747-1)) + EXP(2.21*(I747-1)) + EXP(2.21*J747) )/100*2.45 ) -> 0.35859414
A748: =Packaging!U23 -> Packaging | B748: =Packaging!V23 -> 2021 | C748: =Packaging!X23 -> LDPE | D748: =Packaging!Y23 -> 176.56195 | E748: Data based on EUROSTAT, polymer distribution based on Cimpan et al. (2021) | F748: 1 | G748: 1 | H748: 2 | I748: 1 | J748: 2 | K748: =IF( OR( ISBLANK(F748),ISBLANK(G748), ISBLANK(H748), ISBLANK(I748), ISBLANK(J748) ), "", 1.5*SQRT( EXP(2.21*(F748-1)) + EXP(2.21*(G748-1)) + EXP(2.21*(H748-1)) + EXP(2.21*(I748-1)) + EXP(2.21*J748) )/100*2.45 ) -> 0.35859414
A749: =Packaging!U39 -> Packaging | B749: =Packaging!V39 -> 2019 | C749: =Packaging!X39 -> LDPE | D749: =Packaging!Y39 -> 169.17765 | E749: Data based on EUROSTAT, polymer distribution based on Cimpan et al. (2021) | F749: 1 | G749: 1 | H749: 2 | I749: 1 | J749: 2 | K749: =IF( OR( ISBLANK(F749),ISBLANK(G749), ISBLANK(H749), ISBLANK(I749), ISBLANK(J749) ), "", 1.5*SQRT( EXP(2.21*(F749-1)) + EXP(2.21*(G749-1)) + EXP(2.21*(H749-1)) + EXP(2.21*(I749-1)) + EXP(2.21*J749) )/100*2.45 ) -> 0.35859414
A750: =Packaging!U47 -> Packaging | B750: =Packaging!V47 -> 2018 | C750: =Packaging!X47 -> LDPE | D750: =Packaging!Y47 -> 169.17765 | E750: Data based on EUROSTAT, polymer distribution based on Cimpan et al. (2021) | F750: 1 | G750: 1 | H750: 2 | I750: 1 | J750: 2 | K750: =IF( OR( ISBLANK(F750),ISBLANK(G750), ISBLANK(H750), ISBLANK(I750), ISBLANK(J750) ), "", 1.5*SQRT( EXP(2.21*(F750-1)) + EXP(2.21*(G750-1)) + EXP(2.21*(H750-1)) + EXP(2.21*(I750-1)) + EXP(2.21*J750) )/100*2.45 ) -> 0.35859414
A751: =Packaging!U55 -> Packaging | B751: =Packaging!V55 -> 2017 | C751: =Packaging!X55 -> LDPE | D751: =Packaging!Y55 -> 165.61942 | E751: Data based on EUROSTAT, polymer distribution based on Cimpan et al. (2021) | F751: 1 | G751: 1 | H751: 2 | I751: 1 | J751: 2 | K751: =IF( OR( ISBLANK(F751),ISBLANK(G751), ISBLANK(H751), ISBLANK(I751), ISBLANK(J751) ), "", 1.5*SQRT( EXP(2.21*(F751-1)) + EXP(2.21*(G751-1)) + EXP(2.21*(H751-1)) + EXP(2.21*(I751-1)) + EXP(2.21*J751) )/100*2.45 ) -> 0.35859414
A752: Packaging | B752: 2020 | C752: PP | D752: =Packaging!E21 -> 116.77935 | E752: Data based on EUROSTAT, polymer distribution based on Cimpan et al. (2021) | F752: 1 | G752: 1 | H752: 2 | I752: 1 | J752: 2 | K752: =IF( OR( ISBLANK(F752),ISBLANK(G752), ISBLANK(H752), ISBLANK(I752), ISBLANK(J752) ), "", 1.5*SQRT( EXP(2.21*(F752-1)) + EXP(2.21*(G752-1)) + EXP(2.21*(H752-1)) + EXP(2.21*(I752-1)) + EXP(2.21*J752) )/100*2.45 ) -> 0.35859414
A753: =Packaging!U25 -> Packaging | B753: =Packaging!V25 -> 2021 | C753: =Packaging!X25 -> PP | D753: =Packaging!Y25 -> 115.05675 | E753: Data based on EUROSTAT, polymer distribution based on Cimpan et al. (2021) | F753: 1 | G753: 1 | H753: 2 | I753: 1 | J753: 2 | K753: =IF( OR( ISBLANK(F753),ISBLANK(G753), ISBLANK(H753), ISBLANK(I753), ISBLANK(J753) ), "", 1.5*SQRT( EXP(2.21*(F753-1)) + EXP(2.21*(G753-1)) + EXP(2.21*(H753-1)) + EXP(2.21*(I753-1)) + EXP(2.21*J753) )/100*2.45 ) -> 0.35859414
A754: =Packaging!U41 -> Packaging | B754: =Packaging!V41 -> 2019 | C754: =Packaging!X41 -> PP | D754: =Packaging!Y41 -> 110.24477 | E754: Data based on EUROSTAT, polymer distribution based on Cimpan et al. (2021) | F754: 1 | G754: 1 | H754: 2 | I754: 1 | J754: 2 | K754: =IF( OR( ISBLANK(F754),ISBLANK(G754), ISBLANK(H754), ISBLANK(I754), ISBLANK(J754) ), "", 1.5*SQRT( EXP(2.21*(F754-1)) + EXP(2.21*(G754-1)) + EXP(2.21*(H754-1)) + EXP(2.21*(I754-1)) + EXP(2.21*J754) )/100*2.45 ) -> 0.35859414
A755: =Packaging!U49 -> Packaging | B755: =Packaging!V49 -> 2018 | C755: =Packaging!X49 -> PP | D755: =Packaging!Y49 -> 110.24477 | E755: Data based on EUROSTAT, polymer distribution based on Cimpan et al. (2021) | F755: 1 | G755: 1 | H755: 2 | I755: 1 | J755: 2 | K755: =IF( OR( ISBLANK(F755),ISBLANK(G755), ISBLANK(H755), ISBLANK(I755), ISBLANK(J755) ), "", 1.5*SQRT( EXP(2.21*(F755-1)) + EXP(2.21*(G755-1)) + EXP(2.21*(H755-1)) + EXP(2.21*(I755-1)) + EXP(2.21*J755) )/100*2.45 ) -> 0.35859414
A756: =Packaging!U57 -> Packaging | B756: =Packaging!V57 -> 2017 | C756: =Packaging!X57 -> PP | D756: =Packaging!Y57 -> 107.92604 | E756: Data based on EUROSTAT, polymer distribution based on Cimpan et al. (2021) | F756: 1 | G756: 1 | H756: 2 | I756: 1 | J756: 2 | K756: =IF( OR( ISBLANK(F756),ISBLANK(G756), ISBLANK(H756), ISBLANK(I756), ISBLANK(J756) ), "", 1.5*SQRT( EXP(2.21*(F756-1)) + EXP(2.21*(G756-1)) + EXP(2.21*(H756-1)) + EXP(2.21*(I756-1)) + EXP(2.21*J756) )/100*2.45 ) -> 0.35859414
A757: Packaging | B757: 2020 | C757: HDPE | D757: =Packaging!E20 -> 102.02795 | E757: Data based on EUROSTAT, polymer distribution based on Cimpan et al. (2021) | F757: 1 | G757: 1 | H757: 2 | I757: 1 | J757: 2 | K757: =IF( OR( ISBLANK(F757),ISBLANK(G757), ISBLANK(H757), ISBLANK(I757), ISBLANK(J757) ), "", 1.5*SQRT( EXP(2.21*(F757-1)) + EXP(2.21*(G757-1)) + EXP(2.21*(H757-1)) + EXP(2.21*(I757-1)) + EXP(2.21*J757) )/100*2.45 ) -> 0.35859414
A758: Packaging | B758: 2020 | C758: PET | D758: =Packaging!E25 -> 101.66359 | E758: Data based on EUROSTAT, polymer distribution based on Cimpan et al. (2021) | F758: 1 | G758: 1 | H758: 2 | I758: 1 | J758: 2 | K758: =IF( OR( ISBLANK(F758),ISBLANK(G758), ISBLANK(H758), ISBLANK(I758), ISBLANK(J758) ), "", 1.5*SQRT( EXP(2.21*(F758-1)) + EXP(2.21*(G758-1)) + EXP(2.21*(H758-1)) + EXP(2.21*(I758-1)) + EXP(2.21*J758) )/100*2.45 ) -> 0.35859414
A759: =Packaging!U24 -> Packaging | B759: =Packaging!V24 -> 2021 | C759: =Packaging!X24 -> HDPE | D759: =Packaging!Y24 -> 100.52294 | E759: Data based on EUROSTAT, polymer distribution based on Cimpan et al. (2021) | F759: 1 | G759: 1 | H759: 2 | I759: 1 | J759: 2 | K759: =IF( OR( ISBLANK(F759),ISBLANK(G759), ISBLANK(H759), ISBLANK(I759), ISBLANK(J759) ), "", 1.5*SQRT( EXP(2.21*(F759-1)) + EXP(2.21*(G759-1)) + EXP(2.21*(H759-1)) + EXP(2.21*(I759-1)) + EXP(2.21*J759) )/100*2.45 ) -> 0.35859414
A760: =Packaging!U29 -> Packaging | B760: =Packaging!V29 -> 2021 | C760: =Packaging!X29 -> PET | D760: =Packaging!Y29 -> 100.16396 | E760: Data based on EUROSTAT, polymer distribution based on Cimpan et al. (2021) | F760: 1 | G760: 1 | H760: 2 | I760: 1 | J760: 2 | K760: =IF( OR( ISBLANK(F760),ISBLANK(G760), ISBLANK(H760), ISBLANK(I760), ISBLANK(J760) ), "", 1.5*SQRT( EXP(2.21*(F760-1)) + EXP(2.21*(G760-1)) + EXP(2.21*(H760-1)) + EXP(2.21*(I760-1)) + EXP(2.21*J760) )/100*2.45 ) -> 0.35859414
A761: =Packaging!U40 -> Packaging | B761: =Packaging!V40 -> 2019 | C761: =Packaging!X40 -> HDPE | D761: =Packaging!Y40 -> 96.318803 | E761: Data based on EUROSTAT, polymer distribution based on Cimpan et al. (2021) | F761: 1 | G761: 1 | H761: 2 | I761: 1 | J761: 2 | K761: =IF( OR( ISBLANK(F761),ISBLANK(G761), ISBLANK(H761), ISBLANK(I761), ISBLANK(J761) ), "", 1.5*SQRT( EXP(2.21*(F761-1)) + EXP(2.21*(G761-1)) + EXP(2.21*(H761-1)) + EXP(2.21*(I761-1)) + EXP(2.21*J761) )/100*2.45 ) -> 0.35859414
A762: =Packaging!U48 -> Packaging | B762: =Packaging!V48 -> 2018 | C762: =Packaging!X48 -> HDPE | D762: =Packaging!Y48 -> 96.318803 | E762: Data based on EUROSTAT, polymer distribution based on Cimpan et al. (2021) | F762: 1 | G762: 1 | H762: 2 | I762: 1 | J762: 2 | K762: =IF( OR( ISBLANK(F762),ISBLANK(G762), ISBLANK(H762), ISBLANK(I762), ISBLANK(J762) ), "", 1.5*SQRT( EXP(2.21*(F762-1)) + EXP(2.21*(G762-1)) + EXP(2.21*(H762-1)) + EXP(2.21*(I762-1)) + EXP(2.21*J762) )/100*2.45 ) -> 0.35859414
A763: =Packaging!U45 -> Packaging | B763: =Packaging!V45 -> 2019 | C763: =Packaging!X45 -> PET | D763: =Packaging!Y45 -> 95.974835 | E763: Data based on EUROSTAT, polymer distribution based on Cimpan et al. (2021) | F763: 1 | G763: 1 | H763: 2 | I763: 1 | J763: 2 | K763: =IF( OR( ISBLANK(F763),ISBLANK(G763), ISBLANK(H763), ISBLANK(I763), ISBLANK(J763) ), "", 1.5*SQRT( EXP(2.21*(F763-1)) + EXP(2.21*(G763-1)) + EXP(2.21*(H763-1)) + EXP(2.21*(I763-1)) + EXP(2.21*J763) )/100*2.45 ) -> 0.35859414
A764: =Packaging!U53 -> Packaging | B764: =Packaging!V53 -> 2018 | C764: =Packaging!X53 -> PET | D764: =Packaging!Y53 -> 95.974835 | E764: Data based on EUROSTAT, polymer distribution based on Cimpan et al. (2021) | F764: 1 | G764: 1 | H764: 2 | I764: 1 | J764: 2 | K764: =IF( OR( ISBLANK(F764),ISBLANK(G764), ISBLANK(H764), ISBLANK(I764), ISBLANK(J764) ), "", 1.5*SQRT( EXP(2.21*(F764-1)) + EXP(2.21*(G764-1)) + EXP(2.21*(H764-1)) + EXP(2.21*(I764-1)) + EXP(2.21*J764) )/100*2.45 ) -> 0.35859414
A765: =Packaging!U56 -> Packaging | B765: =Packaging!V56 -> 2017 | C765: =Packaging!X56 -> HDPE | D765: =Packaging!Y56 -> 94.292977 | E765: Data based on EUROSTAT, polymer distribution based on Cimpan et al. (2021) | F765: 1 | G765: 1 | H765: 2 | I765: 1 | J765: 2 | K765: =IF( OR( ISBLANK(F765),ISBLANK(G765), ISBLANK(H765), ISBLANK(I765), ISBLANK(J765) ), "", 1.5*SQRT( EXP(2.21*(F765-1)) + EXP(2.21*(G765-1)) + EXP(2.21*(H765-1)) + EXP(2.21*(I765-1)) + EXP(2.21*J765) )/100*2.45 ) -> 0.35859414
A766: =Packaging!U61 -> Packaging | B766: =Packaging!V61 -> 2017 | C766: =Packaging!X61 -> PET | D766: =Packaging!Y61 -> 93.956244 | E766: Data based on EUROSTAT, polymer distribution based on Cimpan et al. (2021) | F766: 1 | G766: 1 | H766: 2 | I766: 1 | J766: 2 | K766: =IF( OR( ISBLANK(F766),ISBLANK(G766), ISBLANK(H766), ISBLANK(I766), ISBLANK(J766) ), "", 1.5*SQRT( EXP(2.21*(F766-1)) + EXP(2.21*(G766-1)) + EXP(2.21*(H766-1)) + EXP(2.21*(I766-1)) + EXP(2.21*J766) )/100*2.45 ) -> 0.35859414
A767: Packaging | B767: 2020 | C767: PS | D767: =Packaging!E22 -> 20.887643 | E767: Data based on EUROSTAT, polymer distribution based on Cimpan et al. (2021) | F767: 1 | G767: 1 | H767: 2 | I767: 1 | J767: 2 | K767: =IF( OR( ISBLANK(F767),ISBLANK(G767), ISBLANK(H767), ISBLANK(I767), ISBLANK(J767) ), "", 1.5*SQRT( EXP(2.21*(F767-1)) + EXP(2.21*(G767-1)) + EXP(2.21*(H767-1)) + EXP(2.21*(I767-1)) + EXP(2.21*J767) )/100*2.45 ) -> 0.35859414
A768: =Packaging!U26 -> Packaging | B768: =Packaging!V26 -> 2021 | C768: =Packaging!X26 -> PS | D768: =Packaging!Y26 -> 20.579532 | E768: Data based on EUROSTAT, polymer distribution based on Cimpan et al. (2021) | F768: 1 | G768: 1 | H768: 2 | I768: 1 | J768: 2 | K768: =IF( OR( ISBLANK(F768),ISBLANK(G768), ISBLANK(H768), ISBLANK(I768), ISBLANK(J768) ), "", 1.5*SQRT( EXP(2.21*(F768-1)) + EXP(2.21*(G768-1)) + EXP(2.21*(H768-1)) + EXP(2.21*(I768-1)) + EXP(2.21*J768) )/100*2.45 ) -> 0.35859414
A769: =Packaging!U42 -> Packaging | B769: =Packaging!V42 -> 2019 | C769: =Packaging!X42 -> PS | D769: =Packaging!Y42 -> 19.71884 | E769: Data based on EUROSTAT, polymer distribution based on Cimpan et al. (2021) | F769: 1 | G769: 1 | H769: 2 | I769: 1 | J769: 2 | K769: =IF( OR( ISBLANK(F769),ISBLANK(G769), ISBLANK(H769), ISBLANK(I769), ISBLANK(J769) ), "", 1.5*SQRT( EXP(2.21*(F769-1)) + EXP(2.21*(G769-1)) + EXP(2.21*(H769-1)) + EXP(2.21*(I769-1)) + EXP(2.21*J769) )/100*2.45 ) -> 0.35859414
A770: =Packaging!U50 -> Packaging | B770: =Packaging!V50 -> 2018 | C770: =Packaging!X50 -> PS | D770: =Packaging!Y50 -> 19.71884 | E770: Data based on EUROSTAT, polymer distribution based on Cimpan et al. (2021) | F770: 1 | G770: 1 | H770: 2 | I770: 1 | J770: 2 | K770: =IF( OR( ISBLANK(F770),ISBLANK(G770), ISBLANK(H770), ISBLANK(I770), ISBLANK(J770) ), "", 1.5*SQRT( EXP(2.21*(F770-1)) + EXP(2.21*(G770-1)) + EXP(2.21*(H770-1)) + EXP(2.21*(I770-1)) + EXP(2.21*J770) )/100*2.45 ) -> 0.35859414
A771: =Packaging!U58 -> Packaging | B771: =Packaging!V58 -> 2017 | C771: =Packaging!X58 -> PS | D771: =Packaging!Y58 -> 19.304104 | E771: Data based on EUROSTAT, polymer distribution based on Cimpan et al. (2021) | F771: 1 | G771: 1 | H771: 2 | I771: 1 | J771: 2 | K771: =IF( OR( ISBLANK(F771),ISBLANK(G771), ISBLANK(H771), ISBLANK(I771), ISBLANK(J771) ), "", 1.5*SQRT( EXP(2.21*(F771-1)) + EXP(2.21*(G771-1)) + EXP(2.21*(H771-1)) + EXP(2.21*(I771-1)) + EXP(2.21*J771) )/100*2.45 ) -> 0.35859414
A772: Packaging | B772: 2020 | C772: OTHER | D772: =Packaging!E26 -> 14.067727 | E772: Data based on EUROSTAT, polymer distribution based on Cimpan et al. (2021) | F772: 1 | G772: 1 | H772: 2 | I772: 1 | J772: 2 | K772: =IF( OR( ISBLANK(F772),ISBLANK(G772), ISBLANK(H772), ISBLANK(I772), ISBLANK(J772) ), "", 1.5*SQRT( EXP(2.21*(F772-1)) + EXP(2.21*(G772-1)) + EXP(2.21*(H772-1)) + EXP(2.21*(I772-1)) + EXP(2.21*J772) )/100*2.45 ) -> 0.35859414
A773: =Packaging!U30 -> Packaging | B773: =Packaging!V30 -> 2021 | C773: =Packaging!X30 -> OTHER | D773: =Packaging!Y30 -> 13.860215 | E773: Data based on EUROSTAT, polymer distribution based on Cimpan et al. (2021) | F773: 1 | G773: 1 | H773: 2 | I773: 1 | J773: 2 | K773: =IF( OR( ISBLANK(F773),ISBLANK(G773), ISBLANK(H773), ISBLANK(I773), ISBLANK(J773) ), "", 1.5*SQRT( EXP(2.21*(F773-1)) + EXP(2.21*(G773-1)) + EXP(2.21*(H773-1)) + EXP(2.21*(I773-1)) + EXP(2.21*J773) )/100*2.45 ) -> 0.35859414
A774: =Packaging!U46 -> Packaging | B774: =Packaging!V46 -> 2019 | C774: =Packaging!X46 -> OTHER | D774: =Packaging!Y46 -> 13.280544 | E774: Data based on EUROSTAT, polymer distribution based on Cimpan et al. (2021) | F774: 1 | G774: 1 | H774: 2 | I774: 1 | J774: 2 | K774: =IF( OR( ISBLANK(F774),ISBLANK(G774), ISBLANK(H774), ISBLANK(I774), ISBLANK(J774) ), "", 1.5*SQRT( EXP(2.21*(F774-1)) + EXP(2.21*(G774-1)) + EXP(2.21*(H774-1)) + EXP(2.21*(I774-1)) + EXP(2.21*J774) )/100*2.45 ) -> 0.35859414
A775: =Packaging!U54 -> Packaging | B775: =Packaging!V54 -> 2018 | C775: =Packaging!X54 -> OTHER | D775: =Packaging!Y54 -> 13.280544 | E775: Data based on EUROSTAT, polymer distribution based on Cimpan et al. (2021) | F775: 1 | G775: 1 | H775: 2 | I775: 1 | J775: 2 | K775: =IF( OR( ISBLANK(F775),ISBLANK(G775), ISBLANK(H775), ISBLANK(I775), ISBLANK(J775) ), "", 1.5*SQRT( EXP(2.21*(F775-1)) + EXP(2.21*(G775-1)) + EXP(2.21*(H775-1)) + EXP(2.21*(I775-1)) + EXP(2.21*J775) )/100*2.45 ) -> 0.35859414
A776: =Packaging!U62 -> Packaging | B776: =Packaging!V62 -> 2017 | C776: =Packaging!X62 -> OTHER | D776: =Packaging!Y62 -> 13.001221 | E776: Data based on EUROSTAT, polymer distribution based on Cimpan et al. (2021) | F776: 1 | G776: 1 | H776: 2 | I776: 1 | J776: 2 | K776: =IF( OR( ISBLANK(F776),ISBLANK(G776), ISBLANK(H776), ISBLANK(I776), ISBLANK(J776) ), "", 1.5*SQRT( EXP(2.21*(F776-1)) + EXP(2.21*(G776-1)) + EXP(2.21*(H776-1)) + EXP(2.21*(I776-1)) + EXP(2.21*J776) )/100*2.45 ) -> 0.35859414
...

Sheet Input_EU
A1: Compartment | B1: Year | C1: Material | D1: Data (kt) | E1: Source | F1: Geo | G1: Temp | H1: Mat | I1: Tech | J1: Rel | K1: Spread | L1: Comments
A2: =Agriculture!A10 -> Agriculture | B2: =Agriculture!C10 -> 2018 | C2: =Agriculture!D10 -> PS | D2: =Agriculture!E10 -> 3.9507479 | E2: =Agriculture!F10 -> Combined from TNO Sieger Henke and Statistics - APE Europe [WWW Document], n.d. URL https://web.archive.org/web/20230930160250/https://apeeurope.eu/statistics/ (accessed 3.27.24). | F2: 1 | G2: 2 | H2: 2 | I2: 1 | J2: 2 | K2: =IF( OR( ISBLANK(F2),ISBLANK(G2), ISBLANK(H2), ISBLANK(I2), ISBLANK(J2) ), "", 1.5*SQRT( EXP(2.21*(F2-1)) + EXP(2.21*(G2-1)) + EXP(2.21*(H2-1)) + EXP(2.21*(I2-1)) + EXP(2.21*J2) )/100*2.45 ) -> 0.37356464
A3: =Agriculture!A11 -> Agriculture | B3: =Agriculture!C11 -> 2018 | C3: =Agriculture!D11 -> PP | D3: =Agriculture!E11 -> 3.9660876 | E3: =Agriculture!F11 -> Combined from TNO Sieger Henke and Statistics - APE Europe [WWW Document], n.d. URL https://web.archive.org/web/20230930160250/https://apeeurope.eu/statistics/ (accessed 3.27.24). | F3: 1 | G3: 2 | H3: 2 | I3: 1 | J3: 2 | K3: =IF( OR( ISBLANK(F3),ISBLANK(G3), ISBLANK(H3), ISBLANK(I3), ISBLANK(J3) ), "", 1.5*SQRT( EXP(2.21*(F3-1)) + EXP(2.21*(G3-1)) + EXP(2.21*(H3-1)) + EXP(2.21*(I3-1)) + EXP(2.21*J3) )/100*2.45 ) -> 0.37356464
A4: =Agriculture!A15 -> Agriculture | B4: =Agriculture!C15 -> 2019 | C4: =Agriculture!D15 -> PS | D4: =Agriculture!E15 -> 3.9660876 | E4: =Agriculture!F15 -> Combined from TNO Sieger Henke and Statistics - APE Europe [WWW Document], n.d. URL https://web.archive.org/web/20230930160250/https://apeeurope.eu/statistics/ (accessed 3.27.24). | F4: 1 | G4: 2 | H4: 2 | I4: 1 | J4: 2 | K4: =IF( OR( ISBLANK(F4),ISBLANK(G4), ISBLANK(H4), ISBLANK(I4), ISBLANK(J4) ), "", 1.5*SQRT( EXP(2.21*(F4-1)) + EXP(2.21*(G4-1)) + EXP(2.21*(H4-1)) + EXP(2.21*(I4-1)) + EXP(2.21*J4) )/100*2.45 ) -> 0.37356464
A5: =Agriculture!A16 -> Agriculture | B5: =Agriculture!C16 -> 2019 | C5: =Agriculture!D16 -> PP | D5: =Agriculture!E16 -> 3.9660876 | E5: =Agriculture!F16 -> Combined from TNO Sieger Henke and Statistics - APE Europe [WWW Document], n.d. URL https://web.archive.org/web/20230930160250/https://apeeurope.eu/statistics/ (accessed 3.27.24). | F5: 1 | G5: 2 | H5: 2 | I5: 1 | J5: 2 | K5: =IF( OR( ISBLANK(F5),ISBLANK(G5), ISBLANK(H5), ISBLANK(I5), ISBLANK(J5) ), "", 1.5*SQRT( EXP(2.21*(F5-1)) + EXP(2.21*(G5-1)) + EXP(2.21*(H5-1)) + EXP(2.21*(I5-1)) + EXP(2.21*J5) )/100*2.45 ) -> 0.37356464
A6: =Agriculture!A13 -> Agriculture | B6: =Agriculture!C13 -> 2018 | C6: =Agriculture!D13 -> HDPE | D6: =Agriculture!E13 -> 5.6494845 | E6: =Agriculture!F13 -> Combined from TNO Sieger Henke and Statistics - APE Europe [WWW Document], n.d. URL https://web.archive.org/web/20230930160250/https://apeeurope.eu/statistics/ (accessed 3.27.24). | F6: 1 | G6: 2 | H6: 2 | I6: 1 | J6: 2 | K6: =IF( OR( ISBLANK(F6),ISBLANK(G6), ISBLANK(H6), ISBLANK(I6), ISBLANK(J6) ), "", 1.5*SQRT( EXP(2.21*(F6-1)) + EXP(2.21*(G6-1)) + EXP(2.21*(H6-1)) + EXP(2.21*(I6-1)) + EXP(2.21*J6) )/100*2.45 ) -> 0.37356464
A7: =Agriculture!A18 -> Agriculture | B7: =Agriculture!C18 -> 2019 | C7: =Agriculture!D18 -> HDPE | D7: =Agriculture!E18 -> 5.67142 | E7: =Agriculture!F18 -> Combined from TNO Sieger Henke and Statistics - APE Europe [WWW Document], n.d. URL https://web.archive.org/web/20230930160250/https://apeeurope.eu/statistics/ (accessed 3.27.24). | F7: 1 | G7: 2 | H7: 2 | I7: 1 | J7: 2 | K7: =IF( OR( ISBLANK(F7),ISBLANK(G7), ISBLANK(H7), ISBLANK(I7), ISBLANK(J7) ), "", 1.5*SQRT( EXP(2.21*(F7-1)) + EXP(2.21*(G7-1)) + EXP(2.21*(H7-1)) + EXP(2.21*(I7-1)) + EXP(2.21*J7) )/100*2.45 ) -> 0.37356464
A8: =Agriculture!A9 -> Agriculture | B8: =Agriculture!C9 -> 2018 | C8: =Agriculture!D9 -> PVC | D8: =Agriculture!E9 -> 56.385015 | E8: =Agriculture!F9 -> Combined from TNO Sieger Henke and Statistics - APE Europe [WWW Document], n.d. URL https://web.archive.org/web/20230930160250/https://apeeurope.eu/statistics/ (accessed 3.27.24). | F8: 1 | G8: 2 | H8: 2 | I8: 1 | J8: 2 | K8: =IF( OR( ISBLANK(F8),ISBLANK(G8), ISBLANK(H8), ISBLANK(I8), ISBLANK(J8) ), "", 1.5*SQRT( EXP(2.21*(F8-1)) + EXP(2.21*(G8-1)) + EXP(2.21*(H8-1)) + EXP(2.21*(I8-1)) + EXP(2.21*J8) )/100*2.45 ) -> 0.37356464
A9: =Agriculture!A14 -> Agriculture | B9: =Agriculture!C14 -> 2019 | C9: =Agriculture!D14 -> PVC | D9: =Agriculture!E14 -> 56.603943 | E9: =Agriculture!F14 -> Combined from TNO Sieger Henke and Statistics - APE Europe [WWW Document], n.d. URL https://web.archive.org/web/20230930160250/https://apeeurope.eu/statistics/ (accessed 3.27.24). | F9: 1 | G9: 2 | H9: 2 | I9: 1 | J9: 2 | K9: =IF( OR( ISBLANK(F9),ISBLANK(G9), ISBLANK(H9), ISBLANK(I9), ISBLANK(J9) ), "", 1.5*SQRT( EXP(2.21*(F9-1)) + EXP(2.21*(G9-1)) + EXP(2.21*(H9-1)) + EXP(2.21*(I9-1)) + EXP(2.21*J9) )/100*2.45 ) -> 0.37356464
A10: =Agriculture!A12 -> Agriculture | B10: =Agriculture!C12 -> 2018 | C10: =Agriculture!D12 -> LDPE | D10: =Agriculture!E12 -> 622.871 | E10: =Agriculture!F12 -> Combined from TNO Sieger Henke and Statistics - APE Europe [WWW Document], n.d. URL https://web.archive.org/web/20230930160250/https://apeeurope.eu/statistics/ (accessed 3.27.24). | F10: 1 | G10: 2 | H10: 2 | I10: 1 | J10: 2 | K10: =IF( OR( ISBLANK(F10),ISBLANK(G10), ISBLANK(H10), ISBLANK(I10), ISBLANK(J10) ), "", 1.5*SQRT( EXP(2.21*(F10-1)) + EXP(2.21*(G10-1)) + EXP(2.21*(H10-1)) + EXP(2.21*(I10-1)) + EXP(2.21*J10) )/100*2.45 ) -> 0.37356464
A11: =Agriculture!A17 -> Agriculture | B11: =Agriculture!C17 -> 2019 | C11: =Agriculture!D17 -> LDPE | D11: =Agriculture!E17 -> 625.28945 | E11: =Agriculture!F17 -> Combined from TNO Sieger Henke and Statistics - APE Europe [WWW Document], n.d. URL https://web.archive.org/web/20230930160250/https://apeeurope.eu/statistics/ (accessed 3.27.24). | F11: 1 | G11: 2 | H11: 2 | I11: 1 | J11: 2 | K11: =IF( OR( ISBLANK(F11),ISBLANK(G11), ISBLANK(H11), ISBLANK(I11), ISBLANK(J11) ), "", 1.5*SQRT( EXP(2.21*(F11-1)) + EXP(2.21*(G11-1)) + EXP(2.21*(H11-1)) + EXP(2.21*(I11-1)) + EXP(2.21*J11) )/100*2.45 ) -> 0.37356464
A12: Clothing (product sector) | B12: 2017 | C12: LDPE | D12: 0 | E12: Textiles in Europe's circular economy — European Environment Agency (europa.eu) | F12: 1 | G12: 1 | H12: 3 | I12: 1 | J12: 2 | K12: =IF( OR( ISBLANK(F12),ISBLANK(G12), ISBLANK(H12), ISBLANK(I12), ISBLANK(J12) ), "", 1.5*SQRT( EXP(2.21*(F12-1)) + EXP(2.21*(G12-1)) + EXP(2.21*(H12-1)) + EXP(2.21*(I12-1)) + EXP(2.21*J12) )/100*2.45 ) -> 0.47802211 | L12: Calculated based on the total EU textile consumption (8351.04 kt) and the fractions for the different compartments at NL scale (see table above).
A13: Clothing (product sector) | B13: 2017 | C13: HDPE | D13: 6.0673285 | E13: Textiles in Europe's circular economy — European Environment Agency (europa.eu) | F13: 1 | G13: 1 | H13: 3 | I13: 1 | J13: 2 | K13: =IF( OR( ISBLANK(F13),ISBLANK(G13), ISBLANK(H13), ISBLANK(I13), ISBLANK(J13) ), "", 1.5*SQRT( EXP(2.21*(F13-1)) + EXP(2.21*(G13-1)) + EXP(2.21*(H13-1)) + EXP(2.21*(I13-1)) + EXP(2.21*J13) )/100*2.45 ) -> 0.47802211 | L13: Calculated based on the total EU textile consumption (8351.04 kt) and the fractions for the different compartments at NL scale (see table above).
A14: Clothing (product sector) | B14: 2017 | C14: PP | D14: 6.0673285 | E14: Textiles in Europe's circular economy — European Environment Agency (europa.eu) | F14: 1 | G14: 1 | H14: 3 | I14: 1 | J14: 2 | K14: =IF( OR( ISBLANK(F14),ISBLANK(G14), ISBLANK(H14), ISBLANK(I14), ISBLANK(J14) ), "", 1.5*SQRT( EXP(2.21*(F14-1)) + EXP(2.21*(G14-1)) + EXP(2.21*(H14-1)) + EXP(2.21*(I14-1)) + EXP(2.21*J14) )/100*2.45 ) -> 0.47802211 | L14: Calculated based on the total EU textile consumption (8351.04 kt) and the fractions for the different compartments at NL scale (see table above).
A15: Clothing (product sector) | B15: 2017 | C15: PS | D15: 0 | E15: Textiles in Europe's circular economy — European Environment Agency (europa.eu) | F15: 1 | G15: 1 | H15: 3 | I15: 1 | J15: 2 | K15: =IF( OR( ISBLANK(F15),ISBLANK(G15), ISBLANK(H15), ISBLANK(I15), ISBLANK(J15) ), "", 1.5*SQRT( EXP(2.21*(F15-1)) + EXP(2.21*(G15-1)) + EXP(2.21*(H15-1)) + EXP(2.21*(I15-1)) + EXP(2.21*J15) )/100*2.45 ) -> 0.47802211 | L15: Calculated based on the total EU textile consumption (8351.04 kt) and the fractions for the different compartments at NL scale (see table above).
A16: Clothing (product sector) | B16: 2017 | C16: EPS | D16: 0 | E16: Textiles in Europe's circular economy — European Environment Agency (europa.eu) | F16: 1 | G16: 1 | H16: 3 | I16: 1 | J16: 2 | K16: =IF( OR( ISBLANK(F16),ISBLANK(G16), ISBLANK(H16), ISBLANK(I16), ISBLANK(J16) ), "", 1.5*SQRT( EXP(2.21*(F16-1)) + EXP(2.21*(G16-1)) + EXP(2.21*(H16-1)) + EXP(2.21*(I16-1)) + EXP(2.21*J16) )/100*2.45 ) -> 0.47802211 | L16: Calculated based on the total EU textile consumption (8351.04 kt) and the fractions for the different compartments at NL scale (see table above).
A17: Clothing (product sector) | B17: 2017 | C17: PVC | D17: 0 | E17: Textiles in Europe's circular economy — European Environment Agency (europa.eu) | F17: 1 | G17: 1 | H17: 3 | I17: 1 | J17: 2 | K17: =IF( OR( ISBLANK(F17),ISBLANK(G17), ISBLANK(H17), ISBLANK(I17), ISBLANK(J17) ), "", 1.5*SQRT( EXP(2.21*(F17-1)) + EXP(2.21*(G17-1)) + EXP(2.21*(H17-1)) + EXP(2.21*(I17-1)) + EXP(2.21*J17) )/100*2.45 ) -> 0.47802211 | L17: Calculated based on the total EU textile consumption (8351.04 kt) and the fractions for the different compartments at NL scale (see table above).
A18: Clothing (product sector) | B18: 2017 | C18: PET | D18: 467.1843 | E18: Textiles in Europe's circular economy — European Environment Agency (europa.eu) | F18: 1 | G18: 1 | H18: 3 | I18: 1 | J18: 2 | K18: =IF( OR( ISBLANK(F18),ISBLANK(G18), ISBLANK(H18), ISBLANK(I18), ISBLANK(J18) ), "", 1.5*SQRT( EXP(2.21*(F18-1)) + EXP(2.21*(G18-1)) + EXP(2.21*(H18-1)) + EXP(2.21*(I18-1)) + EXP(2.21*J18) )/100*2.45 ) -> 0.47802211 | L18: Calculated based on the total EU textile consumption (8351.04 kt) and the fractions for the different compartments at NL scale (see table above).
A19: Clothing (product sector) | B19: 2017 | C19: PA | D19: 72.807942 | E19: Textiles in Europe's circular economy — European Environment Agency (europa.eu) | F19: 1 | G19: 1 | H19: 3 | I19: 1 | J19: 2 | K19: =IF( OR( ISBLANK(F19),ISBLANK(G19), ISBLANK(H19), ISBLANK(I19), ISBLANK(J19) ), "", 1.5*SQRT( EXP(2.21*(F19-1)) + EXP(2.21*(G19-1)) + EXP(2.21*(H19-1)) + EXP(2.21*(I19-1)) + EXP(2.21*J19) )/100*2.45 ) -> 0.47802211 | L19: Calculated based on the total EU textile consumption (8351.04 kt) and the fractions for the different compartments at NL scale (see table above).
A20: Clothing (product sector) | B20: 2017 | C20: Acryl | D20: 54.605957 | E20: Textiles in Europe's circular economy — European Environment Agency (europa.eu) | F20: 1 | G20: 1 | H20: 3 | I20: 1 | J20: 2 | K20: =IF( OR( ISBLANK(F20),ISBLANK(G20), ISBLANK(H20), ISBLANK(I20), ISBLANK(J20) ), "", 1.5*SQRT( EXP(2.21*(F20-1)) + EXP(2.21*(G20-1)) + EXP(2.21*(H20-1)) + EXP(2.21*(I20-1)) + EXP(2.21*J20) )/100*2.45 ) -> 0.47802211 | L20: Calculated based on the total EU textile consumption (8351.04 kt) and the fractions for the different compartments at NL scale (see table above).
A21: Domestic primary plastic production | B21: 2015 | C21: ABS | D21: 400 | E21: Statistics | Eurostat [WWW Document], n.d. URL https://ec.europa.eu/eurostat/databrowser/view/DS-056120__custom_6262207/default/table (accessed 2.15.24). | F21: 1 | G21: 1 | H21: 1 | I21: 2 | J21: 2 | K21: =IF( OR( ISBLANK(F21),ISBLANK(G21), ISBLANK(H21), ISBLANK(I21), ISBLANK(J21) ), "", 1.5*SQRT( EXP(2.21*(F21-1)) + EXP(2.21*(G21-1)) + EXP(2.21*(H21-1)) + EXP(2.21*(I21-1)) + EXP(2.21*J21) )/100*2.45 ) -> 0.35859414 | L21: See 'Pellets_trade' document and pellet_input.py in the Microsoft Teams folder 'Pellet'
A22: Domestic primary plastic production | B22: 2013 | C22: ABS | D22: 468 | E22: Statistics | Eurostat [WWW Document], n.d. URL https://ec.europa.eu/eurostat/databrowser/view/DS-056120__custom_6262207/default/table (accessed 2.15.24). | F22: 1 | G22: 1 | H22: 1 | I22: 2 | J22: 2 | K22: =IF( OR( ISBLANK(F22),ISBLANK(G22), ISBLANK(H22), ISBLANK(I22), ISBLANK(J22) ), "", 1.5*SQRT( EXP(2.21*(F22-1)) + EXP(2.21*(G22-1)) + EXP(2.21*(H22-1)) + EXP(2.21*(I22-1)) + EXP(2.21*J22) )/100*2.45 ) -> 0.35859414 | L22: See 'Pellets_trade' document and pellet_input.py in the Microsoft Teams folder 'Pellet'
A23: Domestic primary plastic production | B23: 2016 | C23: ABS | D23: 551 | E23: Statistics | Eurostat [WWW Document], n.d. URL https://ec.europa.eu/eurostat/databrowser/view/DS-056120__custom_6262207/default/table (accessed 2.15.24). | F23: 1 | G23: 1 | H23: 1 | I23: 2 | J23: 2 | K23: =IF( OR( ISBLANK(F23),ISBLANK(G23), ISBLANK(H23), ISBLANK(I23), ISBLANK(J23) ), "", 1.5*SQRT( EXP(2.21*(F23-1)) + EXP(2.21*(G23-1)) + EXP(2.21*(H23-1)) + EXP(2.21*(I23-1)) + EXP(2.21*J23) )/100*2.45 ) -> 0.35859414 | L23: See 'Pellets_trade' document and pellet_input.py in the Microsoft Teams folder 'Pellet'
... A523: Import of primary plastics | B523: 2021 | C523: OTHER | D523: 1687 | E523: Statistics | Eurostat [WWW Document], n.d. URL https://ec.europa.eu/eurostat/databrowser/view/DS-056120__custom_6262207/default/table (accessed 2.15.24). | F523: 1 | G523: 1 | H523: 1 | I523: 2 | J523: 2 | K523: =IF( OR( ISBLANK(F523),ISBLANK(G523), ISBLANK(H523), ISBLANK(I523), ISBLANK(J523) ), "", 1.5*SQRT( EXP(2.21*(F523-1)) + EXP(2.21*(G523-1)) + EXP(2.21*(H523-1)) + EXP(2.21*(I523-1)) + EXP(2.21*J523) )/100*2.45 ) -> 0.35859414 | L523: See 'Pellets_trade' document and pellet_input.py in the Microsoft Teams folder 'Pellet'
A524: Intentionally produced microparticles | B524: 2020 | C524: PS | D524: =Intentionally_produced_MPs!G57 -> 0 | E524: Information combined from: Scudo et al. (2017), Microplastics Annex XV Report (2020), and Statistics | Eurostat | F524: 1 | G524: 1 | H524: 3 | I524: 1 | J524: 1 | K524: =IF( OR( ISBLANK(F524),ISBLANK(G524), ISBLANK(H524), ISBLANK(I524), ISBLANK(J524) ), "", 1.5*SQRT( EXP(2.21*(F524-1)) + EXP(2.21*(G524-1)) + EXP(2.21*(H524-1)) + EXP(2.21*(I524-1)) + EXP(2.21*J524) )/100*2.45 ) -> 0.35859414
A525: Intentionally produced microparticles | B525: 2020 | C525: EPS | D525: =Intentionally_produced_MPs!H57 -> 0 | E525: Information combined from: Scudo et al. (2017), Microplastics Annex XV Report (2020), and Statistics | Eurostat | F525: 1 | G525: 1 | H525: 3 | I525: 1 | J525: 1 | K525: =IF( OR( ISBLANK(F525),ISBLANK(G525), ISBLANK(H525), ISBLANK(I525), ISBLANK(J525) ), "", 1.5*SQRT( EXP(2.21*(F525-1)) + EXP(2.21*(G525-1)) + EXP(2.21*(H525-1)) + EXP(2.21*(I525-1)) + EXP(2.21*J525) )/100*2.45 ) -> 0.35859414
A526: Intentionally produced microparticles | B526: 2020 | C526: ABS | D526: =Intentionally_produced_MPs!M57 -> 0 | E526: Information combined from: Scudo et al. (2017), Microplastics Annex XV Report (2020), and Statistics | Eurostat | F526: 1 | G526: 1 | H526: 3 | I526: 1 | J526: 1 | K526: =IF( OR( ISBLANK(F526),ISBLANK(G526), ISBLANK(H526), ISBLANK(I526), ISBLANK(J526) ), "", 1.5*SQRT( EXP(2.21*(F526-1)) + EXP(2.21*(G526-1)) + EXP(2.21*(H526-1)) + EXP(2.21*(I526-1)) + EXP(2.21*J526) )/100*2.45 ) -> 0.35859414
A527: Intentionally produced microparticles | B527: 2020 | C527: PC | D527: =Intentionally_produced_MPs!O57 -> 0 | E527: Information combined from: Scudo et al. (2017), Microplastics Annex XV Report (2020), and Statistics | Eurostat | F527: 1 | G527: 1 | H527: 3 | I527: 1 | J527: 1 | K527: =IF( OR( ISBLANK(F527),ISBLANK(G527), ISBLANK(H527), ISBLANK(I527), ISBLANK(J527) ), "", 1.5*SQRT( EXP(2.21*(F527-1)) + EXP(2.21*(G527-1)) + EXP(2.21*(H527-1)) + EXP(2.21*(I527-1)) + EXP(2.21*J527) )/100*2.45 ) -> 0.35859414
A528: Intentionally produced microparticles | B528: 2020 | C528: PET | D528: =Intentionally_produced_MPs!J57 -> 0.60256976 | E528: Information combined from: Scudo et al. (2017), Microplastics Annex XV Report (2020), and Statistics | Eurostat | F528: 1 | G528: 1 | H528: 3 | I528: 1 | J528: 1 | K528: =IF( OR( ISBLANK(F528),ISBLANK(G528), ISBLANK(H528), ISBLANK(I528), ISBLANK(J528) ), "", 1.5*SQRT( EXP(2.21*(F528-1)) + EXP(2.21*(G528-1)) + EXP(2.21*(H528-1)) + EXP(2.21*(I528-1)) + EXP(2.21*J528) )/100*2.45 ) -> 0.35859414
A529: Intentionally produced microparticles | B529: 2020 | C529: PP | D529: =Intentionally_produced_MPs!F57 -> 1 | E529: Information combined from: Scudo et al. (2017), Microplastics Annex XV Report (2020), and Statistics | Eurostat | F529: 1 | G529: 1 | H529: 3 | I529: 1 | J529: 1 | K529: =IF( OR( ISBLANK(F529),ISBLANK(G529), ISBLANK(H529), ISBLANK(I529), ISBLANK(J529) ), "", 1.5*SQRT( EXP(2.21*(F529-1)) + EXP(2.21*(G529-1)) + EXP(2.21*(H529-1)) + EXP(2.21*(I529-1)) + EXP(2.21*J529) )/100*2.45 ) -> 0.35859414
A530: Intentionally produced microparticles | B530: 2020 | C530: LDPE | D530: =Intentionally_produced_MPs!D57 -> 1.125 | E530: Information combined from: Scudo et al. (2017), Microplastics Annex XV Report (2020), and Statistics | Eurostat | F530: 1 | G530: 1 | H530: 3 | I530: 1 | J530: 1 | K530: =IF( OR( ISBLANK(F530),ISBLANK(G530), ISBLANK(H530), ISBLANK(I530), ISBLANK(J530) ), "", 1.5*SQRT( EXP(2.21*(F530-1)) + EXP(2.21*(G530-1)) + EXP(2.21*(H530-1)) + EXP(2.21*(I530-1)) + EXP(2.21*J530) )/100*2.45 ) -> 0.35859414
A531: Intentionally produced microparticles | B531: 2020 | C531: PVC | D531: =Intentionally_produced_MPs!I57 -> 1.125 | E531: Information combined from: Scudo et al. (2017), Microplastics Annex XV Report (2020), and Statistics | Eurostat | F531: 1 | G531: 1 | H531: 3 | I531: 1 | J531: 1 | K531: =IF( OR( ISBLANK(F531),ISBLANK(G531), ISBLANK(H531), ISBLANK(I531), ISBLANK(J531) ), "", 1.5*SQRT( EXP(2.21*(F531-1)) + EXP(2.21*(G531-1)) + EXP(2.21*(H531-1)) + EXP(2.21*(I531-1)) + EXP(2.21*J531) )/100*2.45 ) -> 0.35859414
A532: Intentionally produced microparticles | B532: 2020 | C532: PMMA | D532: =Intentionally_produced_MPs!P57 -> 1.6025698 | E532: Information combined from: Scudo et al. (2017), Microplastics Annex XV Report (2020), and Statistics | Eurostat | F532: 1 | G532: 1 | H532: 3 | I532: 1 | J532: 1 | K532: =IF( OR( ISBLANK(F532),ISBLANK(G532), ISBLANK(H532), ISBLANK(I532), ISBLANK(J532) ), "", 1.5*SQRT( EXP(2.21*(F532-1)) + EXP(2.21*(G532-1)) + EXP(2.21*(H532-1)) + EXP(2.21*(I532-1)) + EXP(2.21*J532) )/100*2.45 ) -> 0.35859414
A533: Intentionally produced microparticles | B533: 2020 | C533: PA | D533: =Intentionally_produced_MPs!N57 -> 1.616339 | E533: Information combined from: Scudo et al. (2017), Microplastics Annex XV Report (2020), and Statistics | Eurostat | F533: 1 | G533: 1 | H533: 3 | I533: 1 | J533: 1 | K533: =IF( OR( ISBLANK(F533),ISBLANK(G533), ISBLANK(H533), ISBLANK(I533), ISBLANK(J533) ), "", 1.5*SQRT( EXP(2.21*(F533-1)) + EXP(2.21*(G533-1)) + EXP(2.21*(H533-1)) + EXP(2.21*(I533-1)) + EXP(2.21*J533) )/100*2.45 ) -> 0.35859414
A534: Intentionally produced microparticles | B534: 2020 | C534: HDPE | D534: =Intentionally_produced_MPs!E57 -> 8.4170263 | E534: Information combined from: Scudo et al. (2017), Microplastics Annex XV Report (2020), and Statistics | Eurostat | F534: 1 | G534: 1 | H534: 3 | I534: 1 | J534: 1 | K534: =IF( OR( ISBLANK(F534),ISBLANK(G534), ISBLANK(H534), ISBLANK(I534), ISBLANK(J534) ), "", 1.5*SQRT( EXP(2.21*(F534-1)) + EXP(2.21*(G534-1)) + EXP(2.21*(H534-1)) + EXP(2.21*(I534-1)) + EXP(2.21*J534) )/100*2.45 ) -> 0.35859414
A535: Intentionally produced microparticles | B535: 2020 | C535: OTHER | D535: =Intentionally_produced_MPs!Q57 -> 9.6628389 | E535: Information combined from: Scudo et al. (2017), Microplastics Annex XV Report (2020), and Statistics | Eurostat | F535: 1 | G535: 1 | H535: 3 | I535: 1 | J535: 1 | K535: =IF( OR( ISBLANK(F535),ISBLANK(G535), ISBLANK(H535), ISBLANK(I535), ISBLANK(J535) ), "", 1.5*SQRT( EXP(2.21*(F535-1)) + EXP(2.21*(G535-1)) + EXP(2.21*(H535-1)) + EXP(2.21*(I535-1)) + EXP(2.21*J535) )/100*2.45 ) -> 0.35859414
A536: Intentionally produced microparticles | B536: 2020 | C536: PUR | D536: =Intentionally_produced_MPs!L57 -> 21.948661 | E536: Information combined from: Scudo et al. (2017), Microplastics Annex XV Report (2020), and Statistics | Eurostat | F536: 1 | G536: 1 | H536: 3 | I536: 1 | J536: 1 | K536: =IF( OR( ISBLANK(F536),ISBLANK(G536), ISBLANK(H536), ISBLANK(I536), ISBLANK(J536) ), "", 1.5*SQRT( EXP(2.21*(F536-1)) + EXP(2.21*(G536-1)) + EXP(2.21*(H536-1)) + EXP(2.21*(I536-1)) + EXP(2.21*J536) )/100*2.45 ) -> 0.35859414
A537: Intentionally produced microparticles | B537: 2020 | C537: RUBBER | D537: =Intentionally_produced_MPs!K57 -> 115.5 | E537: Information combined from: Scudo et al. (2017), Microplastics Annex XV Report (2020), and Statistics | Eurostat | F537: 1 | G537: 1 | H537: 3 | I537: 1 | J537: 1 | K537: =IF( OR( ISBLANK(F537),ISBLANK(G537), ISBLANK(H537), ISBLANK(I537), ISBLANK(J537) ), "", 1.5*SQRT( EXP(2.21*(F537-1)) + EXP(2.21*(G537-1)) + EXP(2.21*(H537-1)) + EXP(2.21*(I537-1)) + EXP(2.21*J537) )/100*2.45 ) -> 0.35859414
A538: =Packaging!AF59 -> Packaging | B538: =Packaging!AG59 -> 2017 | C538: =Packaging!AI59 -> EPS | D538: =Packaging!AJ59 -> 196.16894 | E538: Data based on EUROSTAT, polymer distribution based on Cimpan et al. (2021) | F538: 1 | G538: 1 | H538: 2 | I538: 1 | J538: 2 | K538: =IF( OR( ISBLANK(F538),ISBLANK(G538), ISBLANK(H538), ISBLANK(I538), ISBLANK(J538) ), "", 1.5*SQRT( EXP(2.21*(F538-1)) + EXP(2.21*(G538-1)) + EXP(2.21*(H538-1)) + EXP(2.21*(I538-1)) + EXP(2.21*J538) )/100*2.45 ) -> 0.35859414
A539: =Packaging!AF51 -> Packaging | B539: =Packaging!AG51 -> 2018 | C539: =Packaging!AI51 -> EPS | D539: =Packaging!AJ51 -> 199.75023 | E539: Data based on EUROSTAT, polymer distribution based on Cimpan et al. (2021) | F539: 1 | G539: 1 | H539: 2 | I539: 1 | J539: 2 | K539: =IF( OR( ISBLANK(F539),ISBLANK(G539), ISBLANK(H539), ISBLANK(I539), ISBLANK(J539) ), "", 1.5*SQRT( EXP(2.21*(F539-1)) + EXP(2.21*(G539-1)) + EXP(2.21*(H539-1)) + EXP(2.21*(I539-1)) + EXP(2.21*J539) )/100*2.45 ) -> 0.35859414
A540: =Packaging!AF43 -> Packaging | B540: =Packaging!AG43 -> 2019 | C540: =Packaging!AI43 -> EPS | D540: =Packaging!AJ43 -> 205.75393 | E540: Data based on EUROSTAT, polymer distribution based on Cimpan et al. (2021) | F540: 1 | G540: 1 | H540: 2 | I540: 1 | J540: 2 | K540: =IF( OR( ISBLANK(F540),ISBLANK(G540), ISBLANK(H540), ISBLANK(I540), ISBLANK(J540) ), "", 1.5*SQRT( EXP(2.21*(F540-1)) + EXP(2.21*(G540-1)) + EXP(2.21*(H540-1)) + EXP(2.21*(I540-1)) + EXP(2.21*J540) )/100*2.45 ) -> 0.35859414
A541: =Packaging!AF35 -> Packaging | B541: =Packaging!AG35 -> 2020 | C541: =Packaging!AI35 -> EPS | D541: =Packaging!AJ35 -> 208.3271 | E541: Data based on EUROSTAT, polymer distribution based on Cimpan et al. (2021) | F541: 1 | G541: 1 | H541: 2 | I541: 1 | J541: 2 | K541: =IF( OR( ISBLANK(F541),ISBLANK(G541), ISBLANK(H541), ISBLANK(I541), ISBLANK(J541) ), "", 1.5*SQRT( EXP(2.21*(F541-1)) + EXP(2.21*(G541-1)) + EXP(2.21*(H541-1)) + EXP(2.21*(I541-1)) + EXP(2.21*J541) )/100*2.45 ) -> 0.35859414
A542: =Packaging!AF27 -> Packaging | B542: =Packaging!AG27 -> 2021 | C542: =Packaging!AI27 -> EPS | D542: =Packaging!AJ27 -> 216.38777 | E542: Data based on EUROSTAT, polymer distribution based on Cimpan et al. (2021) | F542: 1 | G542: 1 | H542: 2 | I542: 1 | J542: 2 | K542: =IF( OR( ISBLANK(F542),ISBLANK(G542), ISBLANK(H542), ISBLANK(I542), ISBLANK(J542) ), "", 1.5*SQRT( EXP(2.21*(F542-1)) + EXP(2.21*(G542-1)) + EXP(2.21*(H542-1)) + EXP(2.21*(I542-1)) + EXP(2.21*J542) )/100*2.45 ) -> 0.35859414
A543: =Packaging!AF60 -> Packaging | B543: =Packaging!AG60 -> 2017 | C543: =Packaging!AI60 -> PVC | D543: =Packaging!AJ60 -> 312.57448 | E543: Data based on EUROSTAT, polymer distribution based on Cimpan et al. (2021) | F543: 1 | G543: 1 | H543: 2 | I543: 1 | J543: 2 | K543: =IF( OR( ISBLANK(F543),ISBLANK(G543), ISBLANK(H543), ISBLANK(I543), ISBLANK(J543) ), "", 1.5*SQRT( EXP(2.21*(F543-1)) + EXP(2.21*(G543-1)) + EXP(2.21*(H543-1)) + EXP(2.21*(I543-1)) + EXP(2.21*J543) )/100*2.45 ) -> 0.35859414
A544: =Packaging!AF52 -> Packaging | B544: =Packaging!AG52 -> 2018 | C544: =Packaging!AI52 -> PVC | D544: =Packaging!AJ52 -> 318.2809 | E544: Data based on EUROSTAT, polymer distribution based on Cimpan et al. (2021) | F544: 1 | G544: 1 | H544: 2 | I544: 1 | J544: 2 | K544: =IF( OR( ISBLANK(F544),ISBLANK(G544), ISBLANK(H544), ISBLANK(I544), ISBLANK(J544) ), "", 1.5*SQRT( EXP(2.21*(F544-1)) + EXP(2.21*(G544-1)) + EXP(2.21*(H544-1)) + EXP(2.21*(I544-1)) + EXP(2.21*J544) )/100*2.45 ) -> 0.35859414
A545: =Packaging!AF44 -> Packaging | B545: =Packaging!AG44 -> 2019 | C545: =Packaging!AI44 -> PVC | D545: =Packaging!AJ44 -> 327.84716 | E545: Data based on EUROSTAT, polymer distribution based on Cimpan et al. (2021) | F545: 1 | G545: 1 | H545: 2 | I545: 1 | J545: 2 | K545: =IF( OR( ISBLANK(F545),ISBLANK(G545), ISBLANK(H545), ISBLANK(I545), ISBLANK(J545) ), "", 1.5*SQRT( EXP(2.21*(F545-1)) + EXP(2.21*(G545-1)) + EXP(2.21*(H545-1)) + EXP(2.21*(I545-1)) + EXP(2.21*J545) )/100*2.45 ) -> 0.35859414
A546: =Packaging!AF36 -> Packaging | B546: =Packaging!AG36 -> 2020 | C546: =Packaging!AI36 -> PVC | D546: =Packaging!AJ36 -> 331.94723 | E546: Data based on EUROSTAT, polymer distribution based on Cimpan et al. (2021) | F546: 1 | G546: 1 | H546: 2 | I546: 1 | J546: 2 | K546: =IF( OR( ISBLANK(F546),ISBLANK(G546), ISBLANK(H546), ISBLANK(I546), ISBLANK(J546) ), "", 1.5*SQRT( EXP(2.21*(F546-1)) + EXP(2.21*(G546-1)) + EXP(2.21*(H546-1)) + EXP(2.21*(I546-1)) + EXP(2.21*J546) )/100*2.45 ) -> 0.35859414
A547: =Packaging!AF28 -> Packaging | B547: =Packaging!AG28 -> 2021 | C547: =Packaging!AI28 -> PVC | D547: =Packaging!AJ28 -> 344.79105 | E547: Data based on EUROSTAT, polymer distribution based on Cimpan et al. (2021) | F547: 1 | G547: 1 | H547: 2 | I547: 1 | J547: 2 | K547: =IF( OR( ISBLANK(F547),ISBLANK(G547), ISBLANK(H547), ISBLANK(I547), ISBLANK(J547) ), "", 1.5*SQRT( EXP(2.21*(F547-1)) + EXP(2.21*(G547-1)) + EXP(2.21*(H547-1)) + EXP(2.21*(I547-1)) + EXP(2.21*J547) )/100*2.45 ) -> 0.35859414
A548: =Packaging!AF62 -> Packaging | B548: =Packaging!AG62 -> 2017 | C548: =Packaging!AI62 -> OTHER | D548: =Packaging!AJ62 -> 369.51335 | E548: Data based on EUROSTAT, polymer distribution based on Cimpan et al. (2021) | F548: 1 | G548: 1 | H548: 2 | I548: 1 | J548: 2 | K548: =IF( OR( ISBLANK(F548),ISBLANK(G548), ISBLANK(H548), ISBLANK(I548), ISBLANK(J548) ), "", 1.5*SQRT( EXP(2.21*(F548-1)) + EXP(2.21*(G548-1)) + EXP(2.21*(H548-1)) + EXP(2.21*(I548-1)) + EXP(2.21*J548) )/100*2.45 ) -> 0.35859414
A549: =Packaging!AF54 -> Packaging | B549: =Packaging!AG54 -> 2018 | C549: =Packaging!AI54 -> OTHER | D549: =Packaging!AJ54 -> 376.25926 | E549: Data based on EUROSTAT, polymer distribution based on Cimpan et al. (2021) | F549: 1 | G549: 1 | H549: 2 | I549: 1 | J549: 2 | K549: =IF( OR( ISBLANK(F549),ISBLANK(G549), ISBLANK(H549), ISBLANK(I549), ISBLANK(J549) ), "", 1.5*SQRT( EXP(2.21*(F549-1)) + EXP(2.21*(G549-1)) + EXP(2.21*(H549-1)) + EXP(2.21*(I549-1)) + EXP(2.21*J549) )/100*2.45 ) -> 0.35859414
A550: =Packaging!AF46 -> Packaging | B550: =Packaging!AG46 -> 2019 | C550: =Packaging!AI46 -> OTHER | D550: =Packaging!AJ46 -> 387.56811 | E550: Data based on EUROSTAT, polymer distribution based on Cimpan et al. (2021) | F550: 1 | G550: 1 | H550: 2 | I550: 1 | J550: 2 | K550: =IF( OR( ISBLANK(F550),ISBLANK(G550), ISBLANK(H550), ISBLANK(I550), ISBLANK(J550) ), "", 1.5*SQRT( EXP(2.21*(F550-1)) + EXP(2.21*(G550-1)) + EXP(2.21*(H550-1)) + EXP(2.21*(I550-1)) + EXP(2.21*J550) )/100*2.45 ) -> 0.35859414
A551: =Packaging!AF38 -> Packaging | B551: =Packaging!AG38 -> 2020 | C551: =Packaging!AI38 -> OTHER | D551: =Packaging!AJ38 -> 392.41506 | E551: Data based on EUROSTAT, polymer distribution based on Cimpan et al. (2021) | F551: 1 | G551: 1 | H551: 2 | I551: 1 | J551: 2 | K551: =IF( OR( ISBLANK(F551),ISBLANK(G551), ISBLANK(H551), ISBLANK(I551), ISBLANK(J551) ), "", 1.5*SQRT( EXP(2.21*(F551-1)) + EXP(2.21*(G551-1)) + EXP(2.21*(H551-1)) + EXP(2.21*(I551-1)) + EXP(2.21*J551) )/100*2.45 ) -> 0.35859414
A552: =Packaging!AF30 -> Packaging | B552: =Packaging!AG30 -> 2021 | C552: =Packaging!AI30 -> OTHER | D552: =Packaging!AJ30 -> 407.59853 | E552: Data based on EUROSTAT, polymer distribution based on Cimpan et al. (2021) | F552: 1 | G552: 1 | H552: 2 | I552: 1 | J552: 2 | K552: =IF( OR( ISBLANK(F552),ISBLANK(G552), ISBLANK(H552), ISBLANK(I552), ISBLANK(J552) ), "", 1.5*SQRT( EXP(2.21*(F552-1)) + EXP(2.21*(G552-1)) + EXP(2.21*(H552-1)) + EXP(2.21*(I552-1)) + EXP(2.21*J552) )/100*2.45 ) -> 0.35859414
A553: =Packaging!AF58 -> Packaging | B553: =Packaging!AG58 -> 2017 | C553: =Packaging!AI58 -> PS | D553: =Packaging!AJ58 -> 548.65034 | E553: Data based on EUROSTAT, polymer distribution based on Cimpan et al. (2021) | F553: 1 | G553: 1 | H553: 2 | I553: 1 | J553: 2 | K553: =IF( OR( ISBLANK(F553),ISBLANK(G553), ISBLANK(H553), ISBLANK(I553), ISBLANK(J553) ), "", 1.5*SQRT( EXP(2.21*(F553-1)) + EXP(2.21*(G553-1)) + EXP(2.21*(H553-1)) + EXP(2.21*(I553-1)) + EXP(2.21*J553) )/100*2.45 ) -> 0.35859414
A554: =Packaging!AF50 -> Packaging | B554: =Packaging!AG50 -> 2018 | C554: =Packaging!AI50 -> PS | D554: =Packaging!AJ50 -> 558.66661 | E554: Data based on EUROSTAT, polymer distribution based on Cimpan et al. (2021) | F554: 1 | G554: 1 | H554: 2 | I554: 1 | J554: 2 | K554: =IF( OR( ISBLANK(F554),ISBLANK(G554), ISBLANK(H554), ISBLANK(I554), ISBLANK(J554) ), "", 1.5*SQRT( EXP(2.21*(F554-1)) + EXP(2.21*(G554-1)) + EXP(2.21*(H554-1)) + EXP(2.21*(I554-1)) + EXP(2.21*J554) )/100*2.45 ) -> 0.35859414
A555: =Packaging!AF42 -> Packaging | B555: =Packaging!AG42 -> 2019 | C555: =Packaging!AI42 -> PS | D555: =Packaging!AJ42 -> 575.4579 | E555: Data based on EUROSTAT, polymer distribution based on Cimpan et al. (2021) | F555: 1 | G555: 1 | H555: 2 | I555: 1 | J555: 2 | K555: =IF( OR( ISBLANK(F555),ISBLANK(G555), ISBLANK(H555), ISBLANK(I555), ISBLANK(J555) ), "", 1.5*SQRT( EXP(2.21*(F555-1)) + EXP(2.21*(G555-1)) + EXP(2.21*(H555-1)) + EXP(2.21*(I555-1)) + EXP(2.21*J555) )/100*2.45 ) -> 0.35859414
A556: =Packaging!AF34 -> Packaging | B556: =Packaging!AG34 -> 2020 | C556: =Packaging!AI34 -> PS | D556: =Packaging!AJ34 -> 582.65459 | E556: Data based on EUROSTAT, polymer distribution based on Cimpan et al. (2021) | F556: 1 | G556: 1 | H556: 2 | I556: 1 | J556: 2 | K556: =IF( OR( ISBLANK(F556),ISBLANK(G556), ISBLANK(H556), ISBLANK(I556), ISBLANK(J556) ), "", 1.5*SQRT( EXP(2.21*(F556-1)) + EXP(2.21*(G556-1)) + EXP(2.21*(H556-1)) + EXP(2.21*(I556-1)) + EXP(2.21*J556) )/100*2.45 ) -> 0.35859414
A557: =Packaging!AF26 -> Packaging | B557: =Packaging!AG26 -> 2021 | C557: =Packaging!AI26 -> PS | D557: =Packaging!AJ26 -> 605.19888 | E557: Data based on EUROSTAT, polymer distribution based on Cimpan et al. (2021) | F557: 1 | G557: 1 | H557: 2 | I557: 1 | J557: 2 | K557: =IF( OR( ISBLANK(F557),ISBLANK(G557), ISBLANK(H557), ISBLANK(I557), ISBLANK(J557) ), "", 1.5*SQRT( EXP(2.21*(F557-1)) + EXP(2.21*(G557-1)) + EXP(2.21*(H557-1)) + EXP(2.21*(I557-1)) + EXP(2.21*J557) )/100*2.45 ) -> 0.35859414
A558: =Packaging!AF61 -> Packaging | B558: =Packaging!AG61 -> 2017 | C558: =Packaging!AI61 -> PET | D558: =Packaging!AJ61 -> 2670.3713 | E558: Data based on EUROSTAT, polymer distribution based on Cimpan et al. (2021) | F558: 1 | G558: 1 | H558: 2 | I558: 1 | J558: 2 | K558: =IF( OR( ISBLANK(F558),ISBLANK(G558), ISBLANK(H558), ISBLANK(I558), ISBLANK(J558) ), "", 1.5*SQRT( EXP(2.21*(F558-1)) + EXP(2.21*(G558-1)) + EXP(2.21*(H558-1)) + EXP(2.21*(I558-1)) + EXP(2.21*J558) )/100*2.45 ) -> 0.35859414
A559: =Packaging!AF56 -> Packaging | B559: =Packaging!AG56 -> 2017 | C559: =Packaging!AI56 -> HDPE | D559: =Packaging!AJ56 -> 2679.9418 | E559: Data based on EUROSTAT, polymer distribution based on Cimpan et al. (2021) | F559: 1 | G559: 1 | H559: 2 | I559: 1 | J559: 2 | K559: =IF( OR( ISBLANK(F559),ISBLANK(G559), ISBLANK(H559), ISBLANK(I559), ISBLANK(J559) ), "", 1.5*SQRT( EXP(2.21*(F559-1)) + EXP(2.21*(G559-1)) + EXP(2.21*(H559-1)) + EXP(2.21*(I559-1)) + EXP(2.21*J559) )/100*2.45 ) -> 0.35859414
A560: =Packaging!AF53 -> Packaging | B560: =Packaging!AG53 -> 2018 | C560: =Packaging!AI53 -> PET | D560: =Packaging!AJ53 -> 2719.1221 | E560: Data based on EUROSTAT, polymer distribution based on Cimpan et al. (2021) | F560: 1 | G560: 1 | H560: 2 | I560: 1 | J560: 2 | K560: =IF( OR( ISBLANK(F560),ISBLANK(G560), ISBLANK(H560), ISBLANK(I560), ISBLANK(J560) ), "", 1.5*SQRT( EXP(2.21*(F560-1)) + EXP(2.21*(G560-1)) + EXP(2.21*(H560-1)) + EXP(2.21*(I560-1)) + EXP(2.21*J560) )/100*2.45 ) -> 0.35859414
A561: =Packaging!AF48 -> Packaging | B561: =Packaging!AG48 -> 2018 | C561: =Packaging!AI48 -> HDPE | D561: =Packaging!AJ48 -> 2728.8673 | E561: Data based on EUROSTAT, polymer distribution based on Cimpan et al. (2021) | F561: 1 | G561: 1 | H561: 2 | I561: 1 | J561: 2 | K561: =IF( OR( ISBLANK(F561),ISBLANK(G561), ISBLANK(H561), ISBLANK(I561), ISBLANK(J561) ), "", 1.5*SQRT( EXP(2.21*(F561-1)) + EXP(2.21*(G561-1)) + EXP(2.21*(H561-1)) + EXP(2.21*(I561-1)) + EXP(2.21*J561) )/100*2.45 ) -> 0.35859414
A562: =Packaging!AF45 -> Packaging | B562: =Packaging!AG45 -> 2019 | C562: =Packaging!AI45 -> PET | D562: =Packaging!AJ45 -> 2800.8481 | E562: Data based on EUROSTAT, polymer distribution based on Cimpan et al. (2021) | F562: 1 | G562: 1 | H562: 2 | I562: 1 | J562: 2 | K562: =IF( OR( ISBLANK(F562),ISBLANK(G562), ISBLANK(H562), ISBLANK(I562), ISBLANK(J562) ), "", 1.5*SQRT( EXP(2.21*(F562-1)) + EXP(2.21*(G562-1)) + EXP(2.21*(H562-1)) + EXP(2.21*(I562-1)) + EXP(2.21*J562) )/100*2.45 ) -> 0.35859414
A563: =Packaging!AF40 -> Packaging | B563: =Packaging!AG40 -> 2019 | C563: =Packaging!AI40 -> HDPE | D563: =Packaging!AJ40 -> 2810.8862 | E563: Data based on EUROSTAT, polymer distribution based on Cimpan et al. (2021) | F563: 1 | G563: 1 | H563: 2 | I563: 1 | J563: 2 | K563: =IF( OR( ISBLANK(F563),ISBLANK(G563), ISBLANK(H563), ISBLANK(I563), ISBLANK(J563) ), "", 1.5*SQRT( EXP(2.21*(F563-1)) + EXP(2.21*(G563-1)) + EXP(2.21*(H563-1)) + EXP(2.21*(I563-1)) + EXP(2.21*J563) )/100*2.45 ) -> 0.35859414
A564: =Packaging!AF37 -> Packaging | B564: =Packaging!AG37 -> 2020 | C564: =Packaging!AI37 -> PET | D564: =Packaging!AJ37 -> 2835.8756 | E564: Data based on EUROSTAT, polymer distribution based on Cimpan et al. (2021) | F564: 1 | G564: 1 | H564: 2 | I564: 1 | J564: 2 | K564: =IF( OR( ISBLANK(F564),ISBLANK(G564), ISBLANK(H564), ISBLANK(I564), ISBLANK(J564) ), "", 1.5*SQRT( EXP(2.21*(F564-1)) + EXP(2.21*(G564-1)) + EXP(2.21*(H564-1)) + EXP(2.21*(I564-1)) + EXP(2.21*J564) )/100*2.45 ) -> 0.35859414
A565: =Packaging!AF32 -> Packaging | B565: =Packaging!AG32 -> 2020 | C565: =Packaging!AI32 -> HDPE | D565: =Packaging!AJ32 -> 2846.0392 | E565: Data based on EUROSTAT, polymer distribution based on Cimpan et al. (2021) | F565: 1 | G565: 1 | H565: 2 | I565: 1 | J565: 2 | K565: =IF( OR( ISBLANK(F565),ISBLANK(G565), ISBLANK(H565), ISBLANK(I565), ISBLANK(J565) ), "", 1.5*SQRT( EXP(2.21*(F565-1)) + EXP(2.21*(G565-1)) + EXP(2.21*(H565-1)) + EXP(2.21*(I565-1)) + EXP(2.21*J565) )/100*2.45 ) -> 0.35859414
A566: =Packaging!AF29 -> Packaging | B566: =Packaging!AG29 -> 2021 | C566: =Packaging!AI29 -> PET | D566: =Packaging!AJ29 -> 2945.6024 | E566: Data based on EUROSTAT, polymer distribution based on Cimpan et al. (2021) | F566: 1 | G566: 1 | H566: 2 | I566: 1 | J566: 2 | K566: =IF( OR( ISBLANK(F566),ISBLANK(G566), ISBLANK(H566), ISBLANK(I566), ISBLANK(J566) ), "", 1.5*SQRT( EXP(2.21*(F566-1)) + EXP(2.21*(G566-1)) + EXP(2.21*(H566-1)) + EXP(2.21*(I566-1)) + EXP(2.21*J566) )/100*2.45 ) -> 0.35859414
A567: =Packaging!AF24 -> Packaging | B567: =Packaging!AG24 -> 2021 | C567: =Packaging!AI24 -> HDPE | D567: =Packaging!AJ24 -> 2956.1592 | E567: Data based on EUROSTAT, polymer distribution based on Cimpan et al. (2021) | F567: 1 | G567: 1 | H567: 2 | I567: 1 | J567: 2 | K567: =IF( OR( ISBLANK(F567),ISBLANK(G567), ISBLANK(H567), ISBLANK(I567), ISBLANK(J567) ), "", 1.5*SQRT( EXP(2.21*(F567-1)) + EXP(2.21*(G567-1)) + EXP(2.21*(H567-1)) + EXP(2.21*(I567-1)) + EXP(2.21*J567) )/100*2.45 ) -> 0.35859414
A568: =Packaging!AF57 -> Packaging | B568: =Packaging!AG57 -> 2017 | C568: =Packaging!AI57 -> PP | D568: =Packaging!AJ57 -> 3067.4131 | E568: Data based on EUROSTAT, polymer distribution based on Cimpan et al. (2021) | F568: 1 | G568: 1 | H568: 2 | I568: 1 | J568: 2 | K568: =IF( OR( ISBLANK(F568),ISBLANK(G568), ISBLANK(H568), ISBLANK(I568), ISBLANK(J568) ), "", 1.5*SQRT( EXP(2.21*(F568-1)) + EXP(2.21*(G568-1)) + EXP(2.21*(H568-1)) + EXP(2.21*(I568-1)) + EXP(2.21*J568) )/100*2.45 ) -> 0.35859414
A569: =Packaging!AF49 -> Packaging | B569: =Packaging!AG49 -> 2018 | C569: =Packaging!AI49 -> PP | D569: =Packaging!AJ49 -> 3123.4124 | E569: Data based on EUROSTAT, polymer distribution based on Cimpan et al. (2021) | F569: 1 | G569: 1 | H569: 2 | I569: 1 | J569: 2 | K569: =IF( OR( ISBLANK(F569),ISBLANK(G569), ISBLANK(H569), ISBLANK(I569), ISBLANK(J569) ), "", 1.5*SQRT( EXP(2.21*(F569-1)) + EXP(2.21*(G569-1)) + EXP(2.21*(H569-1)) + EXP(2.21*(I569-1)) + EXP(2.21*J569) )/100*2.45 ) -> 0.35859414
A570: =Packaging!AF41 -> Packaging | B570: =Packaging!AG41 -> 2019 | C570: =Packaging!AI41 -> PP | D570: =Packaging!AJ41 -> 3217.2897 | E570: Data based on EUROSTAT, polymer distribution based on Cimpan et al. (2021) | F570: 1 | G570: 1 | H570: 2 | I570: 1 | J570: 2 | K570: =IF( OR( ISBLANK(F570),ISBLANK(G570), ISBLANK(H570), ISBLANK(I570), ISBLANK(J570) ), "", 1.5*SQRT( EXP(2.21*(F570-1)) + EXP(2.21*(G570-1)) + EXP(2.21*(H570-1)) + EXP(2.21*(I570-1)) + EXP(2.21*J570) )/100*2.45 ) -> 0.35859414
A571: =Packaging!AF33 -> Packaging | B571: =Packaging!AG33 -> 2020 | C571: =Packaging!AI33 -> PP | D571: =Packaging!AJ33 -> 3257.5253 | E571: Data based on EUROSTAT, polymer distribution based on Cimpan et al. (2021) | F571: 1 | G571: 1 | H571: 2 | I571: 1 | J571: 2 | K571: =IF( OR( ISBLANK(F571),ISBLANK(G571), ISBLANK(H571), ISBLANK(I571), ISBLANK(J571) ), "", 1.5*SQRT( EXP(2.21*(F571-1)) + EXP(2.21*(G571-1)) + EXP(2.21*(H571-1)) + EXP(2.21*(I571-1)) + EXP(2.21*J571) )/100*2.45 ) -> 0.35859414
A572: =Packaging!AF25 -> Packaging | B572: =Packaging!AG25 -> 2021 | C572: =Packaging!AI25 -> PP | D572: =Packaging!AJ25 -> 3383.5667 | E572: Data based on EUROSTAT, polymer distribution based on Cimpan et al. (2021) | F572: 1 | G572: 1 | H572: 2 | I572: 1 | J572: 2 | K572: =IF( OR( ISBLANK(F572),ISBLANK(G572), ISBLANK(H572), ISBLANK(I572), ISBLANK(J572) ), "", 1.5*SQRT( EXP(2.21*(F572-1)) + EXP(2.21*(G572-1)) + EXP(2.21*(H572-1)) + EXP(2.21*(I572-1)) + EXP(2.21*J572) )/100*2.45 ) -> 0.35859414
A573: =Packaging!AF55 -> Packaging | B573: =Packaging!AG55 -> 2017 | C573: =Packaging!AI55 -> LDPE | D573: =Packaging!AJ55 -> 4707.1417 | E573: Data based on EUROSTAT, polymer distribution based on Cimpan et al. (2021) | F573: 1 | G573: 1 | H573: 2 | I573: 1 | J573: 2 | K573: =IF( OR( ISBLANK(F573),ISBLANK(G573), ISBLANK(H573), ISBLANK(I573), ISBLANK(J573) ), "", 1.5*SQRT( EXP(2.21*(F573-1)) + EXP(2.21*(G573-1)) + EXP(2.21*(H573-1)) + EXP(2.21*(I573-1)) + EXP(2.21*J573) )/100*2.45 ) -> 0.35859414
A574: =Packaging!AF47 -> Packaging | B574: =Packaging!AG47 -> 2018 | C574: =Packaging!AI47 -> LDPE | D574: =Packaging!AJ47 -> 4793.0761 | E574: Data based on EUROSTAT, polymer distribution based on Cimpan et al. (2021) | F574: 1 | G574: 1 | H574: 2 | I574: 1 | J574: 2 | K574: =IF( OR( ISBLANK(F574),ISBLANK(G574), ISBLANK(H574), ISBLANK(I574), ISBLANK(J574) ), "", 1.5*SQRT( EXP(2.21*(F574-1)) + EXP(2.21*(G574-1)) + EXP(2.21*(H574-1)) + EXP(2.21*(I574-1)) + EXP(2.21*J574) )/100*2.45 ) -> 0.35859414
A575: =Packaging!AF39 -> Packaging | B575: =Packaging!AG39 -> 2019 | C575: =Packaging!AI39 -> LDPE | D575: =Packaging!AJ39 -> 4937.1369 | E575: Data based on EUROSTAT, polymer distribution based on Cimpan et al. (2021) | F575: 1 | G575: 1 | H575: 2 | I575: 1 | J575: 2 | K575: =IF( OR( ISBLANK(F575),ISBLANK(G575), ISBLANK(H575), ISBLANK(I575), ISBLANK(J575) ), "", 1.5*SQRT( EXP(2.21*(F575-1)) + EXP(2.21*(G575-1)) + EXP(2.21*(H575-1)) + EXP(2.21*(I575-1)) + EXP(2.21*J575) )/100*2.45 ) -> 0.35859414
A576: =Packaging!AF31 -> Packaging | B576: =Packaging!AG31 -> 2020 | C576: =Packaging!AI31 -> LDPE | D576: =Packaging!AJ31 -> 4998.8809 | E576: Data based on EUROSTAT, polymer distribution based on Cimpan et al. (2021) | F576: 1 | G576: 1 | H576: 2 | I576: 1 | J576: 2 | K576: =IF( OR( ISBLANK(F576),ISBLANK(G576), ISBLANK(H576), ISBLANK(I576), ISBLANK(J576) ), "", 1.5*SQRT( EXP(2.21*(F576-1)) + EXP(2.21*(G576-1)) + EXP(2.21*(H576-1)) + EXP(2.21*(I576-1)) + EXP(2.21*J576) )/100*2.45 ) -> 0.35859414
A577: =Packaging!AF23 -> Packaging | B577: =Packaging!AG23 -> 2021 | C577: =Packaging!AI23 -> LDPE | D577: =Packaging!AJ23 -> 5192.2995 | E577: Data based on EUROSTAT, polymer distribution based on Cimpan et al. (2021) | F577: 1 | G577: 1 | H577: 2 | I577: 1 | J577: 2 | K577: =IF( OR( ISBLANK(F577),ISBLANK(G577), ISBLANK(H577), ISBLANK(I577), ISBLANK(J577) ), "", 1.5*SQRT( EXP(2.21*(F577-1)) + EXP(2.21*(G577-1)) + EXP(2.21*(H577-1)) + EXP(2.21*(I577-1)) + EXP(2.21*J577) )/100*2.45 ) -> 0.35859414
A578: Paint | B578: 2019 | C578: Acryl | D578: 2326 | E578: Annex to 'Proposal for a regulation of the European Parliament and of the council on preventing plastic pellet losses to reduce microplastic pollution (European Commission) | F578: 1 | G578: 1 | H578: 3 | I578: 1 | J578: 2 | K578: =IF( OR( ISBLANK(F578),ISBLANK(G578), ISBLANK(H578), ISBLANK(I578), ISBLANK(J578) ), "", 1.5*SQRT( EXP(2.21*(F578-1)) + EXP(2.21*(G578-1)) + EXP(2.21*(H578-1)) + EXP(2.21*(I578-1)) + EXP(2.21*J578) )/100*2.45 ) -> 0.47802211
A579: Technical textiles | B579: 2017 | C579: LDPE | D579: 0 | E579: Textiles in Europe's circular economy — European Environment Agency (europa.eu) | F579: 1 | G579: 1 | H579: 3 | I579: 1 | J579: 2 | K579: =IF( OR( ISBLANK(F579),ISBLANK(G579), ISBLANK(H579), ISBLANK(I579), ISBLANK(J579) ), "", 1.5*SQRT( EXP(2.21*(F579-1)) + EXP(2.21*(G579-1)) + EXP(2.21*(H579-1)) + EXP(2.21*(I579-1)) + EXP(2.21*J579) )/100*2.45 ) -> 0.47802211 | L579: Calculated based on the total EU textile consumption (8351.04 kt) and the fractions for the different compartments at NL scale (see table above).
A580: Technical textiles | B580: 2017 | C580: HDPE | D580: 4 | E580: Textiles in Europe's circular economy — European Environment Agency (europa.eu) | F580: 1 | G580: 1 | H580: 3 | I580: 1 | J580: 2 | K580: =IF( OR( ISBLANK(F580),ISBLANK(G580), ISBLANK(H580), ISBLANK(I580), ISBLANK(J580) ), "", 1.5*SQRT( EXP(2.21*(F580-1)) + EXP(2.21*(G580-1)) + EXP(2.21*(H580-1)) + EXP(2.21*(I580-1)) + EXP(2.21*J580) )/100*2.45 ) -> 0.47802211 | L580: Calculated based on the total EU textile consumption (8351.04 kt) and the fractions for the different compartments at NL scale (see table above).
A581: Technical textiles | B581: 2017 | C581: PP | D581: 1903.3412 | E581: Textiles in Europe's circular economy — European Environment Agency (europa.eu) | F581: 1 | G581: 1 | H581: 3 | I581: 1 | J581: 2 | K581: =IF( OR( ISBLANK(F581),ISBLANK(G581), ISBLANK(H581), ISBLANK(I581), ISBLANK(J581) ), "", 1.5*SQRT( EXP(2.21*(F581-1)) + EXP(2.21*(G581-1)) + EXP(2.21*(H581-1)) + EXP(2.21*(I581-1)) + EXP(2.21*J581) )/100*2.45 ) -> 0.47802211 | L581: Calculated based on the total EU textile consumption (8351.04 kt) and the fractions for the different compartments at NL scale (see table above).
A582: Technical textiles | B582: 2017 | C582: PS | D582: 0 | E582: Textiles in Europe's circular economy — European Environment Agency (europa.eu) | F582: 1 | G582: 1 | H582: 3 | I582: 1 | J582: 2 | K582: =IF( OR( ISBLANK(F582),ISBLANK(G582), ISBLANK(H582), ISBLANK(I582), ISBLANK(J582) ), "", 1.5*SQRT( EXP(2.21*(F582-1)) + EXP(2.21*(G582-1)) + EXP(2.21*(H582-1)) + EXP(2.21*(I582-1)) + EXP(2.21*J582) )/100*2.45 ) -> 0.47802211 | L582: Calculated based on the total EU textile consumption (8351.04 kt) and the fractions for the different compartments at NL scale (see table above).
A583: Technical textiles | B583: 2017 | C583: EPS | D583: 0 | E583: Textiles in Europe's circular economy — European Environment Agency (europa.eu) | F583: 1 | G583: 1 | H583: 3 | I583: 1 | J583: 2 | K583: =IF( OR( ISBLANK(F583),ISBLANK(G583), ISBLANK(H583), ISBLANK(I583), ISBLANK(J583) ), "", 1.5*SQRT( EXP(2.21*(F583-1)) + EXP(2.21*(G583-1)) + EXP(2.21*(H583-1)) + EXP(2.21*(I583-1)) + EXP(2.21*J583) )/100*2.45 ) -> 0.47802211 | L583: Calculated based on the total EU textile consumption (8351.04 kt) and the fractions for the different compartments at NL scale (see table above).
A584: Technical textiles | B584: 2017 | C584: PVC | D584: 208.87861 | E584: Textiles in Europe's circular economy — European Environment Agency (europa.eu) | F584: 1 | G584: 1 | H584: 3 | I584: 1 | J584: 2 | K584: =IF( OR( ISBLANK(F584),ISBLANK(G584), ISBLANK(H584), ISBLANK(I584), ISBLANK(J584) ), "", 1.5*SQRT( EXP(2.21*(F584-1)) + EXP(2.21*(G584-1)) + EXP(2.21*(H584-1)) + EXP(2.21*(I584-1)) + EXP(2.21*J584) )/100*2.45 ) -> 0.47802211 | L584: Calculated based on the total EU textile consumption (8351.04 kt) and the fractions for the different compartments at NL scale (see table above).
A585: Technical textiles | B585: 2017 | C585: PET | D585: 1840.5619 | E585: Textiles in Europe's circular economy — European Environment Agency (europa.eu) | F585: 1 | G585: 1 | H585: 3 | I585: 1 | J585: 2 | K585: =IF( OR( ISBLANK(F585),ISBLANK(G585), ISBLANK(H585), ISBLANK(I585), ISBLANK(J585) ), "", 1.5*SQRT( EXP(2.21*(F585-1)) + EXP(2.21*(G585-1)) + EXP(2.21*(H585-1)) + EXP(2.21*(I585-1)) + EXP(2.21*J585) )/100*2.45 ) -> 0.47802211 | L585: Calculated based on the total EU textile consumption (8351.04 kt) and the fractions for the different compartments at NL scale (see table above).
A586: Technical textiles | B586: 2017 | C586: PA | D586: 2388.6652 | E586: Textiles in Europe's circular economy — European Environment Agency (europa.eu) | F586: 1 | G586: 1 | H586: 3 | I586: 1 | J586: 2 | K586: =IF( OR( ISBLANK(F586),ISBLANK(G586), ISBLANK(H586), ISBLANK(I586), ISBLANK(J586) ), "", 1.5*SQRT( EXP(2.21*(F586-1)) + EXP(2.21*(G586-1)) + EXP(2.21*(H586-1)) + EXP(2.21*(I586-1)) + EXP(2.21*J586) )/100*2.45 ) -> 0.47802211 | L586: Calculated based on the total EU textile consumption (8351.04 kt) and the fractions for the different compartments at NL scale (see table above).
A587: Technical textiles | B587: 2017 | C587: Acryl | D587: 403.5071 | E587: Textiles in Europe's circular economy — European Environment Agency (europa.eu) | F587: 1 | G587: 1 | H587: 3 | I587: 1 | J587: 2 | K587: =IF( OR( ISBLANK(F587),ISBLANK(G587), ISBLANK(H587), ISBLANK(I587), ISBLANK(J587) ), "", 1.5*SQRT( EXP(2.21*(F587-1)) + EXP(2.21*(G587-1)) + EXP(2.21*(H587-1)) + EXP(2.21*(I587-1)) + EXP(2.21*J587) )/100*2.45 ) -> 0.47802211 | L587: Calculated based on the total EU textile consumption (8351.04 kt) and the fractions for the different compartments at NL scale (see table above).
A588: ='Tyre wear'!B46 -> Tyre wear | B588: ='Tyre wear'!C46 -> 1990 | C588: ='Tyre wear'!D46 -> RUBBER | D588: ='Tyre wear'!E46 -> 274.36552 | E588: ='Tyre wear'!F46 -> LOW - Scaling from NL to EU using population | F588: ='Tyre wear'!G46 -> 1 | G588: ='Tyre wear'!H46 -> 1 | H588: ='Tyre wear'!I46 -> 1 | ... K588: ='Tyre wear'!L46 -> 0.21607442
A589: ='Tyre wear'!B47 -> Tyre wear | B589: ='Tyre wear'!C47 -> 1995 | C589: ='Tyre wear'!D47 -> RUBBER | D589: ='Tyre wear'!E47 -> 289.04881 | E589: ='Tyre wear'!F47 -> LOW - Scaling from NL to EU using population | F589: ='Tyre wear'!G47 -> 1 | G589: ='Tyre wear'!H47 -> 1 | H589: ='Tyre wear'!I47 -> 1 | ... K589: ='Tyre wear'!L47 -> 0.21607442
A590: ='Tyre wear'!B53 -> Tyre wear | B590: ='Tyre wear'!C53 -> 2020 | C590: ='Tyre wear'!D53 -> RUBBER | D590: ='Tyre wear'!E53 -> 299.66902 | E590: ='Tyre wear'!F53 -> LOW - Scaling from NL to EU using population | F590: ='Tyre wear'!G53 -> 1 | G590: ='Tyre wear'!H53 -> 1 | H590: ='Tyre wear'!I53 -> 1 | ... K590: ='Tyre wear'!L53 -> 0.21607442
A591: ='Tyre wear'!B48 -> Tyre wear | B591: ='Tyre wear'!C48 -> 2000 | C591: ='Tyre wear'!D48 -> RUBBER | D591: ='Tyre wear'!E48 -> 315.12798 | E591: ='Tyre wear'!F48 -> LOW - Scaling from NL to EU using population | F591: ='Tyre wear'!G48 -> 1 | G591: ='Tyre wear'!H48 -> 1 | H591: ='Tyre wear'!I48 -> 1 | ... K591: ='Tyre wear'!L48 -> 0.21607442
A592: ='Tyre wear'!B49 -> Tyre wear | B592: ='Tyre wear'!C49 -> 2005 | C592: ='Tyre wear'!D49 -> RUBBER | D592: ='Tyre wear'!E49 -> 330.49692 | E592: ='Tyre wear'!F49 -> LOW - Scaling from NL to EU using population | F592: ='Tyre wear'!G49 -> 1 | G592: ='Tyre wear'!H49 -> 1 | H592: ='Tyre wear'!I49 -> 1 | ... K592: ='Tyre wear'!L49 -> 0.21607442
A593: ='Tyre wear'!B51 -> Tyre wear | B593: ='Tyre wear'!C51 -> 2015 | C593: ='Tyre wear'!D51 -> RUBBER | D593: ='Tyre wear'!E51 -> 333.36119 | E593: ='Tyre wear'!F51 -> LOW - Scaling from NL to EU using population | F593: ='Tyre wear'!G51 -> 1 | G593: ='Tyre wear'!H51 -> 1 | H593: ='Tyre wear'!I51 -> 1 | ... K593: ='Tyre wear'!L51 -> 0.21607442
A594: ='Tyre wear'!B50 -> Tyre wear | B594: ='Tyre wear'!C50 -> 2010 | C594: ='Tyre wear'!D50 -> RUBBER | D594: ='Tyre wear'!E50 -> 333.95978 | E594: ='Tyre wear'!F50 -> LOW - Scaling from NL to EU using population | F594: ='Tyre wear'!G50 -> 1 | G594: ='Tyre wear'!H50 -> 1 | H594: ='Tyre wear'!I50 -> 1 | ... K594: ='Tyre wear'!L50 -> 0.21607442
A595: ='Tyre wear'!B52 -> Tyre wear | B595: ='Tyre wear'!C52 -> 2019 | C595: ='Tyre wear'!D52 -> RUBBER | D595: ='Tyre wear'!E52 -> 347.52849 | E595: ='Tyre wear'!F52 -> LOW - Scaling from NL to EU using population | F595: ='Tyre wear'!G52 -> 1 | G595: ='Tyre wear'!H52 -> 1 | H595: ='Tyre wear'!I52 -> 1 | ... K595: ='Tyre wear'!L52 -> 0.21607442
A596: ='Tyre wear'!B55 -> Tyre wear | B596: ='Tyre wear'!C55 -> 1990 | C596: ='Tyre wear'!D55 -> RUBBER | D596: ='Tyre wear'!E55 -> 505.23406 | E596: ='Tyre wear'!F55 -> HIGH - Scaling from NL to EU using population | F596: ='Tyre wear'!G55 -> 1 | G596: ='Tyre wear'!H55 -> 1 | H596: ='Tyre wear'!I55 -> 1 | ... J596: ='Tyre wear'!K55 -> 2 | K596: 0.61786152
A597: ='Tyre wear'!B56 -> Tyre wear | B597: ='Tyre wear'!C56 -> 1995 | C597: ='Tyre wear'!D56 -> RUBBER | D597: ='Tyre wear'!E56 -> 532.27281 | E597: ='Tyre wear'!F56 -> HIGH - Scaling from NL to EU using population | F597: ='Tyre wear'!G56 -> 1 | G597: ='Tyre wear'!H56 -> 1 | H597: ='Tyre wear'!I56 -> 1 | ... J597: ='Tyre wear'!K56 -> 2 | K597: 0.61786152
A598: ='Tyre wear'!B62 -> Tyre wear | B598: ='Tyre wear'!C62 -> 2020 | C598: ='Tyre wear'!D62 -> RUBBER | D598: ='Tyre wear'!E62 -> 551.82953 | E598: ='Tyre wear'!F62 -> HIGH - Scaling from NL to EU using population | F598: ='Tyre wear'!G62 -> 1 | G598: ='Tyre wear'!H62 -> 1 | H598: ='Tyre wear'!I62 -> 1 | ... J598: ='Tyre wear'!K62 -> 2 | K598: 0.61786152
A599: ='Tyre wear'!B57 -> Tyre wear | B599: ='Tyre wear'!C57 -> 2000 | C599: ='Tyre wear'!D57 -> RUBBER | D599: ='Tyre wear'!E57 -> 580.29665 | E599: ='Tyre wear'!F57 -> HIGH - Scaling from NL to EU using population | F599: ='Tyre wear'!G57 -> 1 | G599: ='Tyre wear'!H57 -> 1 | H599: ='Tyre wear'!I57 -> 1 | ... J599: ='Tyre wear'!K57 -> 2 | K599: 0.61786152
...

Sheet Transfer coefficients
A1: From | B1: To | C1: Scale | D1: Material | E1: Data | F1: Priority | G1: Source | H1: Geo NL | I1: Geo EU | J1: Temp | K1: Mat | L1: Tech | M1: Rel | N1: Spread NL | O1: Spread EU | P1: Comments
A2: =Agriculture!A92 -> Agriculture | B2: =Agriculture!B92 -> Agricultural greenhouse films (discarded) | C2: =Agriculture!C92 -> NL | D2: =Agriculture!D92 -> PVC | E2: =Agriculture!E92 -> 0.062695658 | F2: =Agriculture!F92 -> 1 | G2: =Agriculture!G92 -> Urbanus, J.H., Brunner, A., Boersma, A., Henke, S., Kooter, I., Lensen, S., Parker, L., Schwarz, A., Imhof, P., Dortmans, A., Wijngaard, M., 2022. Autobanden, verpakkingen en landbouwfolie zijn in Nederland de grootste bronnen van microplastics. TNO. | H2: 1 | J2: 2 | K2: 1 | L2: 1 | M2: 2 | N2: =IF( OR( ISBLANK(H2),ISBLANK(J2), ISBLANK(K2), ISBLANK(L2), ISBLANK(M2) ), "", 1.5*SQRT( EXP(2.21*(H2-1)) + EXP(2.21*(J2-1)) + EXP(2.21*(K2-1)) + EXP(2.21*(L2-1)) + EXP(2.21*M2) )/100*2.45 ) -> 0.35859414 | O2: =IF( OR( ISBLANK(I2),ISBLANK(J2), ISBLANK(K2), ISBLANK(L2), ISBLANK(M2) ), "", 1.5*SQRT( EXP(2.21*(I2-1)) + EXP(2.21*(J2-1)) + EXP(2.21*(K2-1)) + EXP(2.21*(L2-1)) + EXP(2.21*M2) )/100*2.45 )
A3: =Agriculture!A93 -> Agriculture | B3: =Agriculture!B93 -> Agricultural greenhouse films (discarded) | C3: =Agriculture!C93 -> NL | D3: =Agriculture!D93 -> PS | E3: =Agriculture!E93 -> 0 | F3: =Agriculture!F93 -> 1 | G3: =Agriculture!G93 -> Urbanus, J.H., Brunner, A., Boersma, A., Henke, S., Kooter, I., Lensen, S., Parker, L., Schwarz, A., Imhof, P., Dortmans, A., Wijngaard, M., 2022. Autobanden, verpakkingen en landbouwfolie zijn in Nederland de grootste bronnen van microplastics. TNO. | H3: 1 | J3: 2 | K3: 1 | L3: 1 | M3: 2 | N3: =IF( OR( ISBLANK(H3),ISBLANK(J3), ISBLANK(K3), ISBLANK(L3), ISBLANK(M3) ), "", 1.5*SQRT( EXP(2.21*(H3-1)) + EXP(2.21*(J3-1)) + EXP(2.21*(K3-1)) + EXP(2.21*(L3-1)) + EXP(2.21*M3) )/100*2.45 ) -> 0.35859414 | O3: =IF( OR( ISBLANK(I3),ISBLANK(J3), ISBLANK(K3), ISBLANK(L3), ISBLANK(M3) ), "", 1.5*SQRT( EXP(2.21*(I3-1)) + EXP(2.21*(J3-1)) + EXP(2.21*(K3-1)) + EXP(2.21*(L3-1)) + EXP(2.21*M3) )/100*2.45 )
A4: =Agriculture!A94 -> Agriculture | B4: =Agriculture!B94 -> Agricultural greenhouse films (discarded) | C4: =Agriculture!C94 -> NL | D4: =Agriculture!D94 -> PP | E4: =Agriculture!E94 -> 0 | F4: =Agriculture!F94 -> 1 | G4: =Agriculture!G94 -> Urbanus, J.H., Brunner, A., Boersma, A., Henke, S., Kooter, I., Lensen, S., Parker, L., Schwarz, A., Imhof, P., Dortmans, A., Wijngaard, M., 2022. Autobanden, verpakkingen en landbouwfolie zijn in Nederland de grootste bronnen van microplastics. TNO. | H4: 1 | J4: 2 | K4: 1 | L4: 1 | M4: 2 | N4: =IF( OR( ISBLANK(H4),ISBLANK(J4), ISBLANK(K4), ISBLANK(L4), ISBLANK(M4) ), "", 1.5*SQRT( EXP(2.21*(H4-1)) + EXP(2.21*(J4-1)) + EXP(2.21*(K4-1)) + EXP(2.21*(L4-1)) + EXP(2.21*M4) )/100*2.45 ) -> 0.35859414 | O4: =IF( OR( ISBLANK(I4),ISBLANK(J4), ISBLANK(K4), ISBLANK(L4), ISBLANK(M4) ), "", 1.5*SQRT( EXP(2.21*(I4-1)) + EXP(2.21*(J4-1)) + EXP(2.21*(K4-1)) + EXP(2.21*(L4-1)) + EXP(2.21*M4) )/100*2.45 )
A5: =Agriculture!A95 -> Agriculture | B5: =Agriculture!B95 -> Agricultural greenhouse films (discarded) | C5: =Agriculture!C95 -> NL | D5: =Agriculture!D95 -> LDPE | E5: =Agriculture!E95 -> 0.13959893 | F5: =Agriculture!F95 -> 1 | G5: =Agriculture!G95 -> Urbanus, J.H., Brunner, A., Boersma, A., Henke, S., Kooter, I., Lensen, S., Parker, L., Schwarz, A., Imhof, P., Dortmans, A., Wijngaard, M., 2022. Autobanden, verpakkingen en landbouwfolie zijn in Nederland de grootste bronnen van microplastics. TNO. | H5: 1 | J5: 2 | K5: 1 | L5: 1 | M5: 2 | N5: =IF( OR( ISBLANK(H5),ISBLANK(J5), ISBLANK(K5), ISBLANK(L5), ISBLANK(M5) ), "", 1.5*SQRT( EXP(2.21*(H5-1)) + EXP(2.21*(J5-1)) + EXP(2.21*(K5-1)) + EXP(2.21*(L5-1)) + EXP(2.21*M5) )/100*2.45 ) -> 0.35859414 | O5: =IF( OR( ISBLANK(I5),ISBLANK(J5), ISBLANK(K5), ISBLANK(L5), ISBLANK(M5) ), "", 1.5*SQRT( EXP(2.21*(I5-1)) + EXP(2.21*(J5-1)) + EXP(2.21*(K5-1)) + EXP(2.21*(L5-1)) + EXP(2.21*M5) )/100*2.45 )
A6: =Agriculture!A96 -> Agriculture | B6: =Agriculture!B96 -> Agricultural greenhouse films (discarded) | C6: =Agriculture!C96 -> NL | D6: =Agriculture!D96 -> HDPE | E6: =Agriculture!E96 -> 0 | F6: =Agriculture!F96 -> 1 | G6: =Agriculture!G96 -> Urbanus, J.H., Brunner, A., Boersma, A., Henke, S., Kooter, I., Lensen, S., Parker, L., Schwarz, A., Imhof, P., Dortmans, A., Wijngaard, M., 2022. Autobanden, verpakkingen en landbouwfolie zijn in Nederland de grootste bronnen van microplastics. TNO. | H6: 1 | J6: 2 | K6: 1 | L6: 1 | M6: 2 | N6: =IF( OR( ISBLANK(H6),ISBLANK(J6), ISBLANK(K6), ISBLANK(L6), ISBLANK(M6) ), "", 1.5*SQRT( EXP(2.21*(H6-1)) + EXP(2.21*(J6-1)) + EXP(2.21*(K6-1)) + EXP(2.21*(L6-1)) + EXP(2.21*M6) )/100*2.45 ) -> 0.35859414 | O6: =IF( OR( ISBLANK(I6),ISBLANK(J6), ISBLANK(K6), ISBLANK(L6), ISBLANK(M6) ), "", 1.5*SQRT( EXP(2.21*(I6-1)) + EXP(2.21*(J6-1)) + EXP(2.21*(K6-1)) + EXP(2.21*(L6-1)) + EXP(2.21*M6) )/100*2.45 )
A7: =Agriculture!A97 -> Agriculture | B7: =Agriculture!B97 -> Agricultural greenhouse films (discarded) | C7: =Agriculture!C97 -> EU | D7: =Agriculture!D97 -> PVC | E7: =Agriculture!E97 -> 0.09115863 | F7: =Agriculture!F97 -> 1 | G7: =Agriculture!G97 -> Assessment of agricultural plastics and their sustainability: A call for action, 2021. . FAO. https://doi.org/10.4060/cb7856en | I7: 1 | J7: 2 | K7: 1 | L7: 1 | M7: 2 | N7: =IF( OR( ISBLANK(H7),ISBLANK(J7), ISBLANK(K7), ISBLANK(L7), ISBLANK(M7) ), "", 1.5*SQRT( EXP(2.21*(H7-1)) + EXP(2.21*(J7-1)) + EXP(2.21*(K7-1)) + EXP(2.21*(L7-1)) + EXP(2.21*M7) )/100*2.45 ) | O7: =IF( OR( ISBLANK(I7),ISBLANK(J7), ISBLANK(K7), ISBLANK(L7), ISBLANK(M7) ), "", 1.5*SQRT( EXP(2.21*(I7-1)) + EXP(2.21*(J7-1)) + EXP(2.21*(K7-1)) + EXP(2.21*(L7-1)) + EXP(2.21*M7) )/100*2.45 ) -> 0.35859414
A8: =Agriculture!A98 -> Agriculture | B8: =Agriculture!B98 -> Agricultural greenhouse films (discarded) | C8: =Agriculture!C98 -> EU | D8: =Agriculture!D98 -> PS | E8: =Agriculture!E98 -> 0 | F8: =Agriculture!F98 -> 1 | G8: =Agriculture!G98 -> Assessment of agricultural plastics and their sustainability: A call for action, 2021. . FAO. https://doi.org/10.4060/cb7856en | I8: 1 | J8: 2 | K8: 1 | L8: 1 | M8: 2 | N8: =IF( OR( ISBLANK(H8),ISBLANK(J8), ISBLANK(K8), ISBLANK(L8), ISBLANK(M8) ), "", 1.5*SQRT( EXP(2.21*(H8-1)) + EXP(2.21*(J8-1)) + EXP(2.21*(K8-1)) + EXP(2.21*(L8-1)) + EXP(2.21*M8) )/100*2.45 ) | O8: =IF( OR( ISBLANK(I8),ISBLANK(J8), ISBLANK(K8), ISBLANK(L8), ISBLANK(M8) ), "", 1.5*SQRT( EXP(2.21*(I8-1)) + EXP(2.21*(J8-1)) + EXP(2.21*(K8-1)) + EXP(2.21*(L8-1)) + EXP(2.21*M8) )/100*2.45 ) -> 0.35859414
A9: =Agriculture!A99 -> Agriculture | B9: =Agriculture!B99 -> Agricultural greenhouse films (discarded) | C9: =Agriculture!C99 -> EU | D9: =Agriculture!D99 -> PP | E9: =Agriculture!E99 -> 0 | F9: =Agriculture!F99 -> 1 | G9: =Agriculture!G99 -> Assessment of agricultural plastics and their sustainability: A call for action, 2021. . FAO. https://doi.org/10.4060/cb7856en | I9: 1 | J9: 2 | K9: 1 | L9: 1 | M9: 2 | N9: =IF( OR( ISBLANK(H9),ISBLANK(J9), ISBLANK(K9), ISBLANK(L9), ISBLANK(M9) ), "", 1.5*SQRT( EXP(2.21*(H9-1)) + EXP(2.21*(J9-1)) + EXP(2.21*(K9-1)) + EXP(2.21*(L9-1)) + EXP(2.21*M9) )/100*2.45 ) | O9: =IF( OR( ISBLANK(I9),ISBLANK(J9), ISBLANK(K9), ISBLANK(L9), ISBLANK(M9) ), "", 1.5*SQRT( EXP(2.21*(I9-1)) + EXP(2.21*(J9-1)) + EXP(2.21*(K9-1)) + EXP(2.21*(L9-1)) + EXP(2.21*M9) )/100*2.45 ) -> 0.35859414
A10: =Agriculture!A100 -> Agriculture | B10: =Agriculture!B100 -> Agricultural greenhouse films (discarded) | C10: =Agriculture!C100 -> EU | D10: =Agriculture!D100 -> LDPE | E10: =Agriculture!E100 -> 0.1567895 | F10: =Agriculture!F100 -> 1 | G10: =Agriculture!G100 -> Assessment of agricultural plastics and their sustainability: A call for action, 2021. . FAO. https://doi.org/10.4060/cb7856en | I10: 1 | J10: 2 | K10: 1 | L10: 1 | M10: 2 | N10: =IF( OR( ISBLANK(H10),ISBLANK(J10), ISBLANK(K10), ISBLANK(L10), ISBLANK(M10) ), "", 1.5*SQRT( EXP(2.21*(H10-1)) + EXP(2.21*(J10-1)) + EXP(2.21*(K10-1)) + EXP(2.21*(L10-1)) + EXP(2.21*M10) )/100*2.45 ) | O10: =IF( OR( ISBLANK(I10),ISBLANK(J10), ISBLANK(K10), ISBLANK(L10), ISBLANK(M10) ), "", 1.5*SQRT( EXP(2.21*(I10-1)) + EXP(2.21*(J10-1)) + EXP(2.21*(K10-1)) + EXP(2.21*(L10-1)) + EXP(2.21*M10) )/100*2.45 ) -> 0.35859414
A11: =Agriculture!A101 -> Agriculture | B11: =Agriculture!B101 -> Agricultural greenhouse films (discarded) | C11: =Agriculture!C101 -> EU | D11: =Agriculture!D101 -> HDPE | E11: =Agriculture!E101 -> 0 | F11: =Agriculture!F101 -> 1 | G11: =Agriculture!G101 -> Assessment of agricultural plastics and their sustainability: A call for action, 2021. . FAO. https://doi.org/10.4060/cb7856en | I11: 1 | J11: 2 | K11: 1 | L11: 1 | M11: 2 | N11: =IF( OR( ISBLANK(H11),ISBLANK(J11), ISBLANK(K11), ISBLANK(L11), ISBLANK(M11) ), "", 1.5*SQRT( EXP(2.21*(H11-1)) + EXP(2.21*(J11-1)) + EXP(2.21*(K11-1)) + EXP(2.21*(L11-1)) + EXP(2.21*M11) )/100*2.45 ) | O11: =IF( OR( ISBLANK(I11),ISBLANK(J11), ISBLANK(K11), ISBLANK(L11), ISBLANK(M11) ), "", 1.5*SQRT( EXP(2.21*(I11-1)) + EXP(2.21*(J11-1)) + EXP(2.21*(K11-1)) + EXP(2.21*(L11-1)) + EXP(2.21*M11) )/100*2.45 ) -> 0.35859414
A12: =Agriculture!A72 -> Agriculture | B12: =Agriculture!B72 -> Agricultural greenhouse films (in use) | C12: =Agriculture!C72 -> NL | D12: =Agriculture!D72 -> PVC | E12: =Agriculture!E72 -> 0.0063729615 | F12: =Agriculture!F72 -> 2 | G12: =Agriculture!G72 -> Urbanus, J.H., Brunner, A., Boersma, A., Henke, S., Kooter, I., Lensen, S., Parker, L., Schwarz, A., Imhof, P., Dortmans, A., Wijngaard, M., 2022. Autobanden, verpakkingen en landbouwfolie zijn in Nederland de grootste bronnen van microplastics. TNO. | H12: 1 | J12: 2 | K12: 1 | L12: 1 | M12: 2 | N12: =IF( OR( ISBLANK(H12),ISBLANK(J12), ISBLANK(K12), ISBLANK(L12), ISBLANK(M12) ), "", 1.5*SQRT( EXP(2.21*(H12-1)) + EXP(2.21*(J12-1)) + EXP(2.21*(K12-1)) + EXP(2.21*(L12-1)) + EXP(2.21*M12) )/100*2.45 ) -> 0.35859414 | O12: =IF( OR( ISBLANK(I12),ISBLANK(J12), ISBLANK(K12), ISBLANK(L12), ISBLANK(M12) ), "", 1.5*SQRT( EXP(2.21*(I12-1)) + EXP(2.21*(J12-1)) + EXP(2.21*(K12-1)) + EXP(2.21*(L12-1)) + EXP(2.21*M12) )/100*2.45 )
A13: =Agriculture!A73 -> Agriculture | B13: =Agriculture!B73 -> Agricultural greenhouse films (in use) | C13: =Agriculture!C73 -> NL | D13: =Agriculture!D73 -> PS | E13: =Agriculture!E73 -> 0 | F13: =Agriculture!F73 -> 2 | G13: =Agriculture!G73 -> Urbanus, J.H., Brunner, A., Boersma, A., Henke, S., Kooter, I., Lensen, S., Parker, L., Schwarz, A., Imhof, P., Dortmans, A., Wijngaard, M., 2022. Autobanden, verpakkingen en landbouwfolie zijn in Nederland de grootste bronnen van microplastics. TNO. | H13: 1 | J13: 2 | K13: 1 | L13: 1 | M13: 2 | N13: =IF( OR( ISBLANK(H13),ISBLANK(J13), ISBLANK(K13), ISBLANK(L13), ISBLANK(M13) ), "", 1.5*SQRT( EXP(2.21*(H13-1)) + EXP(2.21*(J13-1)) + EXP(2.21*(K13-1)) + EXP(2.21*(L13-1)) + EXP(2.21*M13) )/100*2.45 ) -> 0.35859414 | O13: =IF( OR( ISBLANK(I13),ISBLANK(J13), ISBLANK(K13), ISBLANK(L13), ISBLANK(M13) ), "", 1.5*SQRT( EXP(2.21*(I13-1)) + EXP(2.21*(J13-1)) + EXP(2.21*(K13-1)) + EXP(2.21*(L13-1)) + EXP(2.21*M13) )/100*2.45 )
A14: =Agriculture!A74 -> Agriculture | B14: =Agriculture!B74 -> Agricultural greenhouse films (in use) | C14: =Agriculture!C74 -> NL | D14: =Agriculture!D74 -> PP | E14: =Agriculture!E74 -> 0 | F14: =Agriculture!F74 -> 2 | G14: =Agriculture!G74 -> Urbanus, J.H., Brunner, A., Boersma, A., Henke, S., Kooter, I., Lensen, S., Parker, L., Schwarz, A., Imhof, P., Dortmans, A., Wijngaard, M., 2022. Autobanden, verpakkingen en landbouwfolie zijn in Nederland de grootste bronnen van microplastics. TNO. | H14: 1 | J14: 2 | K14: 1 | L14: 1 | M14: 2 | N14: =IF( OR( ISBLANK(H14),ISBLANK(J14), ISBLANK(K14), ISBLANK(L14), ISBLANK(M14) ), "", 1.5*SQRT( EXP(2.21*(H14-1)) + EXP(2.21*(J14-1)) + EXP(2.21*(K14-1)) + EXP(2.21*(L14-1)) + EXP(2.21*M14) )/100*2.45 ) -> 0.35859414 | O14: =IF( OR( ISBLANK(I14),ISBLANK(J14), ISBLANK(K14), ISBLANK(L14), ISBLANK(M14) ), "", 1.5*SQRT( EXP(2.21*(I14-1)) + EXP(2.21*(J14-1)) + EXP(2.21*(K14-1)) + EXP(2.21*(L14-1)) + EXP(2.21*M14) )/100*2.45 )
A15: =Agriculture!A75 -> Agriculture | B15: =Agriculture!B75 -> Agricultural greenhouse films (in use) | C15: =Agriculture!C75 -> NL | D15: =Agriculture!D75 -> LDPE | E15: =Agriculture!E75 -> 0.014190116 | F15: =Agriculture!F75 -> 2 | G15: =Agriculture!G75 -> Urbanus, J.H., Brunner, A., Boersma, A., Henke, S., Kooter, I., Lensen, S., Parker, L., Schwarz, A., Imhof, P., Dortmans, A., Wijngaard, M., 2022. Autobanden, verpakkingen en landbouwfolie zijn in Nederland de grootste bronnen van microplastics. TNO. | H15: 1 | J15: 2 | K15: 1 | L15: 1 | M15: 2 | N15: =IF( OR( ISBLANK(H15),ISBLANK(J15), ISBLANK(K15), ISBLANK(L15), ISBLANK(M15) ), "", 1.5*SQRT( EXP(2.21*(H15-1)) + EXP(2.21*(J15-1)) + EXP(2.21*(K15-1)) + EXP(2.21*(L15-1)) + EXP(2.21*M15) )/100*2.45 ) -> 0.35859414 | O15: =IF( OR( ISBLANK(I15),ISBLANK(J15), ISBLANK(K15), ISBLANK(L15), ISBLANK(M15) ), "", 1.5*SQRT( EXP(2.21*(I15-1)) + EXP(2.21*(J15-1)) + EXP(2.21*(K15-1)) + EXP(2.21*(L15-1)) + EXP(2.21*M15) )/100*2.45 )
A16: =Agriculture!A76 -> Agriculture | B16: =Agriculture!B76 -> Agricultural greenhouse films (in use) | C16: =Agriculture!C76 -> NL | D16: =Agriculture!D76 -> HDPE | E16: =Agriculture!E76 -> 0 | F16: =Agriculture!F76 -> 2 | G16: =Agriculture!G76 -> Urbanus, J.H., Brunner, A., Boersma, A., Henke, S., Kooter, I., Lensen, S., Parker, L., Schwarz, A., Imhof, P., Dortmans, A., Wijngaard, M., 2022. Autobanden, verpakkingen en landbouwfolie zijn in Nederland de grootste bronnen van microplastics. TNO. | H16: 1 | J16: 2 | K16: 1 | L16: 1 | M16: 2 | N16: =IF( OR( ISBLANK(H16),ISBLANK(J16), ISBLANK(K16), ISBLANK(L16), ISBLANK(M16) ), "", 1.5*SQRT( EXP(2.21*(H16-1)) + EXP(2.21*(J16-1)) + EXP(2.21*(K16-1)) + EXP(2.21*(L16-1)) + EXP(2.21*M16) )/100*2.45 ) -> 0.35859414 | O16: =IF( OR( ISBLANK(I16),ISBLANK(J16), ISBLANK(K16), ISBLANK(L16), ISBLANK(M16) ), "", 1.5*SQRT( EXP(2.21*(I16-1)) + EXP(2.21*(J16-1)) + EXP(2.21*(K16-1)) + EXP(2.21*(L16-1)) + EXP(2.21*M16) )/100*2.45 )
A17: =Agriculture!A77 -> Agriculture | B17: =Agriculture!B77 -> Agricultural greenhouse films (in use) | C17: =Agriculture!C77 -> EU | D17: =Agriculture!D77 -> PVC | E17: =Agriculture!E77 -> 0.009266199 | F17: =Agriculture!F77 -> 2 | G17: =Agriculture!G77 -> Assessment of agricultural plastics and their sustainability: A call for action, 2021. . FAO. https://doi.org/10.4060/cb7856en | I17: 1 | J17: 2 | K17: 1 | L17: 1 | M17: 2 | N17: =IF( OR( ISBLANK(H17),ISBLANK(J17), ISBLANK(K17), ISBLANK(L17), ISBLANK(M17) ), "", 1.5*SQRT( EXP(2.21*(H17-1)) + EXP(2.21*(J17-1)) + EXP(2.21*(K17-1)) + EXP(2.21*(L17-1)) + EXP(2.21*M17) )/100*2.45 ) | O17: =IF( OR( ISBLANK(I17),ISBLANK(J17), ISBLANK(K17), ISBLANK(L17), ISBLANK(M17) ), "", 1.5*SQRT( EXP(2.21*(I17-1)) + EXP(2.21*(J17-1)) + EXP(2.21*(K17-1)) + EXP(2.21*(L17-1)) + EXP(2.21*M17) )/100*2.45 ) -> 0.35859414
A18: =Agriculture!A78 -> Agriculture | B18: =Agriculture!B78 -> Agricultural greenhouse films (in use) | C18: =Agriculture!C78 -> EU | D18: =Agriculture!D78 -> PS | E18: =Agriculture!E78 -> 0 | F18: =Agriculture!F78 -> 2 | G18: =Agriculture!G78 -> Assessment of agricultural plastics and their sustainability: A call for action, 2021. . FAO. https://doi.org/10.4060/cb7856en | I18: 1 | J18: 2 | K18: 1 | L18: 1 | M18: 2 | N18: =IF( OR( ISBLANK(H18),ISBLANK(J18), ISBLANK(K18), ISBLANK(L18), ISBLANK(M18) ), "", 1.5*SQRT( EXP(2.21*(H18-1)) + EXP(2.21*(J18-1)) + EXP(2.21*(K18-1)) + EXP(2.21*(L18-1)) + EXP(2.21*M18) )/100*2.45 ) | O18: =IF( OR( ISBLANK(I18),ISBLANK(J18), ISBLANK(K18), ISBLANK(L18), ISBLANK(M18) ), "", 1.5*SQRT( EXP(2.21*(I18-1)) + EXP(2.21*(J18-1)) + EXP(2.21*(K18-1)) + EXP(2.21*(L18-1)) + EXP(2.21*M18) )/100*2.45 ) -> 0.35859414
A19: =Agriculture!A79 -> Agriculture | B19: =Agriculture!B79 -> Agricultural greenhouse films (in use) | C19: =Agriculture!C79 -> EU | D19: =Agriculture!D79 -> PP | E19: =Agriculture!E79 -> 0 | F19: =Agriculture!F79 -> 2 | G19: =Agriculture!G79 -> Assessment of agricultural plastics and their sustainability: A call for action, 2021. . FAO. https://doi.org/10.4060/cb7856en | I19: 1 | J19: 2 | K19: 1 | L19: 1 | M19: 2 | N19: =IF( OR( ISBLANK(H19),ISBLANK(J19), ISBLANK(K19), ISBLANK(L19), ISBLANK(M19) ), "", 1.5*SQRT( EXP(2.21*(H19-1)) + EXP(2.21*(J19-1)) + EXP(2.21*(K19-1)) + EXP(2.21*(L19-1)) + EXP(2.21*M19) )/100*2.45 ) | O19: =IF( OR( ISBLANK(I19),ISBLANK(J19), ISBLANK(K19), ISBLANK(L19), ISBLANK(M19) ), "", 1.5*SQRT( EXP(2.21*(I19-1)) + EXP(2.21*(J19-1)) + EXP(2.21*(K19-1)) + EXP(2.21*(L19-1)) + EXP(2.21*M19) )/100*2.45 ) -> 0.35859414
A20: =Agriculture!A80 -> Agriculture | B20: =Agriculture!B80 -> Agricultural greenhouse films (in use) | C20: =Agriculture!C80 -> EU | D20: =Agriculture!D80 -> LDPE | E20: =Agriculture!E80 -> 0.015937522 | F20: =Agriculture!F80 -> 2 | G20: =Agriculture!G80 -> Assessment of agricultural plastics and their sustainability: A call for action, 2021. . FAO. https://doi.org/10.4060/cb7856en | I20: 1 | J20: 2 | K20: 1 | L20: 1 | M20: 2 | N20: =IF( OR( ISBLANK(H20),ISBLANK(J20), ISBLANK(K20), ISBLANK(L20), ISBLANK(M20) ), "", 1.5*SQRT( EXP(2.21*(H20-1)) + EXP(2.21*(J20-1)) + EXP(2.21*(K20-1)) + EXP(2.21*(L20-1)) + EXP(2.21*M20) )/100*2.45 ) | O20: =IF( OR( ISBLANK(I20),ISBLANK(J20), ISBLANK(K20), ISBLANK(L20), ISBLANK(M20) ), "", 1.5*SQRT( EXP(2.21*(I20-1)) + EXP(2.21*(J20-1)) + EXP(2.21*(K20-1)) + EXP(2.21*(L20-1)) + EXP(2.21*M20) )/100*2.45 ) -> 0.35859414
A21: =Agriculture!A81 -> Agriculture | B21: =Agriculture!B81 -> Agricultural greenhouse films (in use) | C21: =Agriculture!C81 -> EU | D21: =Agriculture!D81 -> HDPE | E21: =Agriculture!E81 -> 0 | F21: =Agriculture!F81 -> 2 | G21: =Agriculture!G81 -> Assessment of agricultural plastics and their sustainability: A call for action, 2021. . FAO. https://doi.org/10.4060/cb7856en | I21: 1 | J21: 2 | K21: 1 | L21: 1 | M21: 2 | N21: =IF( OR( ISBLANK(H21),ISBLANK(J21), ISBLANK(K21), ISBLANK(L21), ISBLANK(M21) ), "", 1.5*SQRT( EXP(2.21*(H21-1)) + EXP(2.21*(J21-1)) + EXP(2.21*(K21-1)) + EXP(2.21*(L21-1)) + EXP(2.21*M21) )/100*2.45 ) | O21: =IF( OR( ISBLANK(I21),ISBLANK(J21), ISBLANK(K21), ISBLANK(L21), ISBLANK(M21) ), "", 1.5*SQRT( EXP(2.21*(I21-1)) + EXP(2.21*(J21-1)) + EXP(2.21*(K21-1)) + EXP(2.21*(L21-1)) + EXP(2.21*M21) )/100*2.45 ) -> 0.35859414
A22: =Agriculture!A102 -> Agriculture | B22: =Agriculture!B102 -> Agricultural mulching films | C22: =Agriculture!C102 -> NL | D22: =Agriculture!D102 -> PVC | E22: =Agriculture!E102 -> 0.27195769 | F22: =Agriculture!F102 -> 1 | G22: =Agriculture!G102 -> Urbanus, J.H., Brunner, A., Boersma, A., Henke, S., Kooter, I., Lensen, S., Parker, L., Schwarz, A., Imhof, P., Dortmans, A., Wijngaard, M., 2022. Autobanden, verpakkingen en landbouwfolie zijn in Nederland de grootste bronnen van microplastics. TNO. | H22: 1 | J22: 2 | K22: 1 | L22: 1 | M22: 2 | N22: =IF( OR( ISBLANK(H22),ISBLANK(J22), ISBLANK(K22), ISBLANK(L22), ISBLANK(M22) ), "", 1.5*SQRT( EXP(2.21*(H22-1)) + EXP(2.21*(J22-1)) + EXP(2.21*(K22-1)) + EXP(2.21*(L22-1)) + EXP(2.21*M22) )/100*2.45 ) -> 0.35859414 | O22: =IF( OR( ISBLANK(I22),ISBLANK(J22), ISBLANK(K22), ISBLANK(L22), ISBLANK(M22) ), "", 1.5*SQRT( EXP(2.21*(I22-1)) + EXP(2.21*(J22-1)) + EXP(2.21*(K22-1)) + EXP(2.21*(L22-1)) + EXP(2.21*M22) )/100*2.45 )
A23: =Agriculture!A103 -> Agriculture | B23: =Agriculture!B103 -> Agricultural mulching films | C23: =Agriculture!C103 -> NL | D23: =Agriculture!D103 -> PS | E23: =Agriculture!E103 -> 0 | F23: =Agriculture!F103 -> 1 | G23: =Agriculture!G103 -> Urbanus, J.H., Brunner, A., Boersma, A., Henke, S., Kooter, I., Lensen, S., Parker, L., Schwarz, A., Imhof, P., Dortmans, A., Wijngaard, M., 2022. Autobanden, verpakkingen en landbouwfolie zijn in Nederland de grootste bronnen van microplastics. TNO. | H23: 1 | J23: 2 | K23: 1 | L23: 1 | M23: 2 | N23: =IF( OR( ISBLANK(H23),ISBLANK(J23), ISBLANK(K23), ISBLANK(L23), ISBLANK(M23) ), "", 1.5*SQRT( EXP(2.21*(H23-1)) + EXP(2.21*(J23-1)) + EXP(2.21*(K23-1)) + EXP(2.21*(L23-1)) + EXP(2.21*M23) )/100*2.45 ) -> 0.35859414 | O23: =IF( OR( ISBLANK(I23),ISBLANK(J23), ISBLANK(K23), ISBLANK(L23), ISBLANK(M23) ), "", 1.5*SQRT( EXP(2.21*(I23-1)) + EXP(2.21*(J23-1)) + EXP(2.21*(K23-1)) + EXP(2.21*(L23-1)) + EXP(2.21*M23) )/100*2.45 )
A24: =Agriculture!A104 -> Agriculture | B24: =Agriculture!B104 -> Agricultural mulching films | C24: =Agriculture!C104 -> NL | D24: =Agriculture!D104 -> PP | E24: =Agriculture!E104 -> 0 | F24: =Agriculture!F104 -> 1 | G24: =Agriculture!G104 -> Urbanus, J.H., Brunner, A., Boersma, A., Henke, S., Kooter, I., Lensen, S., Parker, L., Schwarz, A., Imhof, P., Dortmans, A., Wijngaard, M., 2022. Autobanden, verpakkingen en landbouwfolie zijn in Nederland de grootste bronnen van microplastics. TNO. | H24: 1 | J24: 2 | K24: 1 | L24: 1 | M24: 2 | N24: =IF( OR( ISBLANK(H24),ISBLANK(J24), ISBLANK(K24), ISBLANK(L24), ISBLANK(M24) ), "", 1.5*SQRT( EXP(2.21*(H24-1)) + EXP(2.21*(J24-1)) + EXP(2.21*(K24-1)) + EXP(2.21*(L24-1)) + EXP(2.21*M24) )/100*2.45 ) -> 0.35859414 | O24: =IF( OR( ISBLANK(I24),ISBLANK(J24), ISBLANK(K24), ISBLANK(L24), ISBLANK(M24) ), "", 1.5*SQRT( EXP(2.21*(I24-1)) + EXP(2.21*(J24-1)) + EXP(2.21*(K24-1)) + EXP(2.21*(L24-1)) + EXP(2.21*M24) )/100*2.45 )
A25: =Agriculture!A105 -> Agriculture | B25: =Agriculture!B105 -> Agricultural mulching films | C25: =Agriculture!C105 -> NL | D25: =Agriculture!D105 -> LDPE | E25: =Agriculture!E105 -> 0.60554438 | F25: =Agriculture!F105 -> 1 | G25: =Agriculture!G105 -> Urbanus, J.H., Brunner, A., Boersma, A., Henke, S., Kooter, I., Lensen, S., Parker, L., Schwarz, A., Imhof, P., Dortmans, A., Wijngaard, M., 2022. Autobanden, verpakkingen en landbouwfolie zijn in Nederland de grootste bronnen van microplastics. TNO. | H25: 1 | J25: 2 | K25: 1 | L25: 1 | M25: 2 | N25: =IF( OR( ISBLANK(H25),ISBLANK(J25), ISBLANK(K25), ISBLANK(L25), ISBLANK(M25) ), "", 1.5*SQRT( EXP(2.21*(H25-1)) + EXP(2.21*(J25-1)) + EXP(2.21*(K25-1)) + EXP(2.21*(L25-1)) + EXP(2.21*M25) )/100*2.45 ) -> 0.35859414 | O25: =IF( OR( ISBLANK(I25),ISBLANK(J25), ISBLANK(K25), ISBLANK(L25), ISBLANK(M25) ), "", 1.5*SQRT( EXP(2.21*(I25-1)) + EXP(2.21*(J25-1)) + EXP(2.21*(K25-1)) + EXP(2.21*(L25-1)) + EXP(2.21*M25) )/100*2.45 )
A26: =Agriculture!A106 -> Agriculture | B26: =Agriculture!B106 -> Agricultural mulching films | C26: =Agriculture!C106 -> NL | D26: =Agriculture!D106 -> HDPE | E26: =Agriculture!E106 -> 0 | F26: =Agriculture!F106 -> 1 | G26: =Agriculture!G106 -> Urbanus, J.H., Brunner, A., Boersma, A., Henke, S., Kooter, I., Lensen, S., Parker, L., Schwarz, A., Imhof, P., Dortmans, A., Wijngaard, M., 2022. Autobanden, verpakkingen en landbouwfolie zijn in Nederland de grootste bronnen van microplastics. TNO. | H26: 1 | J26: 2 | K26: 1 | L26: 1 | M26: 2 | N26: =IF( OR( ISBLANK(H26),ISBLANK(J26), ISBLANK(K26), ISBLANK(L26), ISBLANK(M26) ), "", 1.5*SQRT( EXP(2.21*(H26-1)) + EXP(2.21*(J26-1)) + EXP(2.21*(K26-1)) + EXP(2.21*(L26-1)) + EXP(2.21*M26) )/100*2.45 ) -> 0.35859414 | O26: =IF( OR( ISBLANK(I26),ISBLANK(J26), ISBLANK(K26), ISBLANK(L26), ISBLANK(M26) ), "", 1.5*SQRT( EXP(2.21*(I26-1)) + EXP(2.21*(J26-1)) + EXP(2.21*(K26-1)) + EXP(2.21*(L26-1)) + EXP(2.21*M26) )/100*2.45 )
A27: =Agriculture!A107 -> Agriculture | B27: =Agriculture!B107 -> Agricultural mulching films | C27: =Agriculture!C107 -> EU | D27: =Agriculture!D107 -> PVC | E27: =Agriculture!E107 -> 0.39542276 | F27: =Agriculture!F107 -> 1 | G27: =Agriculture!G107 -> Assessment of agricultural plastics and their sustainability: A call for action, 2021. . FAO. https://doi.org/10.4060/cb7856en | I27: 1 | J27: 2 | K27: 1 | L27: 1 | M27: 2 | N27: =IF( OR( ISBLANK(H27),ISBLANK(J27), ISBLANK(K27), ISBLANK(L27), ISBLANK(M27) ), "", 1.5*SQRT( EXP(2.21*(H27-1)) + EXP(2.21*(J27-1)) + EXP(2.21*(K27-1)) + EXP(2.21*(L27-1)) + EXP(2.21*M27) )/100*2.45 ) | O27: =IF( OR( ISBLANK(I27),ISBLANK(J27), ISBLANK(K27), ISBLANK(L27), ISBLANK(M27) ), "", 1.5*SQRT( EXP(2.21*(I27-1)) + EXP(2.21*(J27-1)) + EXP(2.21*(K27-1)) + EXP(2.21*(L27-1)) + EXP(2.21*M27) )/100*2.45 ) -> 0.35859414
A28: =Agriculture!A108 -> Agriculture | B28: =Agriculture!B108 -> Agricultural mulching films | C28: =Agriculture!C108 -> EU | D28: =Agriculture!D108 -> PS | E28: =Agriculture!E108 -> 0 | F28: =Agriculture!F108 -> 1 | G28: =Agriculture!G108 -> Assessment of agricultural plastics and their sustainability: A call for action, 2021. . FAO. https://doi.org/10.4060/cb7856en | I28: 1 | J28: 2 | K28: 1 | L28: 1 | M28: 2 | N28: =IF( OR( ISBLANK(H28),ISBLANK(J28), ISBLANK(K28), ISBLANK(L28), ISBLANK(M28) ), "", 1.5*SQRT( EXP(2.21*(H28-1)) + EXP(2.21*(J28-1)) + EXP(2.21*(K28-1)) + EXP(2.21*(L28-1)) + EXP(2.21*M28) )/100*2.45 ) | O28: =IF( OR( ISBLANK(I28),ISBLANK(J28), ISBLANK(K28), ISBLANK(L28), ISBLANK(M28) ), "", 1.5*SQRT( EXP(2.21*(I28-1)) + EXP(2.21*(J28-1)) + EXP(2.21*(K28-1)) + EXP(2.21*(L28-1)) + EXP(2.21*M28) )/100*2.45 ) -> 0.35859414
A29: =Agriculture!A109 -> Agriculture | B29: =Agriculture!B109 -> Agricultural mulching films | C29: =Agriculture!C109 -> EU | D29: =Agriculture!D109 -> PP | E29: =Agriculture!E109 -> 0 | F29: =Agriculture!F109 -> 1 | G29: =Agriculture!G109 -> Assessment of agricultural plastics and their sustainability: A call for action, 2021. . FAO. https://doi.org/10.4060/cb7856en | I29: 1 | J29: 2 | K29: 1 | L29: 1 | M29: 2 | N29: =IF( OR( ISBLANK(H29),ISBLANK(J29), ISBLANK(K29), ISBLANK(L29), ISBLANK(M29) ), "", 1.5*SQRT( EXP(2.21*(H29-1)) + EXP(2.21*(J29-1)) + EXP(2.21*(K29-1)) + EXP(2.21*(L29-1)) + EXP(2.21*M29) )/100*2.45 ) | O29: =IF( OR( ISBLANK(I29),ISBLANK(J29), ISBLANK(K29), ISBLANK(L29), ISBLANK(M29) ), "", 1.5*SQRT( EXP(2.21*(I29-1)) + EXP(2.21*(J29-1)) + EXP(2.21*(K29-1)) + EXP(2.21*(L29-1)) + EXP(2.21*M29) )/100*2.45 ) -> 0.35859414
A30: =Agriculture!A110 -> Agriculture | B30: =Agriculture!B110 -> Agricultural mulching films | C30: =Agriculture!C110 -> EU | D30: =Agriculture!D110 -> LDPE | E30: =Agriculture!E110 -> 0.68011265 | F30: =Agriculture!F110 -> 1 | G30: =Agriculture!G110 -> Assessment of agricultural plastics and their sustainability: A call for action, 2021. . FAO. https://doi.org/10.4060/cb7856en | I30: 1 | J30: 2 | K30: 1 | L30: 1 | M30: 2 | N30: =IF( OR( ISBLANK(H30),ISBLANK(J30), ISBLANK(K30), ISBLANK(L30), ISBLANK(M30) ), "", 1.5*SQRT( EXP(2.21*(H30-1)) + EXP(2.21*(J30-1)) + EXP(2.21*(K30-1)) + EXP(2.21*(L30-1)) + EXP(2.21*M30) )/100*2.45 ) | O30: =IF( OR( ISBLANK(I30),ISBLANK(J30), ISBLANK(K30), ISBLANK(L30), ISBLANK(M30) ), "", 1.5*SQRT( EXP(2.21*(I30-1)) + EXP(2.21*(J30-1)) + EXP(2.21*(K30-1)) + EXP(2.21*(L30-1)) + EXP(2.21*M30) )/100*2.45 ) -> 0.35859414
A31: =Agriculture!A111 -> Agriculture | B31: =Agriculture!B111 -> Agricultural mulching films | C31: =Agriculture!C111 -> EU | D31: =Agriculture!D111 -> HDPE | E31: =Agriculture!E111 -> 0 | F31: =Agriculture!F111 -> 1 | G31: =Agriculture!G111 -> Assessment of agricultural plastics and their sustainability: A call for action, 2021. . FAO. https://doi.org/10.4060/cb7856en | I31: 1 | J31: 2 | K31: 1 | L31: 1 | M31: 2 | N31: =IF( OR( ISBLANK(H31),ISBLANK(J31), ISBLANK(K31), ISBLANK(L31), ISBLANK(M31) ), "", 1.5*SQRT( EXP(2.21*(H31-1)) + EXP(2.21*(J31-1)) + EXP(2.21*(K31-1)) + EXP(2.21*(L31-1)) + EXP(2.21*M31) )/100*2.45 ) | O31: =IF( OR( ISBLANK(I31),ISBLANK(J31), ISBLANK(K31), ISBLANK(L31), ISBLANK(M31) ), "", 1.5*SQRT( EXP(2.21*(I31-1)) + EXP(2.21*(J31-1)) + EXP(2.21*(K31-1)) + EXP(2.21*(L31-1)) + EXP(2.21*M31) )/100*2.45 ) -> 0.35859414
A32: =Agriculture!A62 -> Agriculture | B32: =Agriculture!B62 -> Agricultural other | C32: =Agriculture!C62 -> NL | D32: =Agriculture!D62 -> PVC | E32: =Agriculture!E62 -> 0.21920245 | F32: =Agriculture!F62 -> 2 | G32: =Agriculture!G62 -> Urbanus, J.H., Brunner, A., Boersma, A., Henke, S., Kooter, I., Lensen, S., Parker, L., Schwarz, A., Imhof, P., Dortmans, A., Wijngaard, M., 2022. Autobanden, verpakkingen en landbouwfolie zijn in Nederland de grootste bronnen van microplastics. TNO. | H32: 1 | J32: 2 | K32: 1 | L32: 1 | M32: 2 | N32: =IF( OR( ISBLANK(H32),ISBLANK(J32), ISBLANK(K32), ISBLANK(L32), ISBLANK(M32) ), "", 1.5*SQRT( EXP(2.21*(H32-1)) + EXP(2.21*(J32-1)) + EXP(2.21*(K32-1)) + EXP(2.21*(L32-1)) + EXP(2.21*M32) )/100*2.45 ) -> 0.35859414 | O32: =IF( OR( ISBLANK(I32),ISBLANK(J32), ISBLANK(K32), ISBLANK(L32), ISBLANK(M32) ), "", 1.5*SQRT( EXP(2.21*(I32-1)) + EXP(2.21*(J32-1)) + EXP(2.21*(K32-1)) + EXP(2.21*(L32-1)) + EXP(2.21*M32) )/100*2.45 )
A33: =Agriculture!A63 -> Agriculture | B33: =Agriculture!B63 -> Agricultural other | C33: =Agriculture!C63 -> NL | D33: =Agriculture!D63 -> PS | E33: =Agriculture!E63 -> 1 | F33: =Agriculture!F63 -> 2 | G33: =Agriculture!G63 -> Urbanus, J.H., Brunner, A., Boersma, A., Henke, S., Kooter, I., Lensen, S., Parker, L., Schwarz, A., Imhof, P., Dortmans, A., Wijngaard, M., 2022. Autobanden, verpakkingen en landbouwfolie zijn in Nederland de grootste bronnen van microplastics. TNO. | H33: 1 | J33: 2 | K33: 1 | L33: 1 | M33: 2 | N33: =IF( OR( ISBLANK(H33),ISBLANK(J33), ISBLANK(K33), ISBLANK(L33), ISBLANK(M33) ), "", 1.5*SQRT( EXP(2.21*(H33-1)) + EXP(2.21*(J33-1)) + EXP(2.21*(K33-1)) + EXP(2.21*(L33-1)) + EXP(2.21*M33) )/100*2.45 ) -> 0.35859414 | O33: =IF( OR( ISBLANK(I33),ISBLANK(J33), ISBLANK(K33), ISBLANK(L33), ISBLANK(M33) ), "", 1.5*SQRT( EXP(2.21*(I33-1)) + EXP(2.21*(J33-1)) + EXP(2.21*(K33-1)) + EXP(2.21*(L33-1)) + EXP(2.21*M33) )/100*2.45 )
A34: =Agriculture!A64 -> Agriculture | B34: =Agriculture!B64 -> Agricultural other | C34: =Agriculture!C64 -> NL | D34: =Agriculture!D64 -> PP | E34: =Agriculture!E64 -> 1 | F34: =Agriculture!F64 -> 2 | G34: =Agriculture!G64 -> Urbanus, J.H., Brunner, A., Boersma, A., Henke, S., Kooter, I., Lensen, S., Parker, L., Schwarz, A., Imhof, P., Dortmans, A., Wijngaard, M., 2022. Autobanden, verpakkingen en landbouwfolie zijn in Nederland de grootste bronnen van microplastics. TNO. | H34: 1 | J34: 2 | K34: 1 | L34: 1 | M34: 2 | N34: =IF( OR( ISBLANK(H34),ISBLANK(J34), ISBLANK(K34), ISBLANK(L34), ISBLANK(M34) ), "", 1.5*SQRT( EXP(2.21*(H34-1)) + EXP(2.21*(J34-1)) + EXP(2.21*(K34-1)) + EXP(2.21*(L34-1)) + EXP(2.21*M34) )/100*2.45 ) -> 0.35859414 | O34: =IF( OR( ISBLANK(I34),ISBLANK(J34), ISBLANK(K34), ISBLANK(L34), ISBLANK(M34) ), "", 1.5*SQRT( EXP(2.21*(I34-1)) + EXP(2.21*(J34-1)) + EXP(2.21*(K34-1)) + EXP(2.21*(L34-1)) + EXP(2.21*M34) )/100*2.45 )
A35: =Agriculture!A65 -> Agriculture | B35: =Agriculture!B65 -> Agricultural other | C35: =Agriculture!C65 -> NL | D35: =Agriculture!D65 -> LDPE | E35: =Agriculture!E65 -> 0.08605602 | F35: =Agriculture!F65 -> 2 | G35: =Agriculture!G65 -> Urbanus, J.H., Brunner, A., Boersma, A., Henke, S., Kooter, I., Lensen, S., Parker, L., Schwarz, A., Imhof, P., Dortmans, A., Wijngaard, M., 2022. Autobanden, verpakkingen en landbouwfolie zijn in Nederland de grootste bronnen van microplastics. TNO. | H35: 1 | J35: 2 | K35: 1 | L35: 1 | M35: 2 | N35: =IF( OR( ISBLANK(H35),ISBLANK(J35), ISBLANK(K35), ISBLANK(L35), ISBLANK(M35) ), "", 1.5*SQRT( EXP(2.21*(H35-1)) + EXP(2.21*(J35-1)) + EXP(2.21*(K35-1)) + EXP(2.21*(L35-1)) + EXP(2.21*M35) )/100*2.45 ) -> 0.35859414 | O35: =IF( OR( ISBLANK(I35),ISBLANK(J35), ISBLANK(K35), ISBLANK(L35), ISBLANK(M35) ), "", 1.5*SQRT( EXP(2.21*(I35-1)) + EXP(2.21*(J35-1)) + EXP(2.21*(K35-1)) + EXP(2.21*(L35-1)) + EXP(2.21*M35) )/100*2.45 )
A36: =Agriculture!A66 -> Agriculture | B36: =Agriculture!B66 -> Agricultural other | C36: =Agriculture!C66 -> NL | D36: =Agriculture!D66 -> HDPE | E36: =Agriculture!E66 -> 0.3931967 | F36: =Agriculture!F66 -> 2 | G36: =Agriculture!G66 -> Urbanus, J.H., Brunner, A., Boersma, A., Henke, S., Kooter, I., Lensen, S., Parker, L., Schwarz, A., Imhof, P., Dortmans, A., Wijngaard, M., 2022. Autobanden, verpakkingen en landbouwfolie zijn in Nederland de grootste bronnen van microplastics. TNO. | H36: 1 | J36: 2 | K36: 1 | L36: 1 | M36: 2 | N36: =IF( OR( ISBLANK(H36),ISBLANK(J36), ISBLANK(K36), ISBLANK(L36), ISBLANK(M36) ), "", 1.5*SQRT( EXP(2.21*(H36-1)) + EXP(2.21*(J36-1)) + EXP(2.21*(K36-1)) + EXP(2.21*(L36-1)) + EXP(2.21*M36) )/100*2.45 ) -> 0.35859414 | O36: =IF( OR( ISBLANK(I36),ISBLANK(J36), ISBLANK(K36), ISBLANK(L36), ISBLANK(M36) ), "", 1.5*SQRT( EXP(2.21*(I36-1)) + EXP(2.21*(J36-1)) + EXP(2.21*(K36-1)) + EXP(2.21*(L36-1)) + EXP(2.21*M36) )/100*2.45 )
A37: =Agriculture!A67 -> Agriculture | B37: =Agriculture!B67 -> Agricultural other | C37: =Agriculture!C67 -> EU | D37: =Agriculture!D67 -> PVC | E37: =Agriculture!E67 -> 0.32338771 | F37: =Agriculture!F67 -> 2 | G37: =Agriculture!G67 -> Assessment of agricultural plastics and their sustainability: A call for action, 2021. . FAO. https://doi.org/10.4060/cb7856en | I37: 1 | J37: 2 | K37: 1 | L37: 1 | M37: 2 | N37: =IF( OR( ISBLANK(H37),ISBLANK(J37), ISBLANK(K37), ISBLANK(L37), ISBLANK(M37) ), "", 1.5*SQRT( EXP(2.21*(H37-1)) + EXP(2.21*(J37-1)) + EXP(2.21*(K37-1)) + EXP(2.21*(L37-1)) + EXP(2.21*M37) )/100*2.45 ) | O37: =IF( OR( ISBLANK(I37),ISBLANK(J37), ISBLANK(K37), ISBLANK(L37), ISBLANK(M37) ), "", 1.5*SQRT( EXP(2.21*(I37-1)) + EXP(2.21*(J37-1)) + EXP(2.21*(K37-1)) + EXP(2.21*(L37-1)) + EXP(2.21*M37) )/100*2.45 ) -> 0.35859414
A38: =Agriculture!A68 -> Agriculture | B38: =Agriculture!B68 -> Agricultural other | C38: =Agriculture!C68 -> EU | D38: =Agriculture!D68 -> PS | E38: =Agriculture!E68 -> 1 | F38: =Agriculture!F68 -> 2 | G38: =Agriculture!G68 -> Assessment of agricultural plastics and their sustainability: A call for action, 2021. . FAO. https://doi.org/10.4060/cb7856en | I38: 1 | J38: 2 | K38: 1 | L38: 1 | M38: 2 | N38: =IF( OR( ISBLANK(H38),ISBLANK(J38), ISBLANK(K38), ISBLANK(L38), ISBLANK(M38) ), "", 1.5*SQRT( EXP(2.21*(H38-1)) + EXP(2.21*(J38-1)) + EXP(2.21*(K38-1)) + EXP(2.21*(L38-1)) + EXP(2.21*M38) )/100*2.45 ) | O38: =IF( OR( ISBLANK(I38),ISBLANK(J38), ISBLANK(K38), ISBLANK(L38), ISBLANK(M38) ), "", 1.5*SQRT( EXP(2.21*(I38-1)) + EXP(2.21*(J38-1)) + EXP(2.21*(K38-1)) + EXP(2.21*(L38-1)) + EXP(2.21*M38) )/100*2.45 ) -> 0.35859414
A39: =Agriculture!A69 -> Agriculture | B39: =Agriculture!B69 -> Agricultural other | C39: =Agriculture!C69 -> EU | D39: =Agriculture!D69 -> PP | E39: =Agriculture!E69 -> 1 | F39: =Agriculture!F69 -> 2 | G39: =Agriculture!G69 -> Assessment of agricultural plastics and their sustainability: A call for action, 2021. . FAO. https://doi.org/10.4060/cb7856en | I39: 1 | J39: 2 | K39: 1 | L39: 1 | M39: 2 | N39: =IF( OR( ISBLANK(H39),ISBLANK(J39), ISBLANK(K39), ISBLANK(L39), ISBLANK(M39) ), "", 1.5*SQRT( EXP(2.21*(H39-1)) + EXP(2.21*(J39-1)) + EXP(2.21*(K39-1)) + EXP(2.21*(L39-1)) + EXP(2.21*M39) )/100*2.45 ) | O39: =IF( OR( ISBLANK(I39),ISBLANK(J39), ISBLANK(K39), ISBLANK(L39), ISBLANK(M39) ), "", 1.5*SQRT( EXP(2.21*(I39-1)) + EXP(2.21*(J39-1)) + EXP(2.21*(K39-1)) + EXP(2.21*(L39-1)) + EXP(2.21*M39) )/100*2.45 ) -> 0.35859414
A40: =Agriculture!A70 -> Agriculture | B40: =Agriculture!B70 -> Agricultural other | C40: =Agriculture!C70 -> EU | D40: =Agriculture!D70 -> LDPE | E40: =Agriculture!E70 -> 0.098069488 | F40: =Agriculture!F70 -> 2 | G40: =Agriculture!G70 -> Assessment of agricultural plastics and their sustainability: A call for action, 2021. . FAO. https://doi.org/10.4060/cb7856en | I40: 1 | J40: 2 | K40: 1 | L40: 1 | M40: 2 | N40: =IF( OR( ISBLANK(H40),ISBLANK(J40), ISBLANK(K40), ISBLANK(L40), ISBLANK(M40) ), "", 1.5*SQRT( EXP(2.21*(H40-1)) + EXP(2.21*(J40-1)) + EXP(2.21*(K40-1)) + EXP(2.21*(L40-1)) + EXP(2.21*M40) )/100*2.45 ) | O40: =IF( OR( ISBLANK(I40),ISBLANK(J40), ISBLANK(K40), ISBLANK(L40), ISBLANK(M40) ), "", 1.5*SQRT( EXP(2.21*(I40-1)) + EXP(2.21*(J40-1)) + EXP(2.21*(K40-1)) + EXP(2.21*(L40-1)) + EXP(2.21*M40) )/100*2.45 ) -> 0.35859414
A41: =Agriculture!A71 -> Agriculture | B41: =Agriculture!B71 -> Agricultural other | C41: =Agriculture!C71 -> EU | D41: =Agriculture!D71 -> HDPE | E41: =Agriculture!E71 -> 0.69931121 | F41: =Agriculture!F71 -> 2 | G41: =Agriculture!G71 -> Assessment of agricultural plastics and their sustainability: A call for action, 2021. . FAO. https://doi.org/10.4060/cb7856en | I41: 1 | J41: 2 | K41: 1 | L41: 1 | M41: 2 | N41: =IF( OR( ISBLANK(H41),ISBLANK(J41), ISBLANK(K41), ISBLANK(L41), ISBLANK(M41) ), "", 1.5*SQRT( EXP(2.21*(H41-1)) + EXP(2.21*(J41-1)) + EXP(2.21*(K41-1)) + EXP(2.21*(L41-1)) + EXP(2.21*M41) )/100*2.45 ) | O41: =IF( OR( ISBLANK(I41),ISBLANK(J41), ISBLANK(K41), ISBLANK(L41), ISBLANK(M41) ), "", 1.5*SQRT( EXP(2.21*(I41-1)) + EXP(2.21*(J41-1)) + EXP(2.21*(K41-1)) + EXP(2.21*(L41-1)) + EXP(2.21*M41) )/100*2.45 ) -> 0.35859414
A42: Packaging | B42: Agricultural packaging bottles | C42: any | D42: LDPE | E42: 0 | F42: 1 | G42: WRAP, Report: Plastic Packaging Composition 2011, 2013 | N42: =IF( OR( ISBLANK(H42),ISBLANK(J42), ISBLANK(K42), ISBLANK(L42), ISBLANK(M42) ), "", 1.5*SQRT( EXP(2.21*(H42-1)) + EXP(2.21*(J42-1)) + EXP(2.21*(K42-1)) + EXP(2.21*(L42-1)) + EXP(2.21*M42) )/100*2.45 ) | O42: =IF( OR( ISBLANK(I42),ISBLANK(J42), ISBLANK(K42), ISBLANK(L42), ISBLANK(M42) ), "", 1.5*SQRT( EXP(2.21*(I42-1)) + EXP(2.21*(J42-1)) + EXP(2.21*(K42-1)) + EXP(2.21*(L42-1)) + EXP(2.21*M42) )/100*2.45 )
A43: Packaging | B43: Agricultural packaging bottles | C43: any | D43: HDPE | E43: 0.0122 | F43: 1 | G43: WRAP, Report: Plastic Packaging Composition 2011, 2013 | H43: 2 | I43: 2 | J43: 2 | K43: 1 | L43: 1 | M43: 2 | N43: =IF( OR( ISBLANK(H43),ISBLANK(J43), ISBLANK(K43), ISBLANK(L43), ISBLANK(M43) ), "", 1.5*SQRT( EXP(2.21*(H43-1)) + EXP(2.21*(J43-1)) + EXP(2.21*(K43-1)) + EXP(2.21*(L43-1)) + EXP(2.21*M43) )/100*2.45 ) -> 0.37356464 | O43: =IF( OR( ISBLANK(I43),ISBLANK(J43), ISBLANK(K43), ISBLANK(L43), ISBLANK(M43) ), "", 1.5*SQRT( EXP(2.21*(I43-1)) + EXP(2.21*(J43-1)) + EXP(2.21*(K43-1)) + EXP(2.21*(L43-1)) + EXP(2.21*M43) )/100*2.45 ) -> 0.37356464
A44: Packaging | B44: Agricultural packaging bottles | C44: any | D44: PP | E44: 0 | F44: 1 | G44: WRAP, Report: Plastic Packaging Composition 2011, 2013 | N44: =IF( OR( ISBLANK(H44),ISBLANK(J44), ISBLANK(K44), ISBLANK(L44), ISBLANK(M44) ), "", 1.5*SQRT( EXP(2.21*(H44-1)) + EXP(2.21*(J44-1)) + EXP(2.21*(K44-1)) + EXP(2.21*(L44-1)) + EXP(2.21*M44) )/100*2.45 ) | O44: =IF( OR( ISBLANK(I44),ISBLANK(J44), ISBLANK(K44), ISBLANK(L44), ISBLANK(M44) ), "", 1.5*SQRT( EXP(2.21*(I44-1)) + EXP(2.21*(J44-1)) + EXP(2.21*(K44-1)) + EXP(2.21*(L44-1)) + EXP(2.21*M44) )/100*2.45 )
A45: Packaging | B45: Agricultural packaging bottles | C45: any | D45: PS | E45: 0 | F45: 1 | G45: WRAP, Report: Plastic Packaging Composition 2011, 2013 | N45: =IF( OR( ISBLANK(H45),ISBLANK(J45), ISBLANK(K45), ISBLANK(L45), ISBLANK(M45) ), "", 1.5*SQRT( EXP(2.21*(H45-1)) + EXP(2.21*(J45-1)) + EXP(2.21*(K45-1)) + EXP(2.21*(L45-1)) + EXP(2.21*M45) )/100*2.45 ) | O45: =IF( OR( ISBLANK(I45),ISBLANK(J45), ISBLANK(K45), ISBLANK(L45), ISBLANK(M45) ), "", 1.5*SQRT( EXP(2.21*(I45-1)) + EXP(2.21*(J45-1)) + EXP(2.21*(K45-1)) + EXP(2.21*(L45-1)) + EXP(2.21*M45) )/100*2.45 )
A46: Packaging | B46: Agricultural packaging bottles | C46: any | D46: EPS | E46: 0 | F46: 1 | G46: WRAP, Report: Plastic Packaging Composition 2011, 2013 | N46: =IF( OR( ISBLANK(H46),ISBLANK(J46), ISBLANK(K46), ISBLANK(L46), ISBLANK(M46) ), "", 1.5*SQRT( EXP(2.21*(H46-1)) + EXP(2.21*(J46-1)) + EXP(2.21*(K46-1)) + EXP(2.21*(L46-1)) + EXP(2.21*M46) )/100*2.45 ) | O46: =IF( OR( ISBLANK(I46),ISBLANK(J46), ISBLANK(K46), ISBLANK(L46), ISBLANK(M46) ), "", 1.5*SQRT( EXP(2.21*(I46-1)) + EXP(2.21*(J46-1)) + EXP(2.21*(K46-1)) + EXP(2.21*(L46-1)) + EXP(2.21*M46) )/100*2.45 )
A47: Packaging | B47: Agricultural packaging bottles | C47: any | D47: PVC | E47: 0 | F47: 1 | G47: WRAP, Report: Plastic Packaging Composition 2011, 2013 | N47: =IF( OR( ISBLANK(H47),ISBLANK(J47), ISBLANK(K47), ISBLANK(L47), ISBLANK(M47) ), "", 1.5*SQRT( EXP(2.21*(H47-1)) + EXP(2.21*(J47-1)) + EXP(2.21*(K47-1)) + EXP(2.21*(L47-1)) + EXP(2.21*M47) )/100*2.45 ) | O47: =IF( OR( ISBLANK(I47),ISBLANK(J47), ISBLANK(K47), ISBLANK(L47), ISBLANK(M47) ), "", 1.5*SQRT( EXP(2.21*(I47-1)) + EXP(2.21*(J47-1)) + EXP(2.21*(K47-1)) + EXP(2.21*(L47-1)) + EXP(2.21*M47) )/100*2.45 )
A48: Packaging | B48: Agricultural packaging bottles | C48: any | D48: PET | E48: 0 | F48: 1 | G48: WRAP, Report: Plastic Packaging Composition 2011, 2013 | N48: =IF( OR( ISBLANK(H48),ISBLANK(J48), ISBLANK(K48), ISBLANK(L48), ISBLANK(M48) ), "", 1.5*SQRT( EXP(2.21*(H48-1)) + EXP(2.21*(J48-1)) + EXP(2.21*(K48-1)) + EXP(2.21*(L48-1)) + EXP(2.21*M48) )/100*2.45 ) | O48: =IF( OR( ISBLANK(I48),ISBLANK(J48), ISBLANK(K48), ISBLANK(L48), ISBLANK(M48) ), "", 1.5*SQRT( EXP(2.21*(I48-1)) + EXP(2.21*(J48-1)) + EXP(2.21*(K48-1)) + EXP(2.21*(L48-1)) + EXP(2.21*M48) )/100*2.45 )
A49: Packaging | B49: Agricultural packaging bottles | C49: any | D49: OTHER | E49: 0 | F49: 1 | G49: Based on EU flows in Liu etal. 2022 using WRAP and others | N49: =IF( OR( ISBLANK(H49),ISBLANK(J49), ISBLANK(K49), ISBLANK(L49), ISBLANK(M49) ), "", 1.5*SQRT( EXP(2.21*(H49-1)) + EXP(2.21*(J49-1)) + EXP(2.21*(K49-1)) + EXP(2.21*(L49-1)) + EXP(2.21*M49) )/100*2.45 ) | O49: =IF( OR( ISBLANK(I49),ISBLANK(J49), ISBLANK(K49), ISBLANK(L49), ISBLANK(M49) ), "", 1.5*SQRT( EXP(2.21*(I49-1)) + EXP(2.21*(J49-1)) + EXP(2.21*(K49-1)) + EXP(2.21*(L49-1)) + EXP(2.21*M49) )/100*2.45 )
A50: Packaging | B50: Agricultural packaging films | C50: any | D50: LDPE | E50: 0.0329 | F50: 1 | G50: WRAP, Report: Plastic Packaging Composition 2011, 2013 | H50: 2 | I50: 2 | J50: 2 | K50: 1 | L50: 1 | M50: 2 | N50: =IF( OR( ISBLANK(H50),ISBLANK(J50), ISBLANK(K50), ISBLANK(L50), ISBLANK(M50) ), "", 1.5*SQRT( EXP(2.21*(H50-1)) + EXP(2.21*(J50-1)) + EXP(2.21*(K50-1)) + EXP(2.21*(L50-1)) + EXP(2.21*M50) )/100*2.45 ) -> 0.37356464 | O50: =IF( OR( ISBLANK(I50),ISBLANK(J50), ISBLANK(K50), ISBLANK(L50), ISBLANK(M50) ), "", 1.5*SQRT( EXP(2.21*(I50-1)) + EXP(2.21*(J50-1)) + EXP(2.21*(K50-1)) + EXP(2.21*(L50-1)) + EXP(2.21*M50) )/100*2.45 ) -> 0.37356464
A51: Packaging | B51: Agricultural packaging films | C51: any | D51: HDPE | E51: 0 | F51: 1 | G51: WRAP, Report: Plastic Packaging Composition 2011, 2013 | N51: =IF( OR( ISBLANK(H51),ISBLANK(J51), ISBLANK(K51), ISBLANK(L51), ISBLANK(M51) ), "", 1.5*SQRT( EXP(2.21*(H51-1)) + EXP(2.21*(J51-1)) + EXP(2.21*(K51-1)) + EXP(2.21*(L51-1)) + EXP(2.21*M51) )/100*2.45 ) | O51: =IF( OR( ISBLANK(I51),ISBLANK(J51), ISBLANK(K51), ISBLANK(L51), ISBLANK(M51) ), "", 1.5*SQRT( EXP(2.21*(I51-1)) + EXP(2.21*(J51-1)) + EXP(2.21*(K51-1)) + EXP(2.21*(L51-1)) + EXP(2.21*M51) )/100*2.45 )
A52: Packaging | B52: Agricultural packaging films | C52: any | D52: PP | E52: 0.0258 | F52: 1 | G52: WRAP, Report: Plastic Packaging Composition 2011, 2013 | H52: 2 | I52: 2 | J52: 2 | K52: 1 | L52: 1 | M52: 2 | N52: =IF( OR( ISBLANK(H52),ISBLANK(J52), ISBLANK(K52), ISBLANK(L52), ISBLANK(M52) ), "", 1.5*SQRT( EXP(2.21*(H52-1)) + EXP(2.21*(J52-1)) + EXP(2.21*(K52-1)) + EXP(2.21*(L52-1)) + EXP(2.21*M52) )/100*2.45 ) -> 0.37356464 | O52: =IF( OR( ISBLANK(I52),ISBLANK(J52), ISBLANK(K52), ISBLANK(L52), ISBLANK(M52) ), "", 1.5*SQRT( EXP(2.21*(I52-1)) + EXP(2.21*(J52-1)) + EXP(2.21*(K52-1)) + EXP(2.21*(L52-1)) + EXP(2.21*M52) )/100*2.45 ) -> 0.37356464
A53: Packaging | B53: Agricultural packaging films | C53: any | D53: PS | E53: 0 | F53: 1 | G53: WRAP, Report: Plastic Packaging Composition 2011, 2013 | N53: =IF( OR( ISBLANK(H53),ISBLANK(J53), ISBLANK(K53), ISBLANK(L53), ISBLANK(M53) ), "", 1.5*SQRT( EXP(2.21*(H53-1)) + EXP(2.21*(J53-1)) + EXP(2.21*(K53-1)) + EXP(2.21*(L53-1)) + EXP(2.21*M53) )/100*2.45 ) | O53: =IF( OR( ISBLANK(I53),ISBLANK(J53), ISBLANK(K53), ISBLANK(L53), ISBLANK(M53) ), "", 1.5*SQRT( EXP(2.21*(I53-1)) + EXP(2.21*(J53-1)) + EXP(2.21*(K53-1)) + EXP(2.21*(L53-1)) + EXP(2.21*M53) )/100*2.45 )
A54: Packaging | B54: Agricultural packaging films | C54: any | D54: EPS | E54: 0 | F54: 1 | G54: WRAP, Report: Plastic Packaging Composition 2011, 2013 | N54: =IF( OR( ISBLANK(H54),ISBLANK(J54), ISBLANK(K54), ISBLANK(L54), ISBLANK(M54) ), "", 1.5*SQRT( EXP(2.21*(H54-1)) + EXP(2.21*(J54-1)) + EXP(2.21*(K54-1)) + EXP(2.21*(L54-1)) + EXP(2.21*M54) )/100*2.45 ) | O54: =IF( OR( ISBLANK(I54),ISBLANK(J54), ISBLANK(K54), ISBLANK(L54), ISBLANK(M54) ), "", 1.5*SQRT( EXP(2.21*(I54-1)) + EXP(2.21*(J54-1)) + EXP(2.21*(K54-1)) + EXP(2.21*(L54-1)) + EXP(2.21*M54) )/100*2.45 )
A55: Packaging | B55: Agricultural packaging films | C55: any | D55: PVC | E55: 0 | F55: 1 | G55: WRAP, Report: Plastic Packaging Composition 2011, 2013 | N55: =IF( OR( ISBLANK(H55),ISBLANK(J55), ISBLANK(K55), ISBLANK(L55), ISBLANK(M55) ), "", 1.5*SQRT( EXP(2.21*(H55-1)) + EXP(2.21*(J55-1)) + EXP(2.21*(K55-1)) + EXP(2.21*(L55-1)) + EXP(2.21*M55) )/100*2.45 ) | O55: =IF( OR( ISBLANK(I55),ISBLANK(J55), ISBLANK(K55), ISBLANK(L55), ISBLANK(M55) ), "", 1.5*SQRT( EXP(2.21*(I55-1)) + EXP(2.21*(J55-1)) + EXP(2.21*(K55-1)) + EXP(2.21*(L55-1)) + EXP(2.21*M55) )/100*2.45 )
A56: Packaging | B56: Agricultural packaging films | C56: any | D56: PET | E56: 0 | F56: 1 | G56: WRAP, Report: Plastic Packaging Composition 2011, 2013 | N56: =IF( OR( ISBLANK(H56),ISBLANK(J56), ISBLANK(K56), ISBLANK(L56), ISBLANK(M56) ), "", 1.5*SQRT( EXP(2.21*(H56-1)) + EXP(2.21*(J56-1)) + EXP(2.21*(K56-1)) + EXP(2.21*(L56-1)) + EXP(2.21*M56) )/100*2.45 ) | O56: =IF( OR( ISBLANK(I56),ISBLANK(J56), ISBLANK(K56), ISBLANK(L56), ISBLANK(M56) ), "", 1.5*SQRT( EXP(2.21*(I56-1)) + EXP(2.21*(J56-1)) + EXP(2.21*(K56-1)) + EXP(2.21*(L56-1)) + EXP(2.21*M56) )/100*2.45 )
A57: Packaging | B57: Agricultural packaging films | C57: any | D57: OTHER | E57: 0.01331058 | F57: 1 | G57: Based on EU flows in Liu etal. 2022 using WRAP and others | H57: 2 | I57: 1 | J57: 2 | K57: 2 | L57: 1 | M57: 2 | N57: =IF( OR( ISBLANK(H57),ISBLANK(J57), ISBLANK(K57), ISBLANK(L57), ISBLANK(M57) ), "", 1.5*SQRT( EXP(2.21*(H57-1)) + EXP(2.21*(J57-1)) + EXP(2.21*(K57-1)) + EXP(2.21*(L57-1)) + EXP(2.21*M57) )/100*2.45 ) -> 0.38795789 | O57: =IF( OR( ISBLANK(I57),ISBLANK(J57), ISBLANK(K57), ISBLANK(L57), ISBLANK(M57) ), "", 1.5*SQRT( EXP(2.21*(I57-1)) + EXP(2.21*(J57-1)) + EXP(2.21*(K57-1)) + EXP(2.21*(L57-1)) + EXP(2.21*M57) )/100*2.45 ) -> 0.37356464
A58: =Agriculture!A52 -> Agriculture | B58: =Agriculture!B52 -> Agricultural pipes (discarded) | C58: =Agriculture!C52 -> NL | D58: =Agriculture!D52 -> PVC | E58: =Agriculture!E52 -> 0.40710943 | F58: =Agriculture!F52 -> 2 | G58: =Agriculture!G52 -> Urbanus, J.H., Brunner, A., Boersma, A., Henke, S., Kooter, I., Lensen, S., Parker, L., Schwarz, A., Imhof, P., Dortmans, A., Wijngaard, M., 2022. Autobanden, verpakkingen en landbouwfolie zijn in Nederland de grootste bronnen van microplastics. TNO. | H58: 1 | J58: 2 | K58: 1 | L58: 1 | M58: 2 | N58: =IF( OR( ISBLANK(H58),ISBLANK(J58), ISBLANK(K58), ISBLANK(L58), ISBLANK(M58) ), "", 1.5*SQRT( EXP(2.21*(H58-1)) + EXP(2.21*(J58-1)) + EXP(2.21*(K58-1)) + EXP(2.21*(L58-1)) + EXP(2.21*M58) )/100*2.45 ) -> 0.35859414 | O58: =IF( OR( ISBLANK(I58),ISBLANK(J58), ISBLANK(K58), ISBLANK(L58), ISBLANK(M58) ), "", 1.5*SQRT( EXP(2.21*(I58-1)) + EXP(2.21*(J58-1)) + EXP(2.21*(K58-1)) + EXP(2.21*(L58-1)) + EXP(2.21*M58) )/100*2.45 )
A59: =Agriculture!A53 -> Agriculture | B59: =Agriculture!B53 -> Agricultural pipes (discarded) | C59: =Agriculture!C53 -> NL | D59: =Agriculture!D53 -> PS | E59: =Agriculture!E53 -> 0 | F59: =Agriculture!F53 -> 2 | G59: =Agriculture!G53 -> Urbanus, J.H., Brunner, A., Boersma, A., Henke, S., Kooter, I., Lensen, S., Parker, L., Schwarz, A., Imhof, P., Dortmans, A., Wijngaard, M., 2022. Autobanden, verpakkingen en landbouwfolie zijn in Nederland de grootste bronnen van microplastics. TNO. | H59: 1 | J59: 2 | K59: 1 | L59: 1 | M59: 2 | N59: =IF( OR( ISBLANK(H59),ISBLANK(J59), ISBLANK(K59), ISBLANK(L59), ISBLANK(M59) ), "", 1.5*SQRT( EXP(2.21*(H59-1)) + EXP(2.21*(J59-1)) + EXP(2.21*(K59-1)) + EXP(2.21*(L59-1)) + EXP(2.21*M59) )/100*2.45 ) -> 0.35859414 | O59: =IF( OR( ISBLANK(I59),ISBLANK(J59), ISBLANK(K59), ISBLANK(L59), ISBLANK(M59) ), "", 1.5*SQRT( EXP(2.21*(I59-1)) + EXP(2.21*(J59-1)) + EXP(2.21*(K59-1)) + EXP(2.21*(L59-1)) + EXP(2.21*M59) )/100*2.45 )
A60: =Agriculture!A54 -> Agriculture | B60: =Agriculture!B54 -> Agricultural pipes (discarded) | C60: =Agriculture!C54 -> NL | D60: =Agriculture!D54 -> PP | E60: =Agriculture!E54 -> 0 | F60: =Agriculture!F54 -> 2 | G60: =Agriculture!G54 -> Urbanus, J.H., Brunner, A., Boersma, A., Henke, S., Kooter, I., Lensen, S., Parker, L., Schwarz, A., Imhof, P., Dortmans, A., Wijngaard, M., 2022. Autobanden, verpakkingen en landbouwfolie zijn in Nederland de grootste bronnen van microplastics. TNO. | H60: 1 | J60: 2 | K60: 1 | L60: 1 | M60: 2 | N60: =IF( OR( ISBLANK(H60),ISBLANK(J60), ISBLANK(K60), ISBLANK(L60), ISBLANK(M60) ), "", 1.5*SQRT( EXP(2.21*(H60-1)) + EXP(2.21*(J60-1)) + EXP(2.21*(K60-1)) + EXP(2.21*(L60-1)) + EXP(2.21*M60) )/100*2.45 ) -> 0.35859414 | O60: =IF( OR( ISBLANK(I60),ISBLANK(J60), ISBLANK(K60), ISBLANK(L60), ISBLANK(M60) ), "", 1.5*SQRT( EXP(2.21*(I60-1)) + EXP(2.21*(J60-1)) + EXP(2.21*(K60-1)) + EXP(2.21*(L60-1)) + EXP(2.21*M60) )/100*2.45 )
A61: =Agriculture!A55 -> Agriculture | B61: =Agriculture!B55 -> Agricultural pipes (discarded) | C61: =Agriculture!C55 -> NL | D61: =Agriculture!D55 -> LDPE | E61: =Agriculture!E55 -> 0.14312762 | F61: =Agriculture!F55 -> 2 | G61: =Agriculture!G55 -> Urbanus, J.H., Brunner, A., Boersma, A., Henke, S., Kooter, I., Lensen, S., Parker, L., Schwarz, A., Imhof, P., Dortmans, A., Wijngaard, M., 2022. Autobanden, verpakkingen en landbouwfolie zijn in Nederland de grootste bronnen van microplastics. TNO. | H61: 1 | J61: 2 | K61: 1 | L61: 1 | M61: 2 | N61: =IF( OR( ISBLANK(H61),ISBLANK(J61), ISBLANK(K61), ISBLANK(L61), ISBLANK(M61) ), "", 1.5*SQRT( EXP(2.21*(H61-1)) + EXP(2.21*(J61-1)) + EXP(2.21*(K61-1)) + EXP(2.21*(L61-1)) + EXP(2.21*M61) )/100*2.45 ) -> 0.35859414 | O61: =IF( OR( ISBLANK(I61),ISBLANK(J61), ISBLANK(K61), ISBLANK(L61), ISBLANK(M61) ), "", 1.5*SQRT( EXP(2.21*(I61-1)) + EXP(2.21*(J61-1)) + EXP(2.21*(K61-1)) + EXP(2.21*(L61-1)) + EXP(2.21*M61) )/100*2.45 )
A62: =Agriculture!A56 -> Agriculture | B62: =Agriculture!B56 -> Agricultural pipes (discarded) | C62: =Agriculture!C56 -> NL | D62: =Agriculture!D56 -> HDPE | E62: =Agriculture!E56 -> 0.56173601 | F62: =Agriculture!F56 -> 2 | G62: =Agriculture!G56 -> Urbanus, J.H., Brunner, A., Boersma, A., Henke, S., Kooter, I., Lensen, S., Parker, L., Schwarz, A., Imhof, P., Dortmans, A., Wijngaard, M., 2022. Autobanden, verpakkingen en landbouwfolie zijn in Nederland de grootste bronnen van microplastics. TNO. | H62: 1 | J62: 2 | K62: 1 | L62: 1 | M62: 2 | N62: =IF( OR( ISBLANK(H62),ISBLANK(J62), ISBLANK(K62), ISBLANK(L62), ISBLANK(M62) ), "", 1.5*SQRT( EXP(2.21*(H62-1)) + EXP(2.21*(J62-1)) + EXP(2.21*(K62-1)) + EXP(2.21*(L62-1)) + EXP(2.21*M62) )/100*2.45 ) -> 0.35859414 | O62: =IF( OR( ISBLANK(I62),ISBLANK(J62), ISBLANK(K62), ISBLANK(L62), ISBLANK(M62) ), "", 1.5*SQRT( EXP(2.21*(I62-1)) + EXP(2.21*(J62-1)) + EXP(2.21*(K62-1)) + EXP(2.21*(L62-1)) + EXP(2.21*M62) )/100*2.45 )
A63: =Agriculture!A57 -> Agriculture | B63: =Agriculture!B57 -> Agricultural pipes (discarded) | C63: =Agriculture!C57 -> EU | D63: =Agriculture!D57 -> PVC | E63: =Agriculture!E57 -> 0.1673393 | F63: =Agriculture!F57 -> 2 | G63: =Agriculture!G57 -> Assessment of agricultural plastics and their sustainability: A call for action, 2021. . FAO. https://doi.org/10.4060/cb7856en | I63: 1 | J63: 2 | K63: 1 | L63: 1 | M63: 2 | N63: =IF( OR( ISBLANK(H63),ISBLANK(J63), ISBLANK(K63), ISBLANK(L63), ISBLANK(M63) ), "", 1.5*SQRT( EXP(2.21*(H63-1)) + EXP(2.21*(J63-1)) + EXP(2.21*(K63-1)) + EXP(2.21*(L63-1)) + EXP(2.21*M63) )/100*2.45 ) | O63: =IF( OR( ISBLANK(I63),ISBLANK(J63), ISBLANK(K63), ISBLANK(L63), ISBLANK(M63) ), "", 1.5*SQRT( EXP(2.21*(I63-1)) + EXP(2.21*(J63-1)) + EXP(2.21*(K63-1)) + EXP(2.21*(L63-1)) + EXP(2.21*M63) )/100*2.45 ) -> 0.35859414
A64: =Agriculture!A58 -> Agriculture | B64: =Agriculture!B58 -> Agricultural pipes (discarded) | C64: =Agriculture!C58 -> EU | D64: =Agriculture!D58 -> PS | E64: =Agriculture!E58 -> 0 | F64: =Agriculture!F58 -> 2 | G64: =Agriculture!G58 -> Assessment of agricultural plastics and their sustainability: A call for action, 2021. . FAO. https://doi.org/10.4060/cb7856en | I64: 1 | J64: 2 | K64: 1 | L64: 1 | M64: 2 | N64: =IF( OR( ISBLANK(H64),ISBLANK(J64), ISBLANK(K64), ISBLANK(L64), ISBLANK(M64) ), "", 1.5*SQRT( EXP(2.21*(H64-1)) + EXP(2.21*(J64-1)) + EXP(2.21*(K64-1)) + EXP(2.21*(L64-1)) + EXP(2.21*M64) )/100*2.45 ) | O64: =IF( OR( ISBLANK(I64),ISBLANK(J64), ISBLANK(K64), ISBLANK(L64), ISBLANK(M64) ), "", 1.5*SQRT( EXP(2.21*(I64-1)) + EXP(2.21*(J64-1)) + EXP(2.21*(K64-1)) + EXP(2.21*(L64-1)) + EXP(2.21*M64) )/100*2.45 ) -> 0.35859414
A65: =Agriculture!A59 -> Agriculture | B65: =Agriculture!B59 -> Agricultural pipes (discarded) | C65: =Agriculture!C59 -> EU | D65: =Agriculture!D59 -> PP | E65: =Agriculture!E59 -> 0 | F65: =Agriculture!F59 -> 2 | G65: =Agriculture!G59 -> Assessment of agricultural plastics and their sustainability: A call for action, 2021. . FAO. https://doi.org/10.4060/cb7856en | I65: 1 | J65: 2 | K65: 1 | L65: 1 | M65: 2 | N65: =IF( OR( ISBLANK(H65),ISBLANK(J65), ISBLANK(K65), ISBLANK(L65), ISBLANK(M65) ), "", 1.5*SQRT( EXP(2.21*(H65-1)) + EXP(2.21*(J65-1)) + EXP(2.21*(K65-1)) + EXP(2.21*(L65-1)) + EXP(2.21*M65) )/100*2.45 ) | O65: =IF( OR( ISBLANK(I65),ISBLANK(J65), ISBLANK(K65), ISBLANK(L65), ISBLANK(M65) ), "", 1.5*SQRT( EXP(2.21*(I65-1)) + EXP(2.21*(J65-1)) + EXP(2.21*(K65-1)) + EXP(2.21*(L65-1)) + EXP(2.21*M65) )/100*2.45 ) -> 0.35859414
A66: =Agriculture!A60 -> Agriculture | B66: =Agriculture!B60 -> Agricultural pipes (discarded) | C66: =Agriculture!C60 -> EU | D66: =Agriculture!D60 -> LDPE | E66: =Agriculture!E60 -> 0.045444861 | F66: =Agriculture!F60 -> 2 | G66: =Agriculture!G60 -> Assessment of agricultural plastics and their sustainability: A call for action, 2021. . FAO. https://doi.org/10.4060/cb7856en | I66: 1 | J66: 2 | K66: 1 | L66: 1 | M66: 2 | N66: =IF( OR( ISBLANK(H66),ISBLANK(J66), ISBLANK(K66), ISBLANK(L66), ISBLANK(M66) ), "", 1.5*SQRT( EXP(2.21*(H66-1)) + EXP(2.21*(J66-1)) + EXP(2.21*(K66-1)) + EXP(2.21*(L66-1)) + EXP(2.21*M66) )/100*2.45 ) | O66: =IF( OR( ISBLANK(I66),ISBLANK(J66), ISBLANK(K66), ISBLANK(L66), ISBLANK(M66) ), "", 1.5*SQRT( EXP(2.21*(I66-1)) + EXP(2.21*(J66-1)) + EXP(2.21*(K66-1)) + EXP(2.21*(L66-1)) + EXP(2.21*M66) )/100*2.45 ) -> 0.35859414
A67: =Agriculture!A61 -> Agriculture | B67: =Agriculture!B61 -> Agricultural pipes (discarded) | C67: =Agriculture!C61 -> EU | D67: =Agriculture!D61 -> HDPE | E67: =Agriculture!E61 -> 0.27835663 | F67: =Agriculture!F61 -> 2 | G67: =Agriculture!G61 -> Assessment of agricultural plastics and their sustainability: A call for action, 2021. . FAO. https://doi.org/10.4060/cb7856en | I67: 1 | J67: 2 | K67: 1 | L67: 1 | M67: 2 | N67: =IF( OR( ISBLANK(H67),ISBLANK(J67), ISBLANK(K67), ISBLANK(L67), ISBLANK(M67) ), "", 1.5*SQRT( EXP(2.21*(H67-1)) + EXP(2.21*(J67-1)) + EXP(2.21*(K67-1)) + EXP(2.21*(L67-1)) + EXP(2.21*M67) )/100*2.45 ) | O67: =IF( OR( ISBLANK(I67),ISBLANK(J67), ISBLANK(K67), ISBLANK(L67), ISBLANK(M67) ), "", 1.5*SQRT( EXP(2.21*(I67-1)) + EXP(2.21*(J67-1)) + EXP(2.21*(K67-1)) + EXP(2.21*(L67-1)) + EXP(2.21*M67) )/100*2.45 ) -> 0.35859414
A68: =Agriculture!A82 -> Agriculture | B68: =Agriculture!B82 -> Agricultural pipes (in use) | C68: =Agriculture!C82 -> NL | D68: =Agriculture!D82 -> PVC | E68: =Agriculture!E82 -> 0.03266181 | F68: =Agriculture!F82 -> 2 | G68: =Agriculture!G82 -> Urbanus, J.H., Brunner, A., Boersma, A., Henke, S., Kooter, I., Lensen, S., Parker, L., Schwarz, A., Imhof, P., Dortmans, A., Wijngaard, M., 2022. Autobanden, verpakkingen en landbouwfolie zijn in Nederland de grootste bronnen van microplastics. TNO. | H68: 1 | J68: 2 | K68: 1 | L68: 1 | M68: 2 | N68: =IF( OR( ISBLANK(H68),ISBLANK(J68), ISBLANK(K68), ISBLANK(L68), ISBLANK(M68) ), "", 1.5*SQRT( EXP(2.21*(H68-1)) + EXP(2.21*(J68-1)) + EXP(2.21*(K68-1)) + EXP(2.21*(L68-1)) + EXP(2.21*M68) )/100*2.45 ) -> 0.35859414 | O68: =IF( OR( ISBLANK(I68),ISBLANK(J68), ISBLANK(K68), ISBLANK(L68), ISBLANK(M68) ), "", 1.5*SQRT( EXP(2.21*(I68-1)) + EXP(2.21*(J68-1)) + EXP(2.21*(K68-1)) + EXP(2.21*(L68-1)) + EXP(2.21*M68) )/100*2.45 )
A69: =Agriculture!A83 -> Agriculture | B69: =Agriculture!B83 -> Agricultural pipes (in use) | C69: =Agriculture!C83 -> NL | D69: =Agriculture!D83 -> PS | E69: =Agriculture!E83 -> 0 | F69: =Agriculture!F83 -> 2 | G69: =Agriculture!G83 -> Urbanus, J.H., Brunner, A., Boersma, A., Henke, S., Kooter, I., Lensen, S., Parker, L., Schwarz, A., Imhof, P., Dortmans, A., Wijngaard, M., 2022. Autobanden, verpakkingen en landbouwfolie zijn in Nederland de grootste bronnen van microplastics. TNO. | H69: 1 | J69: 2 | K69: 1 | L69: 1 | M69: 2 | N69: =IF( OR( ISBLANK(H69),ISBLANK(J69), ISBLANK(K69), ISBLANK(L69), ISBLANK(M69) ), "", 1.5*SQRT( EXP(2.21*(H69-1)) + EXP(2.21*(J69-1)) + EXP(2.21*(K69-1)) + EXP(2.21*(L69-1)) + EXP(2.21*M69) )/100*2.45 ) -> 0.35859414 | O69: =IF( OR( ISBLANK(I69),ISBLANK(J69), ISBLANK(K69), ISBLANK(L69), ISBLANK(M69) ), "", 1.5*SQRT( EXP(2.21*(I69-1)) + EXP(2.21*(J69-1)) + EXP(2.21*(K69-1)) + EXP(2.21*(L69-1)) + EXP(2.21*M69) )/100*2.45 )
A70: =Agriculture!A84 -> Agriculture | B70: =Agriculture!B84 -> Agricultural pipes (in use) | C70: =Agriculture!C84 -> NL | D70: =Agriculture!D84 -> PP | E70: =Agriculture!E84 -> 0 | F70: =Agriculture!F84 -> 2 | G70: =Agriculture!G84 -> Urbanus, J.H., Brunner, A., Boersma, A., Henke, S., Kooter, I., Lensen, S., Parker, L., Schwarz, A., Imhof, P., Dortmans, A., Wijngaard, M., 2022. Autobanden, verpakkingen en landbouwfolie zijn in Nederland de grootste bronnen van microplastics. TNO. | H70: 1 | J70: 2 | K70: 1 | L70: 1 | M70: 2 | N70: =IF( OR( ISBLANK(H70),ISBLANK(J70), ISBLANK(K70), ISBLANK(L70), ISBLANK(M70) ), "", 1.5*SQRT( EXP(2.21*(H70-1)) + EXP(2.21*(J70-1)) + EXP(2.21*(K70-1)) + EXP(2.21*(L70-1)) + EXP(2.21*M70) )/100*2.45 ) -> 0.35859414 | O70: =IF( OR( ISBLANK(I70),ISBLANK(J70), ISBLANK(K70), ISBLANK(L70), ISBLANK(M70) ), "", 1.5*SQRT( EXP(2.21*(I70-1)) + EXP(2.21*(J70-1)) + EXP(2.21*(K70-1)) + EXP(2.21*(L70-1)) + EXP(2.21*M70) )/100*2.45 )
A71: =Agriculture!A85 -> Agriculture | B71: =Agriculture!B85 -> Agricultural pipes (in use) | C71: =Agriculture!C85 -> NL | D71: =Agriculture!D85 -> LDPE | E71: =Agriculture!E85 -> 0.011482925 | F71: =Agriculture!F85 -> 2 | G71: =Agriculture!G85 -> Urbanus, J.H., Brunner, A., Boersma, A., Henke, S., Kooter, I., Lensen, S., Parker, L., Schwarz, A., Imhof, P., Dortmans, A., Wijngaard, M., 2022. Autobanden, verpakkingen en landbouwfolie zijn in Nederland de grootste bronnen van microplastics. TNO. | H71: 1 | J71: 2 | K71: 1 | L71: 1 | M71: 2 | N71: =IF( OR( ISBLANK(H71),ISBLANK(J71), ISBLANK(K71), ISBLANK(L71), ISBLANK(M71) ), "", 1.5*SQRT( EXP(2.21*(H71-1)) + EXP(2.21*(J71-1)) + EXP(2.21*(K71-1)) + EXP(2.21*(L71-1)) + EXP(2.21*M71) )/100*2.45 ) -> 0.35859414 | O71: =IF( OR( ISBLANK(I71),ISBLANK(J71), ISBLANK(K71), ISBLANK(L71), ISBLANK(M71) ), "", 1.5*SQRT( EXP(2.21*(I71-1)) + EXP(2.21*(J71-1)) + EXP(2.21*(K71-1)) + EXP(2.21*(L71-1)) + EXP(2.21*M71) )/100*2.45 )
A72: =Agriculture!A86 -> Agriculture | B72: =Agriculture!B86 -> Agricultural pipes (in use) | C72: =Agriculture!C86 -> NL | D72: =Agriculture!D86 -> HDPE | E72: =Agriculture!E86 -> 0.045067281 | F72: =Agriculture!F86 -> 2 | G72: =Agriculture!G86 -> Urbanus, J.H., Brunner, A., Boersma, A., Henke, S., Kooter, I., Lensen, S., Parker, L., Schwarz, A., Imhof, P., Dortmans, A., Wijngaard, M., 2022. Autobanden, verpakkingen en landbouwfolie zijn in Nederland de grootste bronnen van microplastics. TNO. | H72: 1 | J72: 2 | K72: 1 | L72: 1 | M72: 2 | N72: =IF( OR( ISBLANK(H72),ISBLANK(J72), ISBLANK(K72), ISBLANK(L72), ISBLANK(M72) ), "", 1.5*SQRT( EXP(2.21*(H72-1)) + EXP(2.21*(J72-1)) + EXP(2.21*(K72-1)) + EXP(2.21*(L72-1)) + EXP(2.21*M72) )/100*2.45 ) -> 0.35859414 | O72: =IF( OR( ISBLANK(I72),ISBLANK(J72), ISBLANK(K72), ISBLANK(L72), ISBLANK(M72) ), "", 1.5*SQRT( EXP(2.21*(I72-1)) + EXP(2.21*(J72-1)) + EXP(2.21*(K72-1)) + EXP(2.21*(L72-1)) + EXP(2.21*M72) )/100*2.45 )
A73: =Agriculture!A87 -> Agriculture | B73: =Agriculture!B87 -> Agricultural pipes (in use) | C73: =Agriculture!C87 -> EU | D73: =Agriculture!D87 -> PVC | E73: =Agriculture!E87 -> 0.013425394 | F73: =Agriculture!F87 -> 2 | G73: =Agriculture!G87 -> Assessment of agricultural plastics and their sustainability: A call for action, 2021. . FAO. https://doi.org/10.4060/cb7856en | I73: 1 | J73: 2 | K73: 1 | L73: 1 | M73: 2 | N73: =IF( OR( ISBLANK(H73),ISBLANK(J73), ISBLANK(K73), ISBLANK(L73), ISBLANK(M73) ), "", 1.5*SQRT( EXP(2.21*(H73-1)) + EXP(2.21*(J73-1)) + EXP(2.21*(K73-1)) + EXP(2.21*(L73-1)) + EXP(2.21*M73) )/100*2.45 ) | O73: =IF( OR( ISBLANK(I73),ISBLANK(J73), ISBLANK(K73), ISBLANK(L73), ISBLANK(M73) ), "", 1.5*SQRT( EXP(2.21*(I73-1)) + EXP(2.21*(J73-1)) + EXP(2.21*(K73-1)) + EXP(2.21*(L73-1)) + EXP(2.21*M73) )/100*2.45 ) -> 0.35859414
A74: =Agriculture!A88 -> Agriculture | B74: =Agriculture!B88 -> Agricultural pipes (in use) | C74: =Agriculture!C88 -> EU | D74: =Agriculture!D88 -> PS | E74: =Agriculture!E88 -> 0 | F74: =Agriculture!F88 -> 2 | G74: =Agriculture!G88 -> Assessment of agricultural plastics and their sustainability: A call for action, 2021. . FAO. https://doi.org/10.4060/cb7856en | I74: 1 | J74: 2 | K74: 1 | L74: 1 | M74: 2 | N74: =IF( OR( ISBLANK(H74),ISBLANK(J74), ISBLANK(K74), ISBLANK(L74), ISBLANK(M74) ), "", 1.5*SQRT( EXP(2.21*(H74-1)) + EXP(2.21*(J74-1)) + EXP(2.21*(K74-1)) + EXP(2.21*(L74-1)) + EXP(2.21*M74) )/100*2.45 ) | O74: =IF( OR( ISBLANK(I74),ISBLANK(J74), ISBLANK(K74), ISBLANK(L74), ISBLANK(M74) ), "", 1.5*SQRT( EXP(2.21*(I74-1)) + EXP(2.21*(J74-1)) + EXP(2.21*(K74-1)) + EXP(2.21*(L74-1)) + EXP(2.21*M74) )/100*2.45 ) -> 0.35859414
A75: =Agriculture!A89 -> Agriculture | B75: =Agriculture!B89 -> Agricultural pipes (in use) | C75: =Agriculture!C89 -> EU | D75: =Agriculture!D89 -> PP | E75: =Agriculture!E89 -> 0 | F75: =Agriculture!F89 -> 2 | G75: =Agriculture!G89 -> Assessment of agricultural plastics and their sustainability: A call for action, 2021. . FAO. https://doi.org/10.4060/cb7856en | I75: 1 | J75: 2 | K75: 1 | L75: 1 | M75: 2 | N75: =IF( OR( ISBLANK(H75),ISBLANK(J75), ISBLANK(K75), ISBLANK(L75), ISBLANK(M75) ), "", 1.5*SQRT( EXP(2.21*(H75-1)) + EXP(2.21*(J75-1)) + EXP(2.21*(K75-1)) + EXP(2.21*(L75-1)) + EXP(2.21*M75) )/100*2.45 ) | O75: =IF( OR( ISBLANK(I75),ISBLANK(J75), ISBLANK(K75), ISBLANK(L75), ISBLANK(M75) ), "", 1.5*SQRT( EXP(2.21*(I75-1)) + EXP(2.21*(J75-1)) + EXP(2.21*(K75-1)) + EXP(2.21*(L75-1)) + EXP(2.21*M75) )/100*2.45 ) -> 0.35859414
A76: =Agriculture!A90 -> Agriculture | B76: =Agriculture!B90 -> Agricultural pipes (in use) | C76: =Agriculture!C90 -> EU | D76: =Agriculture!D90 -> LDPE | E76: =Agriculture!E90 -> 0.0036459765 | F76: =Agriculture!F90 -> 2 | G76: =Agriculture!G90 -> Assessment of agricultural plastics and their sustainability: A call for action, 2021. . FAO. https://doi.org/10.4060/cb7856en | I76: 1 | J76: 2 | K76: 1 | L76: 1 | M76: 2 | N76: =IF( OR( ISBLANK(H76),ISBLANK(J76), ISBLANK(K76), ISBLANK(L76), ISBLANK(M76) ), "", 1.5*SQRT( EXP(2.21*(H76-1)) + EXP(2.21*(J76-1)) + EXP(2.21*(K76-1)) + EXP(2.21*(L76-1)) + EXP(2.21*M76) )/100*2.45 ) | O76: =IF( OR( ISBLANK(I76),ISBLANK(J76), ISBLANK(K76), ISBLANK(L76), ISBLANK(M76) ), "", 1.5*SQRT( EXP(2.21*(I76-1)) + EXP(2.21*(J76-1)) + EXP(2.21*(K76-1)) + EXP(2.21*(L76-1)) + EXP(2.21*M76) )/100*2.45 ) -> 0.35859414
A77: =Agriculture!A91 -> Agriculture | B77: =Agriculture!B91 -> Agricultural pipes (in use) | C77: =Agriculture!C91 -> EU | D77: =Agriculture!D91 -> HDPE | E77: =Agriculture!E91 -> 0.022332156 | F77: =Agriculture!F91 -> 2 | G77: =Agriculture!G91 -> Assessment of agricultural plastics and their sustainability: A call for action, 2021. . FAO. https://doi.org/10.4060/cb7856en | I77: 1 | J77: 2 | K77: 1 | L77: 1 | M77: 2 | N77: =IF( OR( ISBLANK(H77),ISBLANK(J77), ISBLANK(K77), ISBLANK(L77), ISBLANK(M77) ), "", 1.5*SQRT( EXP(2.21*(H77-1)) + EXP(2.21*(J77-1)) + EXP(2.21*(K77-1)) + EXP(2.21*(L77-1)) + EXP(2.21*M77) )/100*2.45 ) | O77: =IF( OR( ISBLANK(I77),ISBLANK(J77), ISBLANK(K77), ISBLANK(L77), ISBLANK(M77) ), "", 1.5*SQRT( EXP(2.21*(I77-1)) + EXP(2.21*(J77-1)) + EXP(2.21*(K77-1)) + EXP(2.21*(L77-1)) + EXP(2.21*M77) )/100*2.45 ) -> 0.35859414
A78: =Agriculture!A146 -> Agricultural waste collection | B78: =Agriculture!B146 -> Agricultural plastic recycling | C78: =Agriculture!C146 -> any | D78: =Agriculture!D146 -> any | E78: =Agriculture!E146 -> 0.12 | F78: =Agriculture!F146 -> 1 | G78: =Agriculture!G146 -> Schelker, Raymond, and Patrik Geisselhardt, Welche Fraktionen - Hauptkunststoffe, 2011 | H78: 2 | I78: 2 | J78: 2 | K78: 3 | L78: 1 | M78: 2 | N78: =IF( OR( ISBLANK(H78),ISBLANK(J78), ISBLANK(K78), ISBLANK(L78), ISBLANK(M78) ), "", 1.5*SQRT( EXP(2.21*(H78-1)) + EXP(2.21*(J78-1)) + EXP(2.21*(K78-1)) + EXP(2.21*(L78-1)) + EXP(2.21*M78) )/100*2.45 ) -> 0.50042652 | O78: =IF( OR( ISBLANK(I78),ISBLANK(J78), ISBLANK(K78), ISBLANK(L78), ISBLANK(M78) ), "", 1.5*SQRT( EXP(2.21*(I78-1)) + EXP(2.21*(J78-1)) + EXP(2.21*(K78-1)) + EXP(2.21*(L78-1)) + EXP(2.21*M78) )/100*2.45 ) -> 0.50042652
A79: =Agriculture!A147 -> Agricultural waste collection | B79: =Agriculture!B147 -> Agricultural plastic recycling | C79: =Agriculture!C147 -> any | D79: =Agriculture!D147 -> any | E79: =Agriculture!E147 -> 0.1333 | F79: =Agriculture!F147 -> 1 | G79: =Agriculture!G147 -> Müller Andreas, 2016 | H79: 2 | I79: 2 | J79: 2 | K79: 3 | L79: 1 | M79: 2 | N79: =IF( OR( ISBLANK(H79),ISBLANK(J79), ISBLANK(K79), ISBLANK(L79), ISBLANK(M79) ), "", 1.5*SQRT( EXP(2.21*(H79-1)) + EXP(2.21*(J79-1)) + EXP(2.21*(K79-1)) + EXP(2.21*(L79-1)) + EXP(2.21*M79) )/100*2.45 ) -> 0.50042652 | O79: =IF( OR( ISBLANK(I79),ISBLANK(J79), ISBLANK(K79), ISBLANK(L79), ISBLANK(M79) ), "", 1.5*SQRT( EXP(2.21*(I79-1)) + EXP(2.21*(J79-1)) + EXP(2.21*(K79-1)) + EXP(2.21*(L79-1)) + EXP(2.21*M79) )/100*2.45 ) -> 0.50042652
A80: =Agriculture!A148 -> Agricultural waste collection | B80: =Agriculture!B148 -> Agricultural plastic recycling | C80: =Agriculture!C148 -> any | D80: =Agriculture!D148 -> any | E80: =Agriculture!E148 -> 0.2667 | F80: =Agriculture!F148 -> 1 | G80: =Agriculture!G148 -> Müller Andreas, 2016 | H80: 2 | I80: 2 | J80: 2 | K80: 3 | L80: 1 | M80: 2 | N80: =IF( OR( ISBLANK(H80),ISBLANK(J80), ISBLANK(K80), ISBLANK(L80), ISBLANK(M80) ), "", 1.5*SQRT( EXP(2.21*(H80-1)) + EXP(2.21*(J80-1)) + EXP(2.21*(K80-1)) + EXP(2.21*(L80-1)) + EXP(2.21*M80) )/100*2.45 ) -> 0.50042652 | O80: =IF( OR( ISBLANK(I80),ISBLANK(J80), ISBLANK(K80), ISBLANK(L80), ISBLANK(M80) ), "", 1.5*SQRT( EXP(2.21*(I80-1)) + EXP(2.21*(J80-1)) + EXP(2.21*(K80-1)) + EXP(2.21*(L80-1)) + EXP(2.21*M80) )/100*2.45 ) -> 0.50042652
A81: =Agriculture!A149 -> Agricultural waste collection | B81: =Agriculture!B149 -> Agricultural plastic recycling | C81: =Agriculture!C149 -> any | D81: =Agriculture!D149 -> any | E81: =Agriculture!E149 -> 0.2 | F81: =Agriculture!F149 -> 1 | G81: =Agriculture!G149 -> Schelker, Raymond, and Patrik Geisselhardt, Projekt „ Kunststoff-Verwertung Schweiz “: Bericht Module 1 Und 2, 2011 | H81: 2 | I81: 2 | J81: 2 | K81: 3 | L81: 1 | M81: 2 | N81: =IF( OR( ISBLANK(H81),ISBLANK(J81), ISBLANK(K81), ISBLANK(L81), ISBLANK(M81) ), "", 1.5*SQRT( EXP(2.21*(H81-1)) + EXP(2.21*(J81-1)) + EXP(2.21*(K81-1)) + EXP(2.21*(L81-1)) + EXP(2.21*M81) )/100*2.45 ) -> 0.50042652 | O81: =IF( OR( ISBLANK(I81),ISBLANK(J81), ISBLANK(K81), ISBLANK(L81), ISBLANK(M81) ), "", 1.5*SQRT( EXP(2.21*(I81-1)) + EXP(2.21*(J81-1)) + EXP(2.21*(K81-1)) + EXP(2.21*(L81-1)) + EXP(2.21*M81) )/100*2.45 ) -> 0.50042652 | P81: =Agriculture!P149 -> Value for films
A82: =Agriculture!A145 -> Agricultural waste collection | B82: =Agriculture!B145 -> Incineration | C82: =Agriculture!C145 -> any | D82: =Agriculture!D145 -> any | E82: =Agriculture!E145 -> rest | F82: =Agriculture!F145 -> 1 | G82: =Agriculture!G145 -> 0 | N82: =IF( OR( ISBLANK(H82),ISBLANK(J82), ISBLANK(K82), ISBLANK(L82), ISBLANK(M82) ), "", 1.5*SQRT( EXP(2.21*(H82-1)) + EXP(2.21*(J82-1)) + EXP(2.21*(K82-1)) + EXP(2.21*(L82-1)) + EXP(2.21*M82) )/100*2.45 ) | O82: =IF( OR( ISBLANK(I82),ISBLANK(J82), ISBLANK(K82), ISBLANK(L82), ISBLANK(M82) ), "", 1.5*SQRT( EXP(2.21*(I82-1)) + EXP(2.21*(J82-1)) + EXP(2.21*(K82-1)) + EXP(2.21*(L82-1)) + EXP(2.21*M82) )/100*2.45 )
A83: =Agriculture!A144 -> Agricultural waste collection | B83: =Agriculture!B144 -> Landfill | C83: =Agriculture!C144 -> any | D83: =Agriculture!D144 -> any | E83: =Agriculture!E144 -> 0 | F83: =Agriculture!F144 -> 1 | G83: =Agriculture!G144 -> 0 | N83: =IF( OR( ISBLANK(H83),ISBLANK(J83), ISBLANK(K83), ISBLANK(L83), ISBLANK(M83) ), "", 1.5*SQRT( EXP(2.21*(H83-1)) + EXP(2.21*(J83-1)) + EXP(2.21*(K83-1)) + EXP(2.21*(L83-1)) + EXP(2.21*M83) )/100*2.45 ) | O83: =IF( OR( ISBLANK(I83),ISBLANK(J83), ISBLANK(K83), ISBLANK(L83), ISBLANK(M83) ), "", 1.5*SQRT( EXP(2.21*(I83-1)) + EXP(2.21*(J83-1)) + EXP(2.21*(K83-1)) + EXP(2.21*(L83-1)) + EXP(2.21*M83) )/100*2.45 )
A84: =Agriculture!A143 -> Agricultural waste collection | B84: =Agriculture!B143 -> Residential soil (macro) | C84: =Agriculture!C143 -> any | D84: =Agriculture!D143 -> any | E84: =Agriculture!E143 -> 0.0001 | F84: =Agriculture!F143 -> 2 | G84: =Agriculture!G143 -> Assumption | H84: 1 | I84: 2 | J84: 1 | K84: 1 | L84: 1 | M84: 3 | N84: =IF( OR( ISBLANK(H84),ISBLANK(J84), ISBLANK(K84), ISBLANK(L84), ISBLANK(M84) ), "", 1.5*SQRT( EXP(2.21*(H84-1)) + EXP(2.21*(J84-1)) + EXP(2.21*(K84-1)) + EXP(2.21*(L84-1)) + EXP(2.21*M84) )/100*2.45 ) -> 1.014115 | O84: =IF( OR( ISBLANK(I84),ISBLANK(J84), ISBLANK(K84), ISBLANK(L84), ISBLANK(M84) ), "", 1.5*SQRT( EXP(2.21*(I84-1)) + EXP(2.21*(J84-1)) + EXP(2.21*(K84-1)) + EXP(2.21*(L84-1)) + EXP(2.21*M84) )/100*2.45 ) -> 1.0195048
A85: Agricultural waste collection (micro) | B85: Agricultural plastic recycling | C85: any | D85: any | E85: 0.12 | F85: 1 | G85: Schelker, Raymond, and Patrik Geisselhardt, Welche Fraktionen - Hauptkunststoffe, 2011 | H85: 2 | I85: 2 | J85: 2 | K85: 3 | L85: 1 | M85: 2 | N85: 0.50042652 | O85: 0.50042652
A86: Agricultural packaging bottles | B86: Agricultural soil (macro) | C86: any | D86: any | E86: 0 | F86: 2 | G86: Best case scenario | N86: =IF( OR( ISBLANK(H86),ISBLANK(J86), ISBLANK(K86), ISBLANK(L86), ISBLANK(M86) ), "", 1.5*SQRT( EXP(2.21*(H86-1)) + EXP(2.21*(J86-1)) + EXP(2.21*(K86-1)) + EXP(2.21*(L86-1)) + EXP(2.21*M86) )/100*2.45 ) | O86: =IF( OR( ISBLANK(I86),ISBLANK(J86), ISBLANK(K86), ISBLANK(L86), ISBLANK(M86) ), "", 1.5*SQRT( EXP(2.21*(I86-1)) + EXP(2.21*(J86-1)) + EXP(2.21*(K86-1)) + EXP(2.21*(L86-1)) + EXP(2.21*M86) )/100*2.45 )
A87: Agricultural packaging bottles | B87: Agricultural soil (macro) | C87: any | D87: any | E87: 0.016 | F87: 2 | G87: Based on Agreste. Chiffres-Clés : 61 Hectares En Moyenne Par Exploitation; 2017 | H87: 1 | J87: 1 | K87: 1 | L87: 1 | M87: 3 | N87: =IF( OR( ISBLANK(H87),ISBLANK(J87), ISBLANK(K87), ISBLANK(L87), ISBLANK(M87) ), "", 1.5*SQRT( EXP(2.21*(H87-1)) + EXP(2.21*(J87-1)) + EXP(2.21*(K87-1)) + EXP(2.21*(L87-1)) + EXP(2.21*M87) )/100*2.45 ) -> 1.014115 | O87: =IF( OR( ISBLANK(I87),ISBLANK(J87), ISBLANK(K87), ISBLANK(L87), ISBLANK(M87) ), "", 1.5*SQRT( EXP(2.21*(I87-1)) + EXP(2.21*(J87-1)) + EXP(2.21*(K87-1)) + EXP(2.21*(L87-1)) + EXP(2.21*M87) )/100*2.45 )
A88: Agricultural packaging films | B88: Agricultural soil (macro) | C88: any | D88: any | E88: 0 | F88: 2 | G88: Best case scenario | N88: =IF( OR( ISBLANK(H88),ISBLANK(J88), ISBLANK(K88), ISBLANK(L88), ISBLANK(M88) ), "", 1.5*SQRT( EXP(2.21*(H88-1)) + EXP(2.21*(J88-1)) + EXP(2.21*(K88-1)) + EXP(2.21*(L88-1)) + EXP(2.21*M88) )/100*2.45 ) | O88: =IF( OR( ISBLANK(I88),ISBLANK(J88), ISBLANK(K88), ISBLANK(L88), ISBLANK(M88) ), "", 1.5*SQRT( EXP(2.21*(I88-1)) + EXP(2.21*(J88-1)) + EXP(2.21*(K88-1)) + EXP(2.21*(L88-1)) + EXP(2.21*M88) )/100*2.45 )
A89: Agricultural packaging films | B89: Agricultural soil (macro) | C89: any | D89: any | E89: 0.059 | F89: 2 | G89: Based on Agreste. Chiffres-Clés : 61 Hectares En Moyenne Par Exploitation; 2017 | H89: 1 | J89: 1 | K89: 1 | L89: 1 | M89: 3 | N89: =IF( OR( ISBLANK(H89),ISBLANK(J89), ISBLANK(K89), ISBLANK(L89), ISBLANK(M89) ), "", 1.5*SQRT( EXP(2.21*(H89-1)) + EXP(2.21*(J89-1)) + EXP(2.21*(K89-1)) + EXP(2.21*(L89-1)) + EXP(2.21*M89) )/100*2.45 ) -> 1.014115 | O89: =IF( OR( ISBLANK(I89),ISBLANK(J89), ISBLANK(K89), ISBLANK(L89), ISBLANK(M89) ), "", 1.5*SQRT( EXP(2.21*(I89-1)) + EXP(2.21*(J89-1)) + EXP(2.21*(K89-1)) + EXP(2.21*(L89-1)) + EXP(2.21*M89) )/100*2.45 )
A90: Compost (macro) | B90: Agricultural soil (macro) | C90: any | D90: any | E90: rest | F90: 1 | N90: =IF( OR( ISBLANK(H90),ISBLANK(J90), ISBLANK(K90), ISBLANK(L90), ISBLANK(M90) ), "", 1.5*SQRT( EXP(2.21*(H90-1)) + EXP(2.21*(J90-1)) + EXP(2.21*(K90-1)) + EXP(2.21*(L90-1)) + EXP(2.21*M90) )/100*2.45 ) | O90: =IF( OR( ISBLANK(I90),ISBLANK(J90), ISBLANK(K90), ISBLANK(L90), ISBLANK(M90) ), "", 1.5*SQRT( EXP(2.21*(I90-1)) + EXP(2.21*(J90-1)) + EXP(2.21*(K90-1)) + EXP(2.21*(L90-1)) + EXP(2.21*M90) )/100*2.45 ) | P90: 97% is used in horticulture and agriculture
A91: Agrotextiles | B91: Agrotextiles (discarded) | C91: any | D91: any | E91: rest | F91: 1 | N91: =IF( OR( ISBLANK(H91),ISBLANK(J91), ISBLANK(K91), ISBLANK(L91), ISBLANK(M91) ), "", 1.5*SQRT( EXP(2.21*(H91-1)) + EXP(2.21*(J91-1)) + EXP(2.21*(K91-1)) + EXP(2.21*(L91-1)) + EXP(2.21*M91) )/100*2.45 ) | O91: =IF( OR( ISBLANK(I91),ISBLANK(J91), ISBLANK(K91), ISBLANK(L91), ISBLANK(M91) ), "", 1.5*SQRT( EXP(2.21*(I91-1)) + EXP(2.21*(J91-1)) + EXP(2.21*(K91-1)) + EXP(2.21*(L91-1)) + EXP(2.21*M91) )/100*2.45 )
A92: =Agriculture!A115 -> Agricultural mulching films | B92: =Agriculture!B115 -> Agricultural soil (macro) | C92: =Agriculture!C115 -> any | D92: =Agriculture!D115 -> any | E92: =Agriculture!E115 -> 0 | F92: =Agriculture!F115 -> 2 | G92: =Agriculture!G115 -> Best case scenario | N92: =IF( OR( ISBLANK(H92),ISBLANK(J92), ISBLANK(K92), ISBLANK(L92), ISBLANK(M92) ), "", 1.5*SQRT( EXP(2.21*(H92-1)) + EXP(2.21*(J92-1)) + EXP(2.21*(K92-1)) + EXP(2.21*(L92-1)) + EXP(2.21*M92) )/100*2.45 ) | O92: =IF( OR( ISBLANK(I92),ISBLANK(J92), ISBLANK(K92), ISBLANK(L92), ISBLANK(M92) ), "", 1.5*SQRT( EXP(2.21*(I92-1)) + EXP(2.21*(J92-1)) + EXP(2.21*(K92-1)) + EXP(2.21*(L92-1)) + EXP(2.21*M92) )/100*2.45 )
A93: =Agriculture!A116 -> Agricultural mulching films | B93: =Agriculture!B116 -> Agricultural soil (macro) | C93: =Agriculture!C116 -> any | D93: =Agriculture!D116 -> any | E93: =Agriculture!E116 -> 0.037 | F93: =Agriculture!F116 -> 2 | G93: =Agriculture!G116 -> Based on Agreste. Chiffres-Clés : 61 Hectares En Moyenne Par Exploitation; 2017 | H93: 2 | I93: 2 | J93: 2 | K93: 1 | L93: 1 | M93: 3 | N93: =IF( OR( ISBLANK(H93),ISBLANK(J93), ISBLANK(K93), ISBLANK(L93), ISBLANK(M93) ), "", 1.5*SQRT( EXP(2.21*(H93-1)) + EXP(2.21*(J93-1)) + EXP(2.21*(K93-1)) + EXP(2.21*(L93-1)) + EXP(2.21*M93) )/100*2.45 ) -> 1.0248662 | O93: =IF( OR( ISBLANK(I93),ISBLANK(J93), ISBLANK(K93), ISBLANK(L93), ISBLANK(M93) ), "", 1.5*SQRT( EXP(2.21*(I93-1)) + EXP(2.21*(J93-1)) + EXP(2.21*(K93-1)) + EXP(2.21*(L93-1)) + EXP(2.21*M93) )/100*2.45 ) -> 1.0248662
A94: =Agriculture!A121 -> Agricultural other | B94: =Agriculture!B121 -> Agricultural soil (macro) | C94: =Agriculture!C121 -> any | D94: =Agriculture!D121 -> any | E94: =Agriculture!E121 -> 0 | F94: =Agriculture!F121 -> 2 | G94: =Agriculture!G121 -> Best case scenario | N94: =IF( OR( ISBLANK(H94),ISBLANK(J94), ISBLANK(K94), ISBLANK(L94), ISBLANK(M94) ), "", 1.5*SQRT( EXP(2.21*(H94-1)) + EXP(2.21*(J94-1)) + EXP(2.21*(K94-1)) + EXP(2.21*(L94-1)) + EXP(2.21*M94) )/100*2.45 ) | O94: =IF( OR( ISBLANK(I94),ISBLANK(J94), ISBLANK(K94), ISBLANK(L94), ISBLANK(M94) ), "", 1.5*SQRT( EXP(2.21*(I94-1)) + EXP(2.21*(J94-1)) + EXP(2.21*(K94-1)) + EXP(2.21*(L94-1)) + EXP(2.21*M94) )/100*2.45 )
A95: =Agriculture!A122 -> Agricultural other | B95: =Agriculture!B122 -> Agricultural soil (macro) | C95: =Agriculture!C122 -> any | D95: =Agriculture!D122 -> any | E95: =Agriculture!E122 -> 0.038 | F95: =Agriculture!F122 -> 2 | G95: =Agriculture!G122 -> Based on Agreste. Chiffres-Clés : 61 Hectares En Moyenne Par Exploitation; 2017 | H95: 2 | I95: 2 | J95: 2 | K95: 1 | L95: 1 | M95: 3 | N95: =IF( OR( ISBLANK(H95),ISBLANK(J95), ISBLANK(K95), ISBLANK(L95), ISBLANK(M95) ), "", 1.5*SQRT( EXP(2.21*(H95-1)) + EXP(2.21*(J95-1)) + EXP(2.21*(K95-1)) + EXP(2.21*(L95-1)) + EXP(2.21*M95) )/100*2.45 ) -> 1.0248662 | O95: =IF( OR( ISBLANK(I95),ISBLANK(J95), ISBLANK(K95), ISBLANK(L95), ISBLANK(M95) ), "", 1.5*SQRT( EXP(2.21*(I95-1)) + EXP(2.21*(J95-1)) + EXP(2.21*(K95-1)) + EXP(2.21*(L95-1)) + EXP(2.21*M95) )/100*2.45 ) -> 1.0248662
A96: =Agriculture!A125 -> Agricultural pipes (in use) | B96: =Agriculture!B125 -> Agricultural soil (macro) | C96: =Agriculture!C125 -> any | D96: =Agriculture!D125 -> any | E96: =Agriculture!E125 -> 0 | F96: =Agriculture!F125 -> 2 | G96: =Agriculture!G125 -> Best case scenario | N96: =IF( OR( ISBLANK(H96),ISBLANK(J96), ISBLANK(K96), ISBLANK(L96), ISBLANK(M96) ), "", 1.5*SQRT( EXP(2.21*(H96-1)) + EXP(2.21*(J96-1)) + EXP(2.21*(K96-1)) + EXP(2.21*(L96-1)) + EXP(2.21*M96) )/100*2.45 ) | O96: =IF( OR( ISBLANK(I96),ISBLANK(J96), ISBLANK(K96), ISBLANK(L96), ISBLANK(M96) ), "", 1.5*SQRT( EXP(2.21*(I96-1)) + EXP(2.21*(J96-1)) + EXP(2.21*(K96-1)) + EXP(2.21*(L96-1)) + EXP(2.21*M96) )/100*2.45 ) | P96: =Agriculture!P125 -> Normalized (See Agriculture sheet)
A97: =Agriculture!A126 -> Agricultural pipes (in use) | B97: =Agriculture!B126 -> Agricultural soil (macro) | C97: =Agriculture!C126 -> any | D97: =Agriculture!D126 -> any | E97: =Agriculture!E126 -> 0.51351351 | F97: =Agriculture!F126 -> 2 | G97: =Agriculture!G126 -> Based on Agreste. Chiffres-Clés : 61 Hectares En Moyenne Par Exploitation; 2017 | H97: 2 | I97: 2 | J97: 2 | K97: 1 | L97: 1 | M97: 3 | N97: =IF( OR( ISBLANK(H97),ISBLANK(J97), ISBLANK(K97), ISBLANK(L97), ISBLANK(M97) ), "", 1.5*SQRT( EXP(2.21*(H97-1)) + EXP(2.21*(J97-1)) + EXP(2.21*(K97-1)) + EXP(2.21*(L97-1)) + EXP(2.21*M97) )/100*2.45 ) -> 1.0248662 | O97: =IF( OR( ISBLANK(I97),ISBLANK(J97), ISBLANK(K97), ISBLANK(L97), ISBLANK(M97) ), "", 1.5*SQRT( EXP(2.21*(I97-1)) + EXP(2.21*(J97-1)) + EXP(2.21*(K97-1)) + EXP(2.21*(L97-1)) + EXP(2.21*M97) )/100*2.45 ) -> 1.0248662 | P97: =Agriculture!P126 -> Normalized (See Agriculture sheet)
A98: =Agriculture!A129 -> Agricultural greenhouse films (in use) | B98: =Agriculture!B129 -> Agricultural soil (macro) | C98: =Agriculture!C129 -> any | D98: =Agriculture!D129 -> any | E98: =Agriculture!E129 -> 0 | F98: =Agriculture!F129 -> 2 | G98: =Agriculture!G129 -> Best case scenario | N98: =IF( OR( ISBLANK(H98),ISBLANK(J98), ISBLANK(K98), ISBLANK(L98), ISBLANK(M98) ), "", 1.5*SQRT( EXP(2.21*(H98-1)) + EXP(2.21*(J98-1)) + EXP(2.21*(K98-1)) + EXP(2.21*(L98-1)) + EXP(2.21*M98) )/100*2.45 ) | O98: =IF( OR( ISBLANK(I98),ISBLANK(J98), ISBLANK(K98), ISBLANK(L98), ISBLANK(M98) ), "", 1.5*SQRT( EXP(2.21*(I98-1)) + EXP(2.21*(J98-1)) + EXP(2.21*(K98-1)) + EXP(2.21*(L98-1)) + EXP(2.21*M98) )/100*2.45 ) | P98: =Agriculture!P129 -> Normalized (See Agriculture sheet)
A99: =Agriculture!A130 -> Agricultural greenhouse films (in use) | B99: =Agriculture!B130 -> Agricultural soil (macro) | C99: =Agriculture!C130 -> any | D99: =Agriculture!D130 -> any | E99: =Agriculture!E130 -> 0.40217391 | F99: =Agriculture!F130 -> 2 | G99: =Agriculture!G130 -> Based on Agreste. Chiffres-Clés : 61 Hectares En Moyenne Par Exploitation; 2017 | H99: 2 | I99: 2 | J99: 2 | K99: 1 | L99: 1 | M99: 3 | N99: =IF( OR( ISBLANK(H99),ISBLANK(J99), ISBLANK(K99), ISBLANK(L99), ISBLANK(M99) ), "", 1.5*SQRT( EXP(2.21*(H99-1)) + EXP(2.21*(J99-1)) + EXP(2.21*(K99-1)) + EXP(2.21*(L99-1)) + EXP(2.21*M99) )/100*2.45 ) -> 1.0248662 | O99: =IF( OR( ISBLANK(I99),ISBLANK(J99), ISBLANK(K99), ISBLANK(L99), ISBLANK(M99) ), "", 1.5*SQRT( EXP(2.21*(I99-1)) + EXP(2.21*(J99-1)) + EXP(2.21*(K99-1)) + EXP(2.21*(L99-1)) + EXP(2.21*M99) )/100*2.45 ) -> 1.0248662 | P99: =Agriculture!P130 -> Normalized (See Agriculture sheet)
A100: Compost (micro) | B100: Agricultural soil (micro) | C100: any | D100: any | E100: rest | F100: 1 | N100: =IF( OR( ISBLANK(H100),ISBLANK(J100), ISBLANK(K100), ISBLANK(L100), ISBLANK(M100) ), "", 1.5*SQRT( EXP(2.21*(H100-1)) + EXP(2.21*(J100-1)) + EXP(2.21*(K100-1)) + EXP(2.21*(L100-1)) + EXP(2.21*M100) )/100*2.45 ) | O100: =IF( OR( ISBLANK(I100),ISBLANK(J100), ISBLANK(K100), ISBLANK(L100), ISBLANK(M100) ), "", 1.5*SQRT( EXP(2.21*(I100-1)) + EXP(2.21*(J100-1)) + EXP(2.21*(K100-1)) + EXP(2.21*(L100-1)) + EXP(2.21*M100) )/100*2.45 ) | P100: 97% is used in horticulture and agriculture
...

Sheet Input_compartment_order
A1: Domestic primary plastic production
A2: Import of primary plastics
A3: Transport of primary plastics
A4: Agriculture
A5: Clothing (product sector)
A6: Household textiles (product sector)
A7: Technical textiles
A8: Intentionally produced microparticles
A9: Packaging
A10: Paint
A11: Tyre wear

Sheet Clothing_update
A1: Transfer coefficients
A3: From | B3: To | C3: Scale | D3: Material | E3: Data | F3: Priority | G3: Source | H3: Geo NL | I3: Geo EU | J3: Temp | K3: Mat | L3: Tech | M3: Rel | N3: Comments
A4: Fibre production (EU) | B4: Pre-consumer textile recycling | C4: NL | D4: any | E4: 0.03 | F4: 2 | G4: Burkhardt, Michael, Alexander Englert, Rico Iten, and Sandro Schärer, Entsorgung Nanosilberhaltiger Abfälle in Der Textilindustrie - Massenflüsse Und Behandlungsverfahren, 2011 | H4: 2 | I4: 2 | J4: 3 | K4: 3 | L4: 3 | M4: 2
A5: Fibre production (EU) | B5: Pre-consumer textile recycling | C5: NL | D5: any | E5: 0.0651 | F5: 2 | G5: Draft Product Environmental Footprint Category Rules (PEFCR) Apparel and Footwear, 2021 | H5: 2 | I5: 2 | J5: 1 | K5: 3 | L5: 2 | M5: 1 | P5: New compartments | Q5: Type
A6: Fibre production (EU) | B6: Clothing manufacturing | C6: NL | D6: any | E6: rest | F6: 1 | O6: New input compartment | P6: Fibre production (EU) | Q6: Flow
A7: Fibre production (outside EU) | B7: Pre-consumer textile recycling | C7: NL | D7: any | E7: 0.03 | F7: 2 | G7: Burkhardt, Michael, Alexander Englert, Rico Iten, and Sandro Schärer, Entsorgung Nanosilberhaltiger Abfälle in Der Textilindustrie - Massenflüsse Und Behandlungsverfahren, 2011 | H7: 2 | I7: 2 | J7: 3 | K7: 3 | L7: 3 | M7: 2 | O7: New input compartment | P7: Fibre production (outside EU) | Q7: Flow
A8: Fibre production (outside EU) | B8: Pre-consumer textile recycling | C8: NL | D8: any | E8: 0.0651 | F8: 2 | G8: Draft Product Environmental Footprint Category Rules (PEFCR) Apparel and Footwear, 2021 | H8: 2 | I8: 2 | J8: 1 | K8: 3 | L8: 2 | M8: 1 | P8: Clothing manufacturing | Q8: Flow
A9: Fibre production (outside EU) | B9: Clothing manufacturing | C9: NL | D9: any | E9: rest | F9: 1 | P9: Pre-consumer textile recycling | Q9: Flow
A10: Clothing manufacturing | B10: Pre-consumer textile recycling | C10: any | D10: any | E10: 0.1 | F10: 2 | G10: Burkhardt, Michael, Alexander Englert, Rico Iten, and Sandro Schärer, Entsorgung Nanosilberhaltiger Abfälle in Der Textilindustrie - Massenflüsse Und Behandlungsverfahren, 2011 | H10: 2 | I10: 2 | J10: 3 | K10: 3 | L10: 3 | M10: 2 | P10: Clothing consumption | Q10: Flow
A11: Clothing manufacturing | B11: Pre-consumer textile recycling | C11: any | D11: any | E11: 0.2 | F11: 2 | G11: Draft Product Environmental Footprint Category Rules (PEFCR) Apparel and Footwear, 2021 | H11: 2 | I11: 2 | J11: 1 | K11: 3 | L11: 2 | M11: 1 | P11: Apparel accessories | Q11: Stock
A12: Clothing manufacturing | B12: Clothing consumption | C12: any | D12: any | E12: rest | F12: 1 | P12: Boots | Q12: Stock
P13: Closed-toed shoes | Q13: Stock
P14: Dresses, skirts and jumpsuits | Q14: Stock
P15: Jackets & coats | Q15: Stock
P16: Leggings, stockings, tights and socks | Q16: Stock
P17: Open-toed shoes | Q17: Stock
P18: Pants & shorts | Q18: Stock
P19: Shirts & blouses | Q19: Stock
A20: Clothing consumption | B20: Apparel accessories | C20: NL | D20: Acryl | E20: 0.17880344 | F20: 1 | G20: https://eeb.org/library/draft-product-environmental-footprint-category-rules-pefcr-apparel-and-footwear/ | H20: 2 | J20: 2 | K20: 1 | L20: 2 | M20: 3 | P20: Sweaters & midlayers | Q20: Stock
A21: Clothing consumption | B21: Apparel accessories | C21: NL | D21: OTHER | E21: 0 | F21: 1 | G21: https://eeb.org/library/draft-product-environmental-footprint-category-rules-pefcr-apparel-and-footwear/ | H21: 2 | J21: 2 | K21: 1 | L21: 2 | M21: 3 | P21: Swimwear | Q21: Stock
A22: Clothing consumption | B22: Apparel accessories | C22: NL | D22: PA | E22: 0.019180867 | F22: 1 | G22: https://eeb.org/library/draft-product-environmental-footprint-category-rules-pefcr-apparel-and-footwear/ | H22: 2 | J22: 2 | K22: 1 | L22: 2 | M22: 3 | P22: T-shirts | Q22: Stock
A23: Clothing consumption | B23: Apparel accessories | C23: NL | D23: PET | E23: 0.030840249 | F23: 1 | G23: https://eeb.org/library/draft-product-environmental-footprint-category-rules-pefcr-apparel-and-footwear/ | H23: 2 | J23: 2 | K23: 1 | L23: 2 | M23: 3 | P23: Underwear | Q23: Stock
A24: Clothing consumption | B24: Boots | C24: NL | D24: OTHER | E24: 0 | F24: 1 | G24: https://eeb.org/library/draft-product-environmental-footprint-category-rules-pefcr-apparel-and-footwear/ | H24: 2 | J24: 2 | K24: 1 | L24: 2 | M24: 3 | O24: Previously "Textile recycling" | P24: Post-consumer textile recycling | Q24: Flow
A25: Clothing consumption | B25: Boots | C25: NL | D25: PA | E25: 0.036350166 | F25: 1 | G25: https://eeb.org/library/draft-product-environmental-footprint-category-rules-pefcr-apparel-and-footwear/ | H25: 2 | J25: 2 | K25: 1 | L25: 2 | M25: 3
